Workbook

Sheet Guideline
A1: Guideline to make and understand Unit Test Case
A3: 1. Overview
A4: - In the template, Unit test cases are based on functions. Each sheet presents test cases for one function.
A5: - Cover: General information of the project and Unit Test cases
A6: - FunctionList: The list of Classes and Functions in the document. + To control that the number of Unit TC meets customer's requirement or the norm, user should fill value for 'Normal number of Test cases/KLOC'.
A7: + Click on Function link to open the related Test cases of the function. Note: You should create new Function sheet before creating the link
A8: - Test Report: provive the overview results of Functions Unit test: Test coverage, Test successful coverage (Summary, for normal/abnormal/boundary cases)
A9: Note: Should check the formula of "Sub Total" if you add more functions
A11: 2. Content in Test function sheet
A12: 2.1 Combination of test cases.
A13: - To verify that number of Unit TC meets customer's requirement or not. User has to fill number LOC of tested function and fill value of 'Normal number test cases/KLOC' item in FunctionList sheet, which is required by customer or normal value. The number of lacked TC is shown in 'Lack of test cases' item.
A14: - If the number of Unit TC does not meet the requirement, creator should explain the reasons.
... A47: - Test requirement: Brief description about requirements which are tested in this function, it is not mandatory.

Sheet Cover
B2: UNIT TEST DOCUMENT
A4: Project Name | B4: AlumNect - FPT University Alumni Network & Career Platform | E4: Creator | F4: AnNH
A5: Project Code | B5: ALUMNECT | E5: Issue Date | F5: 46310
A6: Document Code | B6: =B5&"_"&"UnitTest"&"_"&"v1.5" -> ALUMNECT_UnitTest_v1.5 | E6: Version | F6: v1.5
A9: Record of change
A10: Effective Date | B10: Version | C10: Change Item | D10: *A,D,M | E10: Change description | F10: Reference
A11: 46297 | B11: v1.0 | C11: All document | D11: A | E11: Create document and execute 600 unit test cases of 40 modules | F11: Report3_SRS, Report4_SDD, Report5_Test_Report
A12: 46301 | B12: v1.1 | C12: Add modules | D12: A | E12: Add 319 unit test cases of 24 new modules (FE-41 to FE-64): Group Chat, Community Groups, Mentoring, Admin Mentoring & Finance | F12: Report3_SRS, Report4_SDD, Report5_Test_Report
A13: 46301 | B13: v1.2 | C13: Executed By / Date | D13: M | E13: Assign Executed By (HuyLTN, MinhVB, AnNH, TrietNH, HieuPT) evenly for FE-01 to FE-64 and align Executed Date with Report5_Test_Report | F13: Report3_SRS, Report4_SDD, Report5_Test_Report
A14: 46306 | B14: v1.3 | C14: Group Chat & Community Groups | D14: M | E14: HuyLTN reviews unit test cases of FE-41 to FE-48 (validation limits, role checks, status rules) | F14: Report3_SRS, Report4_SDD, Report5_Test_Report
A15: 46310 | B15: v1.4 | C15: Mentoring | D15: M | E15: TrietNH reviews unit test cases of FE-49 to FE-58 (registration, plans, requests, deals, payment, work logs, completion) | F15: Report3_SRS, Report4_SDD, Report5_Test_Report
A16: 46310 | B16: v1.5 | C16: Admin Mentoring & Statistics | D16: M | E16: HieuPT reviews FE-59 to FE-64 (tickets, disputes, ledgers, revenue); MinhVB verifies Functions list and Statistics | F16: Report3_SRS, Report4_SDD, Report5_Test_Report

Sheet Functions
E2: Function List
A4: Project Name | E4: AlumNect - FPT University Alumni Network & Career Platform
A5: Project Code | E5: ALUMNECT
A6: Normal number of Test cases/KLOC | E6: N/A
A7: Test Environment Setup Description | E7: 1. Language / build: Java 21 (compiled and run with JDK 22), Maven 3.9.9, Spring Boot 4.0.6 2. Test framework: JUnit 5 (Jupiter) + Mockito (spring-boot-starter-test), Hibernate Validator for DTO rules 3. Scope: back-end service layer (alumnect-backend); repositories, mailer, WebSocket and external services are mocked, so no database/server is required 4. Command: mvn test -Dtest="FE*" (source: src/test/java/com/alumnect/alumnect_backend/unit)
A10: No | B10: Requirement Name | C10: Class Name | D10: Function Name | E10: Function Code(Optional) | F10: Sheet Name | G10: Description | H10: Pre-Condition
A11: 1 | B11: Register a New Account | C11: AuthServiceImpl | D11: register() | E11: FE-01 | F11: FE-01
A12: 2 | B12: Register a New Account (email OTP activation) | C12: AuthServiceImpl | D12: verifyEmail() | E12: FE-01 | F12: FE-01
A13: 3 | B13: Register a New Account (resend OTP) | C13: AuthServiceImpl | D13: resendOtp() | E13: FE-01 | F13: FE-01
A14: 4 | B14: Sign In (Email & Password) | C14: AuthServiceImpl | D14: login() | E14: FE-02 | F14: FE-02
A15: 5 | B15: Sign In (Refresh session) | C15: AuthServiceImpl | D15: refresh() | E15: FE-02 | F15: FE-02
A16: 6 | B16: Logout | C16: AuthServiceImpl | D16: logout() | E16: FE-02 | F16: FE-02
A17: 7 | B17: Logout (all devices) | C17: AuthServiceImpl | D17: logoutAllDevices() | E17: FE-02 | F17: FE-02
A18: 8 | B18: Sign In with Google (OAuth 2.0) | C18: AuthServiceImpl | D18: loginWithGoogle() | E18: FE-03 | F18: FE-03
A19: 9 | B19: Sign In with Google (register new account) | C19: AuthServiceImpl | D19: registerWithGoogle() | E19: FE-03 | F19: FE-03
A20: 10 | B20: Forgot Password (request OTP) | C20: AuthServiceImpl | D20: forgotPassword() | E20: FE-04 | F20: FE-04
A21: 11 | B21: Forgot Password (verify OTP) | C21: AuthServiceImpl | D21: verifyResetOtp() | E21: FE-04 | F21: FE-04
A22: 12 | B22: Forgot Password (reset password) | C22: AuthServiceImpl | D22: resetPassword() | E22: FE-04 | F22: FE-04
... A228: 218 | B228: Admin Revenue Overview | C228: AdminRevenueServiceImpl | D228: getOverview() | E228: FE-64 | F228: FE-64

Sheet Statistics
A2: UNIT TEST REPORT
A4: Project Name | B4: AlumNect - FPT University Alumni Network & Career Platform | D4: Creator | F4: AnNH
A5: Project Code | B5: ALUMNECT | D5: Reviewer/Approver | F5: All Member
A6: Document Code | B6: =B5&"_"&"UnitTest"&"_"&"v1.1" -> ALUMNECT_UnitTest_v1.1 | D6: Issue Date | F6: 46310
A7: Notes | B7: The function is required to perform correctly based on SRS
A11: No | B11: Function code | C11: Passed | D11: Failed | E11: Untested | F11: N | G11: A | H11: B | I11: Total Test Cases
A12: 1 | B12: FE-01_Register a New Account | C12: ='FE-01'!A7 -> 23 | D12: ='FE-01'!C7 -> 0 | E12: ='FE-01'!F7 -> 0 | F12: ='FE-01'!L7 -> 5 | H12: ='FE-01'!N7 -> 5 | I12: ='FE-01'!O7 -> 23
A13: 2 | B13: FE-02_Sign In & Logout (Email & Password) | C13: ='FE-02'!A7 -> 14 | D13: ='FE-02'!C7 -> 0 | E13: ='FE-02'!F7 -> 0 | F13: ='FE-02'!L7 -> 4 | G13: ='FE-02'!M7 -> 10 | H13: ='FE-02'!N7 -> 0 | I13: ='FE-02'!O7 -> 14
A14: 3 | B14: FE-03_Sign In with Google (OAuth) | C14: ='FE-03'!A7 -> 8 | D14: ='FE-03'!C7 -> 0 | E14: ='FE-03'!F7 -> 0 | F14: ='FE-03'!L7 -> 3 | G14: ='FE-03'!M7 -> 5 | H14: ='FE-03'!N7 -> 0 | I14: ='FE-03'!O7 -> 8
A15: 4 | B15: FE-04_Manage Password (Change / Forgot ) | C15: ='FE-04'!A7 -> 24 | D15: ='FE-04'!C7 -> 0 | E15: ='FE-04'!F7 -> 0 | F15: ='FE-04'!L7 -> 4 | G15: ='FE-04'!M7 -> 14 | H15: ='FE-04'!N7 -> 6 | I15: ='FE-04'!O7 -> 24
A16: 5 | B16: FE-05_View User Profile | C16: ='FE-05'!A7 -> 7 | D16: ='FE-05'!C7 -> 0 | E16: ='FE-05'!F7 -> 0 | F16: ='FE-05'!L7 -> 3 | G16: ='FE-05'!M7 -> 4 | H16: ='FE-05'!N7 -> 0 | I16: ='FE-05'!O7 -> 7
A17: 6 | B17: FE-06_Edit Profile & Manage Skills | C17: ='FE-06'!A7 -> 4 | D17: ='FE-06'!C7 -> 0 | E17: ='FE-06'!F7 -> 0 | F17: ='FE-06'!L7 -> 2 | G17: ='FE-06'!M7 -> 1 | H17: ='FE-06'!N7 -> 1 | I17: ='FE-06'!O7 -> 4
A18: 7 | B18: FE-07_Manage Career Timeline | C18: ='FE-07'!A7 -> 19 | D18: ='FE-07'!C7 -> 0 | E18: ='FE-07'!F7 -> 0 | F18: ='FE-07'!L7 -> 6 | G18: ='FE-07'!M7 -> 8 | H18: ='FE-07'!N7 -> 5 | I18: ='FE-07'!O7 -> 19
A19: 8 | B19: FE-08_Search Users & Alumni Directory | C19: ='FE-08'!A7 -> 11 | D19: ='FE-08'!C7 -> 0 | E19: ='FE-08'!F7 -> 0 | F19: ='FE-08'!L7 -> 9 | G19: ='FE-08'!M7 -> 0 | H19: ='FE-08'!N7 -> 2 | I19: ='FE-08'!O7 -> 11
A20: 9 | B20: FE-09_View Connection Suggestions | C20: ='FE-09'!A7 -> 13 | D20: ='FE-09'!C7 -> 0 | E20: ='FE-09'!F7 -> 0 | F20: ='FE-09'!L7 -> 8 | G20: ='FE-09'!M7 -> 1 | H20: ='FE-09'!N7 -> 4 | I20: ='FE-09'!O7 -> 13
A21: 10 | B21: FE-10_Manage Social Connections (Follow / Followers / Following) | C21: ='FE-10'!A7 -> 17 | D21: ='FE-10'!C7 -> 0 | E21: ='FE-10'!F7 -> 0 | F21: ='FE-10'!L7 -> 5 | G21: ='FE-10'!M7 -> 11 | H21: ='FE-10'!N7 -> 1 | I21: ='FE-10'!O7 -> 17
A22: 11 | B22: FE-11_Admin Console Shell, Access Control & Navigation | C22: ='FE-11'!A7 -> 22 | D22: ='FE-11'!C7 -> 0 | E22: ='FE-11'!F7 -> 0 | F22: ='FE-11'!L7 -> 9 | G22: ='FE-11'!M7 -> 11 | H22: ='FE-11'!N7 -> 2 | I22: ='FE-11'!O7 -> 22
A23: 12 | B23: FE-12_Admin Overview Dashboard & Operations | C23: ='FE-12'!A7 -> 9 | D23: ='FE-12'!C7 -> 0 | E23: ='FE-12'!F7 -> 0 | F23: ='FE-12'!L7 -> 5 | G23: ='FE-12'!M7 -> 0 | H23: ='FE-12'!N7 -> 4 | I23: ='FE-12'!O7 -> 9
A24: 13 | B24: FE-13_User Account Management | C24: ='FE-13'!A7 -> 12 | D24: ='FE-13'!C7 -> 0 | E24: ='FE-13'!F7 -> 0 | F24: ='FE-13'!L7 -> 7 | G24: ='FE-13'!M7 -> 4 | H24: ='FE-13'!N7 -> 1 | I24: ='FE-13'!O7 -> 12
A25: 14 | B25: FE-14_View & Filter Community Posts | C25: ='FE-14'!A7 -> 4 | D25: ='FE-14'!C7 -> 0 | E25: ='FE-14'!F7 -> 0 | F25: ='FE-14'!L7 -> 3 | G25: ='FE-14'!M7 -> 0 | H25: ='FE-14'!N7 -> 1 | I25: ='FE-14'!O7 -> 4
A26: 15 | B26: FE-15_View Community Post Detail | C26: ='FE-15'!A7 -> 3 | D26: ='FE-15'!C7 -> 0 | E26: ='FE-15'!F7 -> 0 | F26: ='FE-15'!L7 -> 2 | G26: ='FE-15'!M7 -> 1 | H26: ='FE-15'!N7 -> 0 | I26: ='FE-15'!O7 -> 3
A27: 16 | B27: FE-16_Hide / Unhide Violating Posts | C27: ='FE-16'!A7 -> 4 | D27: ='FE-16'!C7 -> 0 | E27: ='FE-16'!F7 -> 0 | F27: ='FE-16'!L7 -> 2 | G27: ='FE-16'!M7 -> 2 | H27: ='FE-16'!N7 -> 0 | I27: ='FE-16'!O7 -> 4
A28: 17 | B28: FE-17_Alumni Verification Management Queue | C28: ='FE-17'!A7 -> 12 | D28: ='FE-17'!C7 -> 0 | E28: ='FE-17'!F7 -> 0 | F28: ='FE-17'!L7 -> 5 | G28: ='FE-17'!M7 -> 5 | H28: ='FE-17'!N7 -> 2 | I28: ='FE-17'!O7 -> 12
A29: 18 | B29: FE-18_Violation Reports & Content Moderation Queue | C29: ='FE-18'!A7 -> 7 | D29: ='FE-18'!C7 -> 0 | E29: ='FE-18'!F7 -> 0 | F29: ='FE-18'!L7 -> 4 | G29: ='FE-18'!M7 -> 3 | H29: ='FE-18'!N7 -> 0 | I29: ='FE-18'!O7 -> 7
A30: 19 | B30: FE-19_Broadcast & System Notifications Management | C30: ='FE-19'!A7 -> 29 | D30: ='FE-19'!C7 -> 0 | E30: ='FE-19'!F7 -> 0 | F30: ='FE-19'!L7 -> 13 | G30: ='FE-19'!M7 -> 12 | H30: ='FE-19'!N7 -> 4 | I30: ='FE-19'!O7 -> 29
A31: 20 | B31: FE-20_Create a Post on the Feed | C31: ='FE-20'!A7 -> 17 | D31: ='FE-20'!C7 -> 0 | E31: ='FE-20'!F7 -> 0 | F31: ='FE-20'!L7 -> 6 | G31: ='FE-20'!M7 -> 7 | H31: ='FE-20'!N7 -> 4 | I31: ='FE-20'!O7 -> 17
A32: 21 | B32: FE-21_View Feed & Post Detail | C32: ='FE-21'!A7 -> 13 | D32: ='FE-21'!C7 -> 0 | E32: ='FE-21'!F7 -> 0 | F32: ='FE-21'!L7 -> 6 | G32: ='FE-21'!M7 -> 4 | H32: ='FE-21'!N7 -> 3 | I32: ='FE-21'!O7 -> 13
A33: 22 | B33: FE-22_Edit a Post | C33: ='FE-22'!A7 -> 8 | D33: ='FE-22'!C7 -> 0 | E33: ='FE-22'!F7 -> 0 | F33: ='FE-22'!L7 -> 3 | G33: ='FE-22'!M7 -> 3 | H33: ='FE-22'!N7 -> 2 | I33: ='FE-22'!O7 -> 8
A34: 23 | B34: FE-23_Like & Report a Post | C34: ='FE-23'!A7 -> 17 | D34: ='FE-23'!C7 -> 0 | E34: ='FE-23'!F7 -> 0 | F34: ='FE-23'!L7 -> 5 | G34: ='FE-23'!M7 -> 7 | H34: ='FE-23'!N7 -> 5 | I34: ='FE-23'!O7 -> 17
A35: 24 | B35: FE-24_Comment on a Post | C35: ='FE-24'!A7 -> 18 | D35: ='FE-24'!C7 -> 0 | E35: ='FE-24'!F7 -> 0 | F35: ='FE-24'!L7 -> 5 | G35: ='FE-24'!M7 -> 8 | H35: ='FE-24'!N7 -> 5 | I35: ='FE-24'!O7 -> 18
A36: 25 | B36: FE-25_Bookmark Posts (Save / View Saved) | C36: ='FE-25'!A7 -> 5 | D36: ='FE-25'!C7 -> 0 | E36: ='FE-25'!F7 -> 0 | F36: ='FE-25'!L7 -> 4 | G36: ='FE-25'!M7 -> 1 | H36: ='FE-25'!N7 -> 0 | I36: ='FE-25'!O7 -> 5
A37: 26 | B37: FE-26_Event Attendance & RSVP Management | C37: ='FE-26'!A7 -> 29 | D37: ='FE-26'!C7 -> 0 | E37: ='FE-26'!F7 -> 0 | F37: ='FE-26'!L7 -> 11 | G37: ='FE-26'!M7 -> 11 | H37: ='FE-26'!N7 -> 7 | I37: ='FE-26'!O7 -> 29
A38: 27 | B38: FE-27_Event Lifecycle & Attendance History | C38: ='FE-27'!A7 -> 21 | D38: ='FE-27'!C7 -> 0 | E38: ='FE-27'!F7 -> 0 | F38: ='FE-27'!L7 -> 10 | G38: ='FE-27'!M7 -> 7 | H38: ='FE-27'!N7 -> 4 | I38: ='FE-27'!O7 -> 21
A39: 28 | B39: FE-28_Manage Notifications (View & Manage Notifications) | C39: ='FE-28'!A7 -> 28 | D39: ='FE-28'!C7 -> 0 | E39: ='FE-28'!F7 -> 0 | F39: ='FE-28'!L7 -> 13 | G39: ='FE-28'!M7 -> 5 | H39: ='FE-28'!N7 -> 10 | I39: ='FE-28'!O7 -> 28
A40: 29 | B40: FE-29_View Conversation List (Inbox) | C40: ='FE-29'!A7 -> 21 | D40: ='FE-29'!C7 -> 0 | E40: ='FE-29'!F7 -> 0 | F40: ='FE-29'!L7 -> 14 | G40: ='FE-29'!M7 -> 5 | H40: ='FE-29'!N7 -> 2 | I40: ='FE-29'!O7 -> 21
A41: 30 | B41: FE-30_Send a Direct Message & Chat History | C41: ='FE-30'!A7 -> 18 | D41: ='FE-30'!C7 -> 0 | E41: ='FE-30'!F7 -> 0 | F41: ='FE-30'!L7 -> 8 | G41: ='FE-30'!M7 -> 9 | H41: ='FE-30'!N7 -> 1 | I41: ='FE-30'!O7 -> 18
A42: 31 | B42: FE-31_Alumni Map (View, Filter & Profile Navigation) | C42: ='FE-31'!A7 -> 7 | D42: ='FE-31'!C7 -> 0 | E42: ='FE-31'!F7 -> 0 | F42: ='FE-31'!L7 -> 5 | G42: ='FE-31'!M7 -> 0 | H42: ='FE-31'!N7 -> 2 | I42: ='FE-31'!O7 -> 7
A43: 32 | B43: FE-32_Manage Career Path (View & Explore Alumni Career Journey) | C43: ='FE-32'!A7 -> 15 | D43: ='FE-32'!C7 -> 0 | E43: ='FE-32'!F7 -> 0 | F43: ='FE-32'!L7 -> 8 | G43: ='FE-32'!M7 -> 3 | H43: ='FE-32'!N7 -> 4 | I43: ='FE-32'!O7 -> 15
A44: 33 | B44: FE-33_Manage Posts (Share, Delete & Search Posts) | C44: ='FE-33'!A7 -> 16 | D44: ='FE-33'!C7 -> 0 | E44: ='FE-33'!F7 -> 0 | F44: ='FE-33'!L7 -> 8 | G44: ='FE-33'!M7 -> 5 | H44: ='FE-33'!N7 -> 3 | I44: ='FE-33'!O7 -> 16
A45: 34 | B45: FE-34_Forum Q&A - View, Search & Filter Questions | C45: ='FE-34'!A7 -> 17 | D45: ='FE-34'!C7 -> 0 | E45: ='FE-34'!F7 -> 0 | F45: ='FE-34'!L7 -> 10 | G45: ='FE-34'!M7 -> 3 | H45: ='FE-34'!N7 -> 4 | I45: ='FE-34'!O7 -> 17
A46: 35 | B46: FE-35_Forum Q&A - Create & Manage Questions | C46: ='FE-35'!A7 -> 21 | D46: ='FE-35'!C7 -> 0 | E46: ='FE-35'!F7 -> 0 | F46: ='FE-35'!L7 -> 5 | G46: ='FE-35'!M7 -> 11 | H46: ='FE-35'!N7 -> 5 | I46: ='FE-35'!O7 -> 21
A47: 36 | B47: FE-36_Forum Q&A - Answer & Manage Answers | C47: ='FE-36'!A7 -> 24 | D47: ='FE-36'!C7 -> 0 | E47: ='FE-36'!F7 -> 0 | F47: ='FE-36'!L7 -> 7 | G47: ='FE-36'!M7 -> 12 | H47: ='FE-36'!N7 -> 5 | I47: ='FE-36'!O7 -> 24
A48: 37 | B48: FE-37_Forum Q&A - Voting on Questions and Answers | C48: ='FE-37'!A7 -> 15 | D48: ='FE-37'!C7 -> 0 | E48: ='FE-37'!F7 -> 0 | F48: ='FE-37'!L7 -> 8 | G48: ='FE-37'!M7 -> 5 | H48: ='FE-37'!N7 -> 2 | I48: ='FE-37'!O7 -> 15
A49: 38 | B49: FE-38_Salary Board - Contribute & View Recent Data | C49: ='FE-38'!A7 -> 24 | D49: ='FE-38'!C7 -> 0 | E49: ='FE-38'!F7 -> 0 | F49: ='FE-38'!L7 -> 8 | G49: ='FE-38'!M7 -> 6 | H49: ='FE-38'!N7 -> 10 | I49: ='FE-38'!O7 -> 24
A50: 39 | B50: FE-39_Salary Board - Edit & Delete My Data | C50: ='FE-39'!A7 -> 8 | D50: ='FE-39'!C7 -> 0 | E50: ='FE-39'!F7 -> 0 | F50: ='FE-39'!L7 -> 3 | G50: ='FE-39'!M7 -> 5 | H50: ='FE-39'!N7 -> 0 | I50: ='FE-39'!O7 -> 8
A51: 40 | B51: FE-40_Salary Board - Statistics & Filter | C51: ='FE-40'!A7 -> 16 | D51: ='FE-40'!C7 -> 0 | E51: ='FE-40'!F7 -> 0 | F51: ='FE-40'!L7 -> 9 | G51: ='FE-40'!M7 -> 3 | H51: ='FE-40'!N7 -> 4 | I51: ='FE-40'!O7 -> 16
A52: 41 | B52: FE-41_Group Chat - Create & Update Group Profile | C52: ='FE-41'!A7 -> 10 | D52: ='FE-41'!C7 -> 0 | E52: ='FE-41'!F7 -> 0 | F52: ='FE-41'!L7 -> 3 | G52: ='FE-41'!M7 -> 5 | H52: ='FE-41'!N7 -> 2 | I52: ='FE-41'!O7 -> 10
A53: 42 | B53: FE-42_Group Chat - Manage Group Members | C53: ='FE-42'!A7 -> 12 | D53: ='FE-42'!C7 -> 0 | E53: ='FE-42'!F7 -> 0 | F53: ='FE-42'!L7 -> 7 | G53: ='FE-42'!M7 -> 5 | H53: ='FE-42'!N7 -> 0 | I53: ='FE-42'!O7 -> 12
A54: 43 | B54: FE-43_Community Groups - View, Search & Group Detail | C54: ='FE-43'!A7 -> 8 | D54: ='FE-43'!C7 -> 0 | E54: ='FE-43'!F7 -> 0 | F54: ='FE-43'!L7 -> 5 | G54: ='FE-43'!M7 -> 2 | H54: ='FE-43'!N7 -> 1 | I54: ='FE-43'!O7 -> 8
A55: 44 | B55: FE-44_Community Groups - Create, Update, Close/Reopen & Delete | C55: ='FE-44'!A7 -> 13 | D55: ='FE-44'!C7 -> 0 | E55: ='FE-44'!F7 -> 0 | F55: ='FE-44'!L7 -> 5 | G55: ='FE-44'!M7 -> 7 | H55: ='FE-44'!N7 -> 1 | I55: ='FE-44'!O7 -> 13
A56: 45 | B56: FE-45_Community Groups - Join, Leave & Handle Join Requests | C56: ='FE-45'!A7 -> 12 | D56: ='FE-45'!C7 -> 0 | E56: ='FE-45'!F7 -> 0 | F56: ='FE-45'!L7 -> 7 | G56: ='FE-45'!M7 -> 5 | H56: ='FE-45'!N7 -> 0 | I56: ='FE-45'!O7 -> 12
A57: 46 | B57: FE-46_Community Groups - Members & Roles | C57: ='FE-46'!A7 -> 9 | D57: ='FE-46'!C7 -> 0 | E57: ='FE-46'!F7 -> 0 | F57: ='FE-46'!L7 -> 5 | G57: ='FE-46'!M7 -> 4 | H57: ='FE-46'!N7 -> 0 | I57: ='FE-46'!O7 -> 9
A58: 47 | B58: FE-47_Community Groups - Manage Group Posts | C58: ='FE-47'!A7 -> 16 | D58: ='FE-47'!C7 -> 0 | E58: ='FE-47'!F7 -> 0 | F58: ='FE-47'!L7 -> 8 | G58: ='FE-47'!M7 -> 7 | H58: ='FE-47'!N7 -> 1 | I58: ='FE-47'!O7 -> 16
A59: 48 | B59: FE-48_Community Groups - Like & Comment on Group Posts | C59: ='FE-48'!A7 -> 13 | D59: ='FE-48'!C7 -> 0 | E59: ='FE-48'!F7 -> 0 | F59: ='FE-48'!L7 -> 8 | G59: ='FE-48'!M7 -> 4 | H59: ='FE-48'!N7 -> 1 | I59: ='FE-48'!O7 -> 13
A60: 49 | B60: FE-49_Mentoring - Terms & Mentor Registration | C60: ='FE-49'!A7 -> 13 | D60: ='FE-49'!C7 -> 0 | E60: ='FE-49'!F7 -> 0 | F60: ='FE-49'!L7 -> 9 | G60: ='FE-49'!M7 -> 3 | H60: ='FE-49'!N7 -> 1 | I60: ='FE-49'!O7 -> 13
A61: 50 | B61: FE-50_Mentoring - Mentor Plan Selection & Payment | C61: ='FE-50'!A7 -> 10 | D61: ='FE-50'!C7 -> 0 | E61: ='FE-50'!F7 -> 0 | F61: ='FE-50'!L7 -> 4 | G61: ='FE-50'!M7 -> 6 | H61: ='FE-50'!N7 -> 0 | I61: ='FE-50'!O7 -> 10
A62: 51 | B62: FE-51_Mentoring - Mentor & Subscription Status | C62: ='FE-51'!A7 -> 13 | D62: ='FE-51'!C7 -> 0 | E62: ='FE-51'!F7 -> 0 | F62: ='FE-51'!L7 -> 10 | G62: ='FE-51'!M7 -> 1 | H62: ='FE-51'!N7 -> 2 | I62: ='FE-51'!O7 -> 13
A63: 52 | B63: FE-52_Mentoring - Mentor Ranking, Search & Detail | C63: ='FE-52'!A7 -> 13 | D63: ='FE-52'!C7 -> 0 | E63: ='FE-52'!F7 -> 0 | F63: ='FE-52'!L7 -> 6 | G63: ='FE-52'!M7 -> 6 | H63: ='FE-52'!N7 -> 1 | I63: ='FE-52'!O7 -> 13
A64: 53 | B64: FE-53_Mentoring - Create Mentoring Request & Direct Request | C64: ='FE-53'!A7 -> 17 | D64: ='FE-53'!C7 -> 0 | E64: ='FE-53'!F7 -> 0 | F64: ='FE-53'!L7 -> 3 | G64: ='FE-53'!M7 -> 13 | H64: ='FE-53'!N7 -> 1 | I64: ='FE-53'!O7 -> 17
A65: 54 | B65: FE-54_Mentoring - View Responses & Respond to Requests | C65: ='FE-54'!A7 -> 15 | D65: ='FE-54'!C7 -> 0 | E65: ='FE-54'!F7 -> 0 | F65: ='FE-54'!L7 -> 6 | G65: ='FE-54'!M7 -> 9 | H65: ='FE-54'!N7 -> 0 | I65: ='FE-54'!O7 -> 15
A66: 55 | B66: FE-55_Mentoring - Negotiate & Confirm a Mentoring Deal | C66: ='FE-55'!A7 -> 17 | D66: ='FE-55'!C7 -> 0 | E66: ='FE-55'!F7 -> 0 | F66: ='FE-55'!L7 -> 5 | G66: ='FE-55'!M7 -> 11 | H66: ='FE-55'!N7 -> 1 | I66: ='FE-55'!O7 -> 17
A67: 56 | B67: FE-56_Mentoring - Pay for a Mentoring Task | C67: ='FE-56'!A7 -> 13 | D67: ='FE-56'!C7 -> 0 | E67: ='FE-56'!F7 -> 0 | F67: ='FE-56'!L7 -> 6 | G67: ='FE-56'!M7 -> 7 | H67: ='FE-56'!N7 -> 0 | I67: ='FE-56'!O7 -> 13
A68: 57 | B68: FE-57_Mentoring - Manage Tasks & Work Logs | C68: ='FE-57'!A7 -> 16 | D68: ='FE-57'!C7 -> 0 | E68: ='FE-57'!F7 -> 0 | F68: ='FE-57'!L7 -> 6 | G68: ='FE-57'!M7 -> 9 | H68: ='FE-57'!N7 -> 1 | I68: ='FE-57'!O7 -> 16
A69: 58 | B69: FE-58_Mentoring - Task Extension, Amendment & Completion | C69: ='FE-58'!A7 -> 23 | D69: ='FE-58'!C7 -> 0 | E69: ='FE-58'!F7 -> 0 | F69: ='FE-58'!L7 -> 10 | G69: ='FE-58'!M7 -> 12 | H69: ='FE-58'!N7 -> 1 | I69: ='FE-58'!O7 -> 23
A70: 59 | B70: FE-59_Mentoring - Settlement Ticket & Dispute Ticket | C70: ='FE-59'!A7 -> 13 | D70: ='FE-59'!C7 -> 0 | E70: ='FE-59'!F7 -> 0 | F70: ='FE-59'!L7 -> 4 | G70: ='FE-59'!M7 -> 9 | H70: ='FE-59'!N7 -> 0 | I70: ='FE-59'!O7 -> 13
A71: 60 | B71: FE-60_Mentoring - Task Result, Payment Report & Reviews | C71: ='FE-60'!A7 -> 13 | D71: ='FE-60'!C7 -> 0 | E71: ='FE-60'!F7 -> 0 | F71: ='FE-60'!L7 -> 7 | G71: ='FE-60'!M7 -> 5 | H71: ='FE-60'!N7 -> 1 | I71: ='FE-60'!O7 -> 13
A72: 61 | B72: FE-61_Mentoring - Group Mentorship | C72: ='FE-61'!A7 -> 18 | D72: ='FE-61'!C7 -> 0 | E72: ='FE-61'!F7 -> 0 | F72: ='FE-61'!L7 -> 6 | G72: ='FE-61'!M7 -> 12 | H72: ='FE-61'!N7 -> 0 | I72: ='FE-61'!O7 -> 18
A73: 62 | B73: FE-62_Admin Mentoring - Dispute Ticket Queue, Evidence & Discussion | C73: ='FE-62'!A7 -> 12 | D73: ='FE-62'!C7 -> 0 | E73: ='FE-62'!F7 -> 0 | F73: ='FE-62'!L7 -> 7 | G73: ='FE-62'!M7 -> 5 | H73: ='FE-62'!N7 -> 0 | I73: ='FE-62'!O7 -> 12
A74: 63 | B74: FE-63_Admin Mentoring - Resolve Ticket & Financial Ledgers | C74: ='FE-63'!A7 -> 11 | D74: ='FE-63'!C7 -> 0 | E74: ='FE-63'!F7 -> 0 | F74: ='FE-63'!L7 -> 6 | G74: ='FE-63'!M7 -> 5 | H74: ='FE-63'!N7 -> 0 | I74: ='FE-63'!O7 -> 11
A75: 64 | B75: FE-64_Admin Mentoring - Mentors, CV, Plans & Revenue | C75: ='FE-64'!A7 -> 9 | D75: ='FE-64'!C7 -> 0 | E75: ='FE-64'!F7 -> 0 | F75: ='FE-64'!L7 -> 5 | G75: ='FE-64'!M7 -> 3 | H75: ='FE-64'!N7 -> 1 | I75: ='FE-64'!O7 -> 9
B78: Sub total | C78: =SUM(C12:C75) -> 919 | D78: =SUM(D12:D75) -> 0 | E78: =SUM(E12:E75) -> 0 | F78: =SUM(F12:F75) -> 403 | G78: =SUM(G12:G75) -> 367 | H78: =SUM(H12:H75) -> 136 | I78: =SUM(I12:I75) -> 919
B80: Test coverage | D80: =IFERROR((C78+D78)/I78,0) -> 1
B81: Test successful coverage | D81: =IFERROR(C78/I78,0) -> 1
B82: Normal case | D82: =IFERROR(F78/I78,0) -> 0.43852013
B83: Abnormal case | D83: =IFERROR(G78/I78,0) -> 0.39934712
B84: Boundary case | D84: =IFERROR(H78/I78,0) -> 0.14798694

Sheet FE-01
A2: Function Code | C2: FE-01 | F2: Function Name | L2: FE-01_Register a New Account
A3: Created By | C3: AnNH | F3: Executed By | L3: HuyLTN
A4: Lines of code | C4: 224 | F4: Lack of test cases | L4: =IF(Functions!E6<>"N/A",SUM(C4*Functions!E6/1000,-O7),"N/A") -> N/A
A5: Test requirement | C5: Register account with email OTP activation and OTP resend
A6: Passed | C6: Failed | F6: Untested | L6: N/A/B | O6: Total Test Cases
A7: =COUNTIF(F89:AB89,"P") -> 23 | C7: =COUNTIF(F89:AB89,"F") -> 0 | F7: =SUM(O7,-A7,-C7) -> 0 | L7: =COUNTIF(F88:AB88,"N") -> 5 | M7: =COUNTIF(F88:AB88,"A") -> 13 | N7: =COUNTIF(F88:AB88,"B") -> 5 | O7: =COUNTA(F9:AB9) -> 23
F9: UTCID01 | G9: UTCID02 | H9: UTCID03 | I9: UTCID04 | J9: UTCID05 | K9: UTCID06 | L9: UTCID07 | M9: UTCID08 | N9: UTCID09 | O9: UTCID10 | P9: UTCID11 | Q9: UTCID12 | R9: UTCID13 | S9: UTCID14 | T9: UTCID15 | U9: UTCID16 | V9: UTCID17 | W9: UTCID18 | X9: UTCID19 | Y9: UTCID20 | Z9: UTCID21 | AA9: UTCID22 | AB9: UTCID23
A10: Condition | B10: Precondition
D11: Email is not registered | F11: O | G11: O | J11: O | K11: O | L11: O | M11: O
D12: Student code is not used | F12: O
D13: Role STUDENT and major id 1 exist | F13: O
D14: Role ALUMNI, proofUrl is provided | G14: O
D15: Email already belongs to an ACTIVE account | H15: O
D16: Email belongs to an account in WAITING_APPROVAL status | I16: O
D17: Student code is already used by another profile | J17: O
D18: Role ALUMNI but proofUrl is blank | L18: O
D19: Major id 99 does not exist | M19: O
D20: Account exists with status PENDING (registered but email not verified yet) | N20: O
D21: Validator is applied to RegisterRequest | O21: O | P21: O | Q21: O | R21: O
D22: Account PENDING with role STUDENT | S22: O
D23: Latest EMAIL_VERIFICATION OTP is unused, not expired | S23: O
D24: Account PENDING with role ALUMNI | T24: O
D25: Latest OTP is valid | T25: O
D26: Latest OTP is valid, failedAttempts = 0 | U26: O
D27: Latest OTP has failedAttempts = 4 (one attempt left) | V27: O
D28: Latest OTP already has failedAttempts = 5 (locked) | W28: O
D29: Latest OTP expired 1 minute ago | X29: O
D30: No account exists for the email | Y30: O
D31: Account not yet email-verified | Z31: O | AA31: O
D32: Last OTP was created just now (< 5 minutes ago) | Z32: O
D33: Last OTP was created 6 minutes ago (cool-down of 5 minutes elapsed) | AA33: O
D34: Account email is already verified | AB34: O
B35: Input
D36: RegisterRequest(role=STUDENT, password=Passw0rd1, email with spaces/upper-case) | F36: O
D37: RegisterRequest(role=ALUMNI, proofUrl=https://cdn/proof.png) | G37: O
D38: RegisterRequest(email of the ACTIVE account) | H38: O
D39: RegisterRequest(email of the WAITING_APPROVAL account) | I39: O
D40: RegisterRequest(studentCode=DE180001) | J40: O
D41: RegisterRequest(role=ADMIN) | K41: O
D42: RegisterRequest(role=ALUMNI, proofUrl="") | L42: O
D43: RegisterRequest(majorId=99) | M43: O
D44: RegisterRequest re-submitted for the same email | N44: O
D45: password length = 8 (lower bound, letters+digits) | O45: O
D46: password length = 7 (below lower bound) | P46: O
D47: password length = 101 (above upper bound) | Q47: O
D48: password = "abcdefgh" (letters only, no digit) | R48: O
D49: email, correct 6-digit OTP | S49: O | T49: O
D50: email, wrong OTP | U50: O
D51: email, wrong OTP (5th wrong attempt) | V51: O
D52: email, correct OTP | W52: O | X52: O
D53: unknown email, OTP 123456 | Y53: O
D54: email | Z54: O | AA54: O | AB54: O
A56: Confirm | B56: Return
D57: Void; User saved as PENDING with email trimmed + lower-cased and password BCrypt-hashed | F57: O
D58: UserProfile + default UserSettings saved | F58: O
D59: Void; VerificationRequest (alumni proof) saved for the new user | G59: O
D60: Void; existing account is reused (no new UserSettings), a new OTP is issued | N60: O
D61: No constraint violation | O61: O
D62: Returns "STUDENT"; account becomes ACTIVE, emailVerified = true, accountVerified = true | S62: O
D63: Returns "ALUMNI"; account becomes WAITING_APPROVAL, accountVerified = false | T63: O
D64: Void; old OTPs invalidated, new OTP saved | AA64: O
B65: Exception
D66: ConflictException: Email này đã được đăng ký và kích hoạt thành công. Vui lòng đăng nhập. | H66: O
D67: ConflictException: Tài khoản của bạn đã xác thực email thành công và đang chờ quản trị viên phê duyệt... | I67: O
D68: ConflictException: Mã số sinh viên này đã được đăng ký trong hệ thống. | J68: O
D69: BadRequestException: Vai trò không hợp lệ để đăng ký: ADMIN | K69: O
D70: BadRequestException: Ảnh minh chứng là bắt buộc khi đăng ký với vai trò Cựu sinh viên | L70: O
D71: ResourceNotFoundException: Chuyên ngành không tồn tại với ID: 99 | M71: O
D72: ConstraintViolation: Mật khẩu phải có độ dài từ 8 đến 100 ký tự | P72: O | Q72: O
D73: ConstraintViolation: Mật khẩu phải chứa ít nhất 1 chữ cái và 1 chữ số | R73: O
D74: BadRequestException: Mã xác thực không chính xác. Bạn còn 4 lần thử. | U74: O
D75: BadRequestException: Mã xác thực đã bị khóa do nhập sai quá 5 lần. Vui lòng yêu cầu gửi lại mã mới. | V75: O
D76: BadRequestException: Mã xác thực đã bị khóa do nhập sai quá 5 lần... | W76: O
D77: BadRequestException: Mã xác thực đã hết hạn | X77: O
D78: ResourceNotFoundException: Không tìm thấy tài khoản người dùng với email: ... | Y78: O
D79: BadRequestException: Vui lòng đợi ... trước khi yêu cầu gửi lại mã OTP mới. | Z79: O
D80: BadRequestException: Tài khoản này đã được xác thực email trước đó | AB80: O
B81: Log message
D82: Verification OTP email sent to student@fpt.edu.vn | F82: O
D83: Verification OTP email sent | G83: O
D84: Verification OTP email re-sent | N84: O
D85: Welcome notification sent | S85: O
D86: Verification OTP email sent with the profile full name | AA86: O
A88: Result | B88: Type(N : Normal, A : Abnormal, B : Boundary) | F88: N | G88: N | H88: A | I88: A | J88: A | K88: A | L88: A | M88: A | N88: N | O88: B | P88: B | Q88: B | R88: A | S88: N | T88: N | U88: A | V88: B | W88: A | X88: A | Y88: A | Z88: A | AA88: B | AB88: A
B89: Passed/Failed | F89: P | G89: P | H89: P | I89: P | J89: P | K89: P | L89: P | M89: P | N89: P | O89: P | P89: P | Q89: P | R89: P | S89: P | T89: P | U89: P | V89: P | W89: P | X89: P | Y89: P | Z89: P | AA89: P | AB89: P
B90: Executed Date | F90: 46206 | G90: 46206 | H90: 46206 | I90: 46206 | J90: 46206 | K90: 46206 | L90: 46206 | M90: 46206 | N90: 46206 | O90: 46206 | P90: 46206 | Q90: 46206 | R90: 46206 | S90: 46206 | T90: 46206 | U90: 46206 | V90: 46206 | W90: 46206 | X90: 46206 | Y90: 46206 | Z90: 46206 | AA90: 46206 | AB90: 46206
B91: Defect ID

Sheet FE-02
A2: Function Code | C2: FE-02 | F2: Function Name | L2: FE-02_Sign In & Logout (Email & Password)
A3: Created By | C3: AnNH | F3: Executed By | L3: MinhVB
A4: Lines of code | C4: 159 | F4: Lack of test cases | L4: =IF(Functions!E6<>"N/A",SUM(C4*Functions!E6/1000,-O7),"N/A") -> N/A
A5: Test requirement | C5: Email/password sign in, token refresh and logout
A6: Passed | C6: Failed | F6: Untested | L6: N/A/B | O6: Total Test Cases
A7: =COUNTIF(F65:T65,"P") -> 14 | C7: =COUNTIF(F65:T65,"F") -> 0 | F7: =SUM(O7,-A7,-C7) -> 0 | L7: =COUNTIF(F64:T64,"N") -> 4 | M7: =COUNTIF(F64:T64,"A") -> 10 | N7: =COUNTIF(F64:T64,"B") -> 0 | O7: =COUNTA(F9:T9) -> 14
F9: UTCID01 | G9: UTCID02 | H9: UTCID03 | I9: UTCID04 | J9: UTCID05 | K9: UTCID06 | L9: UTCID07 | M9: UTCID08 | N9: UTCID09 | O9: UTCID10 | P9: UTCID11 | Q9: UTCID12 | R9: UTCID13 | S9: UTCID14
A10: Condition | B10: Precondition
D11: ACTIVE account with verified email | F11: O
D12: Password matches the stored BCrypt hash | F12: O
D13: No account exists for the email | G13: O
D14: ACTIVE account exists | H14: O
D15: Password does not match the stored hash | H15: O
D16: Account status is LOCKED | I16: O
D17: Password is correct | I17: O
D18: Account status is WAITING_APPROVAL (alumni awaiting admin) | J18: O
D19: Email verified, password correct | J19: O
D20: Account exists but emailVerified = false | K20: O
D21: Password correct | K21: O
D22: Account was created through Google (passwordHash is null) | L22: O
D23: Refresh token JWT is well-formed | M23: O
D24: Stored hash exists, not revoked, not expired | M24: O
D25: Account is ACTIVE | M25: O
D26: Refresh token JWT cannot be parsed (tampered/expired signature) | N26: O
D27: Refresh token was already revoked (replay attack) | O27: O
D28: Stored refresh token expired 1 minute ago | P28: O
D29: Refresh token hash exists in database | Q29: O
D30: Refresh token hash does not exist in database | R30: O
D31: Account exists for the email | S31: O
B32: Input
D33: LoginRequest(email, password), userAgent, ipAddress | F33: O
D34: LoginRequest(unknown email, any password) | G34: O
D35: LoginRequest(email, wrong password) | H35: O
D36: LoginRequest(email, password) | I36: O | J36: O | K36: O | L36: O
D37: RefreshRequest(refreshToken), userAgent, ipAddress | M37: O
D38: RefreshRequest(refreshToken=garbage) | N38: O
D39: RefreshRequest(revoked refresh token) | O39: O
D40: RefreshRequest(expired refresh token) | P40: O
D41: LogoutRequest(refreshToken) | Q41: O
D42: LogoutRequest(unknown refreshToken) | R42: O
D43: email | S43: O
A45: Confirm | B45: Return
D46: LoginResponse with accessToken, refreshToken, id, email, role, fullName, accountStatus=ACTIVE | F46: O
D47: Refresh token (SHA-256 hashed) saved with 7-day expiry | F47: O
D48: New LoginResponse (new access + refresh token) | M48: O
D49: Old refresh token revoked (token rotation) | M49: O
D50: Void; refresh token row deleted (session terminated) | Q50: O
D51: Void; every refresh token of the user is deleted | S51: O
B52: Exception
D53: BadRequestException: Tài khoản hoặc mật khẩu không chính xác | G53: O | H53: O
D54: BadRequestException: Tài khoản của bạn đã bị khóa. Vui lòng liên hệ quản trị viên. | I54: O
D55: BadRequestException: Tài khoản của bạn đang chờ quản trị viên phê duyệt. Vui lòng đợi. | J55: O
D56: BadRequestException: Email của bạn chưa được xác thực. Vui lòng kiểm tra hòm thư để xác thực trước. | K56: O
D57: BadRequestException: Tài khoản này được đăng ký thông qua mạng xã hội khác | L57: O
D58: BadRequestException: Phiên đăng nhập đã hết hạn hoặc bị thu hồi vì lý do bảo mật. Vui lòng đăng nhập lại. | N58: O
D59: BadRequestException: Phiên đăng nhập đã hết hạn hoặc bị thu hồi vì lý do bảo mật... | O59: O | P59: O
D60: BadRequestException: Phiên đăng nhập không tồn tại hoặc đã hết hạn. | R60: O
B61: Log message
D62: All refresh tokens of the user are deleted (force logout on every device) | O62: O
A64: Result | B64: Type(N : Normal, A : Abnormal, B : Boundary) | F64: N | G64: A | H64: A | I64: A | J64: A | K64: A | L64: A | M64: N | N64: A | O64: A | P64: A | Q64: N | R64: A | S64: N
B65: Passed/Failed | F65: P | G65: P | H65: P | I65: P | J65: P | K65: P | L65: P | M65: P | N65: P | O65: P | P65: P | Q65: P | R65: P | S65: P
B66: Executed Date | F66: 46209 | G66: 46209 | H66: 46209 | I66: 46209 | J66: 46209 | K66: 46209 | L66: 46209 | M66: 46209 | N66: 46209 | O66: 46209 | P66: 46209 | Q66: 46209 | R66: 46209 | S66: 46209
B67: Defect ID

Sheet FE-03
A2: Function Code | C2: FE-03 | F2: Function Name | L2: FE-03_Sign In with Google (OAuth)
A3: Created By | C3: AnNH | F3: Executed By | L3: AnNH
A4: Lines of code | C4: 268 | F4: Lack of test cases | L4: =IF(Functions!E6<>"N/A",SUM(C4*Functions!E6/1000,-O7),"N/A") -> N/A
A5: Test requirement | C5: Google OAuth sign in and new account registration
A6: Passed | C6: Failed | F6: Untested | L6: N/A/B | O6: Total Test Cases
A7: =COUNTIF(F44:T44,"P") -> 8 | C7: =COUNTIF(F44:T44,"F") -> 0 | F7: =SUM(O7,-A7,-C7) -> 0 | L7: =COUNTIF(F43:T43,"N") -> 3 | M7: =COUNTIF(F43:T43,"A") -> 5 | N7: =COUNTIF(F43:T43,"B") -> 0 | O7: =COUNTA(F9:T9) -> 8
F9: UTCID01 | G9: UTCID02 | H9: UTCID03 | I9: UTCID04 | J9: UTCID05 | K9: UTCID06 | L9: UTCID07 | M9: UTCID08
A10: Condition | B10: Precondition
D11: Google token valid (aud matches, email_verified=true) | F11: O
D12: Google account already linked to an ACTIVE user | F12: O
D13: Google token valid | G13: O | K13: O | L13: O | M13: O
D14: Google account not linked and email is not registered | G14: O
D15: Google token audience (aud) differs from the configured client id | H15: O
D16: Google reports email_verified = false | I16: O
D17: Google tokeninfo call fails (network error / invalid token) | J17: O
D18: Email is not registered | K18: O | L18: O
D19: Role STUDENT, major exists, student code unused | K19: O
D20: Role ALUMNI with proofUrl | L20: O
D21: Email belongs to an ACTIVE account | M21: O
B22: Input
D23: GoogleLoginRequest(token) | F23: O | G23: O | I23: O | J23: O
D24: GoogleLoginRequest(token issued for another app) | H24: O
D25: GoogleRegisterRequest(role=STUDENT) | K25: O | M25: O
D26: GoogleRegisterRequest(role=ALUMNI, proofUrl) | L26: O
A28: Confirm | B28: Return
D29: LoginResponse with access + refresh tokens | F29: O
D30: lastLoginAt updated | F30: O
D31: LoginResponse with tokens; account ACTIVE, AuthProvider=GOOGLE, avatar taken from Google picture | K31: O
D32: OAuth link UserOAuthProvider saved | K32: O
D33: LoginResponse without tokens (null) and accountStatus=WAITING_APPROVAL | L33: O
D34: VerificationRequest saved | L34: O
B35: Exception
D36: GoogleUserNotFoundException: Tài khoản Google chưa được đăng ký trên hệ thống. (carries email, name, providerUserId) | G36: O
D37: BadRequestException: Token xác thực Google không khớp với Client ID của hệ thống | H37: O
D38: BadRequestException: Tài khoản Google này chưa được xác thực email | I38: O
D39: BadRequestException: Không thể xác thực tài khoản Google vào lúc này. Vui lòng thử lại sau. | J39: O
D40: ConflictException: Email này đã được đăng ký và kích hoạt thành công. Vui lòng đăng nhập. | M40: O
B41: Log message
A43: Result | B43: Type(N : Normal, A : Abnormal, B : Boundary) | F43: N | G43: A | H43: A | I43: A | J43: A | K43: N | L43: N | M43: A
B44: Passed/Failed | F44: P | G44: P | H44: P | I44: P | J44: P | K44: P | L44: P | M44: P
B45: Executed Date | F45: 46209 | G45: 46209 | H45: 46209 | I45: 46209 | J45: 46209 | K45: 46209 | L45: 46209 | M45: 46209
B46: Defect ID

Sheet FE-04
A2: Function Code | C2: FE-04 | F2: Function Name | L2: FE-04_Manage Password (Change / Forgot )
A3: Created By | C3: AnNH | F3: Executed By | L3: TrietNH
A4: Lines of code | C4: 101 | F4: Lack of test cases | L4: =IF(Functions!E6<>"N/A",SUM(C4*Functions!E6/1000,-O7),"N/A") -> N/A
A5: Test requirement | C5: Change password and recover forgotten password via OTP
A6: Passed | C6: Failed | F6: Untested | L6: N/A/B | O6: Total Test Cases
A7: =COUNTIF(F84:AC84,"P") -> 24 | C7: =COUNTIF(F84:AC84,"F") -> 0 | F7: =SUM(O7,-A7,-C7) -> 0 | L7: =COUNTIF(F83:AC83,"N") -> 4 | M7: =COUNTIF(F83:AC83,"A") -> 14 | N7: =COUNTIF(F83:AC83,"B") -> 6 | O7: =COUNTA(F9:AC9) -> 24
F9: UTCID01 | G9: UTCID02 | H9: UTCID03 | I9: UTCID04 | J9: UTCID05 | K9: UTCID06 | L9: UTCID07 | M9: UTCID08 | N9: UTCID09 | O9: UTCID10 | P9: UTCID11 | Q9: UTCID12 | R9: UTCID13 | S9: UTCID14 | T9: UTCID15 | U9: UTCID16 | V9: UTCID17 | W9: UTCID18 | X9: UTCID19 | Y9: UTCID20 | Z9: UTCID21 | AA9: UTCID22 | AB9: UTCID23 | AC9: UTCID24
A10: Condition | B10: Precondition
D11: ACTIVE account exists for the email | F11: O
D12: No previous PASSWORD_RESET OTP | F12: O
D13: No account exists for the email | G13: O
D14: Account status is LOCKED | H14: O
D15: Account status is PENDING (email not verified yet) | I15: O
D16: ACTIVE account | J16: O | K16: O
D17: Last PASSWORD_RESET OTP created just now (< 5 minutes) | J17: O
D18: Last PASSWORD_RESET OTP created 6 minutes ago (cool-down elapsed) | K18: O
D19: Latest PASSWORD_RESET OTP is unused, not expired, failedAttempts = 0 | L19: O
D20: Latest OTP valid, failedAttempts = 0 | M20: O
D21: Latest OTP expired | N21: O
D22: User never requested a reset (no PASSWORD_RESET OTP found) | O22: O
D23: Latest PASSWORD_RESET OTP valid | P23: O
D24: OTP was already used | Q24: O
D25: OTP valid | R25: O
D26: OTP has failedAttempts = 4 | S26: O
D27: Authenticated user with local password | T27: O
D28: Old password matches stored hash | T28: O | V28: O | W28: O
D29: Authenticated user exists | U29: O
D30: Old password does not match stored hash | U30: O
D31: Account was created through Google (passwordHash = null) | X31: O
D32: No account exists for the authenticated email | Y32: O
D33: Validator applied to ChangePasswordRequest | Z33: O | AA33: O
D34: Validator applied to ResetPasswordRequest | AB34: O | AC34: O
B35: Input
D36: ForgotPasswordRequest(email with spaces/upper-case) | F36: O
D37: ForgotPasswordRequest(unknown email) | G37: O
D38: ForgotPasswordRequest(email) | H38: O | I38: O | J38: O | K38: O
D39: VerifyResetOtpRequest(email, correct OTP) | L39: O
D40: VerifyResetOtpRequest(email, wrong OTP) | M40: O
D41: VerifyResetOtpRequest(email, OTP) | N41: O | O41: O
D42: ResetPasswordRequest(email, correct OTP, newPassword=NewPassw0rd) | P42: O
D43: ResetPasswordRequest(email, OTP, newPassword) | Q43: O
D44: ResetPasswordRequest(email, wrong OTP, newPassword) | R44: O
D45: ResetPasswordRequest(email, wrong OTP) - the 5th wrong attempt | S45: O
D46: email, ChangePasswordRequest(oldPassword, newPassword=NewPassw0rd, confirmNewPassword=NewPassw0rd) | T46: O
D47: ChangePasswordRequest(oldPassword=wrong, ...) | U47: O
D48: ChangePasswordRequest(oldPassword = newPassword = SamePassw0rd) | V48: O
D49: ChangePasswordRequest(newPassword != confirmNewPassword) | W49: O
D50: ChangePasswordRequest(...) | X50: O
D51: email, ChangePasswordRequest | Y51: O
D52: newPassword length = 8 with letters and digits | Z52: O
D53: newPassword length = 7 | AA53: O
D54: OTP token length = 6 | AB54: O
D55: OTP token length = 5 (below required 6 digits) | AC55: O
A57: Confirm | B57: Return
D58: Void; old OTPs invalidated, new 6-digit PASSWORD_RESET OTP saved (valid 5 minutes) | F58: O
D59: Void; a new OTP is created and e-mailed | K59: O
D60: Void; no exception and OTP stays unused so it can be used by resetPassword | L60: O
D61: Void; OTP marked used, password hash replaced by BCrypt hash of the new password | P61: O
D62: Void; password hash updated with the BCrypt hash of the new password | T62: O
D63: No constraint violation | Z63: O | AB63: O
B64: Exception
D65: ResourceNotFoundException: Không tìm thấy tài khoản người dùng với email: ... | G65: O | Y65: O
D66: BadRequestException: Tài khoản của bạn đã bị khóa. Vui lòng liên hệ quản trị viên. | H66: O
D67: BadRequestException: Tài khoản của bạn chưa được xác thực email... | I67: O
D68: BadRequestException: Vui lòng đợi ... trước khi yêu cầu gửi lại mã OTP mới. | J68: O
D69: BadRequestException: Mã xác thực không chính xác. Bạn còn 4 lần thử. | M69: O | R69: O
D70: BadRequestException: Mã xác thực đã hết hạn | N70: O
D71: ResourceNotFoundException: Không tìm thấy yêu cầu đặt lại mật khẩu nào cho tài khoản này | O71: O
D72: BadRequestException: Mã xác thực này đã được sử dụng trước đó | Q72: O
D73: BadRequestException: Mã xác thực đã bị khóa do nhập sai quá 5 lần. Vui lòng yêu cầu gửi lại mã mới. | S73: O
D74: BadRequestException: Mật khẩu hiện tại không chính xác. | U74: O | X74: O
D75: BadRequestException: Mật khẩu mới không được trùng với mật khẩu hiện tại. | V75: O
D76: BadRequestException: Xác nhận mật khẩu mới không trùng khớp. | W76: O
D77: ConstraintViolation: Mật khẩu mới phải có độ dài từ 8 đến 100 ký tự | AA77: O
D78: ConstraintViolation: Mã xác thực phải đúng 6 chữ số | AC78: O
B79: Log message
D80: Password reset email sent with the full name from profile | F80: O
D81: Password reset email sent (fallback name = email when profile is missing) | K81: O
A83: Result | B83: Type(N : Normal, A : Abnormal, B : Boundary) | F83: N | G83: A | H83: A | I83: A | J83: A | K83: B | L83: N | M83: A | N83: A | O83: A | P83: N | Q83: A | R83: A | S83: B | T83: N | U83: A | V83: A | W83: A | X83: A | Y83: A | Z83: B | AA83: B | AB83: B | AC83: B
B84: Passed/Failed | F84: P | G84: P | H84: P | I84: P | J84: P | K84: P | L84: P | M84: P | N84: P | O84: P | P84: P | Q84: P | R84: P | S84: P | T84: P | U84: P | V84: P | W84: P | X84: P | Y84: P | Z84: P | AA84: P | AB84: P | AC84: P
B85: Executed Date | F85: 46222 | G85: 46222 | H85: 46222 | I85: 46222 | J85: 46222 | K85: 46222 | L85: 46222 | M85: 46222 | N85: 46222 | O85: 46222 | P85: 46222 | Q85: 46222 | R85: 46222 | S85: 46222 | T85: 46222 | U85: 46222 | V85: 46222 | W85: 46222 | X85: 46222 | Y85: 46222 | Z85: 46222 | AA85: 46222 | AB85: 46222 | AC85: 46222
B86: Defect ID

Sheet FE-05
A2: Function Code | C2: FE-05 | F2: Function Name | L2: FE-05_View User Profile
A3: Created By | C3: AnNH | F3: Executed By | L3: HieuPT
A4: Lines of code | C4: 41 | F4: Lack of test cases | L4: =IF(Functions!E6<>"N/A",SUM(C4*Functions!E6/1000,-O7),"N/A") -> N/A
A5: Test requirement | C5: View own profile and public profiles of other members
A6: Passed | C6: Failed | F6: Untested | L6: N/A/B | O6: Total Test Cases
A7: =COUNTIF(F39:T39,"P") -> 7 | C7: =COUNTIF(F39:T39,"F") -> 0 | F7: =SUM(O7,-A7,-C7) -> 0 | L7: =COUNTIF(F38:T38,"N") -> 3 | M7: =COUNTIF(F38:T38,"A") -> 4 | N7: =COUNTIF(F38:T38,"B") -> 0 | O7: =COUNTA(F9:T9) -> 7
F9: UTCID01 | G9: UTCID02 | H9: UTCID03 | I9: UTCID04 | J9: UTCID05 | K9: UTCID06 | L9: UTCID07
A10: Condition | B10: Precondition
D11: Authenticated user with a profile | F11: O
D12: followers = 7, following = 3 | F12: O
D13: No account exists for the email | G13: O
D14: Account exists but has no profile row | H14: O
D15: Target user is ACTIVE | I15: O | J15: O
D16: Viewer is anonymous (no authentication) | I16: O
D17: Logged-in viewer already follows the target | J17: O
D18: Target user exists but account is LOCKED | K18: O
D19: No user with id 999 | L19: O
B20: Input
D21: email of the logged-in user | F21: O
D22: unknown email | G22: O
D23: email | H23: O
D24: userId = 10 | I24: O | J24: O | K24: O
D25: userId = 999 | L25: O
A27: Confirm | B27: Return
D28: UserProfileResponse with followersCount = 7, followingCount = 3, isFollowing = false | F28: O
D29: UserProfileResponse with isFollowing = false and follow counters | I29: O
D30: UserProfileResponse with isFollowing = true | J30: O
B31: Exception
D32: ResourceNotFoundException: Không tìm thấy tài khoản người dùng với email: ... | G32: O
D33: ResourceNotFoundException: Không tìm thấy hồ sơ cá nhân cho tài khoản: ... | H33: O
D34: BadRequestException: Tài khoản người dùng này chưa được kích hoạt hoặc đã bị khóa. | K34: O
D35: ResourceNotFoundException: Không tìm thấy tài khoản người dùng với ID: 999 | L35: O
B36: Log message
A38: Result | B38: Type(N : Normal, A : Abnormal, B : Boundary) | F38: N | G38: A | H38: A | I38: N | J38: N | K38: A | L38: A
B39: Passed/Failed | F39: P | G39: P | H39: P | I39: P | J39: P | K39: P | L39: P
B40: Executed Date | F40: 46213 | G40: 46213 | H40: 46213 | I40: 46213 | J40: 46213 | K40: 46213 | L40: 46213
B41: Defect ID

Sheet FE-06
A2: Function Code | C2: FE-06 | F2: Function Name | L2: FE-06_Edit Profile & Manage Skills
A3: Created By | C3: AnNH | F3: Executed By | L3: HuyLTN
A4: Lines of code | C4: 41 | F4: Lack of test cases | L4: =IF(Functions!E6<>"N/A",SUM(C4*Functions!E6/1000,-O7),"N/A") -> N/A
A5: Test requirement | C5: Edit profile, upload images and manage skills
A6: Passed | C6: Failed | F6: Untested | L6: N/A/B | O6: Total Test Cases
A7: =COUNTIF(F31:T31,"P") -> 4 | C7: =COUNTIF(F31:T31,"F") -> 0 | F7: =SUM(O7,-A7,-C7) -> 0 | L7: =COUNTIF(F30:T30,"N") -> 2 | M7: =COUNTIF(F30:T30,"A") -> 1 | N7: =COUNTIF(F30:T30,"B") -> 1 | O7: =COUNTA(F9:T9) -> 4
F9: UTCID01 | G9: UTCID02 | H9: UTCID03 | I9: UTCID04
A10: Condition | B10: Precondition
D11: Authenticated user with a profile | F11: O | G11: O
D12: Major id 1 exists | F12: O
D13: Major id 99 does not exist | H13: O
D14: Authenticated user with existing skills | I14: O
B15: Input
D16: UpdateProfileRequest(majorId=1, skills=[Java, React]) | F16: O
D17: UpdateProfileRequest(majorId = null, skills = null) | G17: O
D18: UpdateProfileRequest(majorId = 99) | H18: O
D19: UpdateProfileRequest(skills = [] empty list) | I19: O
A21: Confirm | B21: Return
D22: UserProfileResponse; profile saved with the major | F22: O
D23: Old skills deleted, 2 new UserSkill rows saved | F23: O
D24: Major cleared (null) and existing skills untouched | G24: O
D25: All existing skills deleted and nothing inserted (saveAll not called) | I25: O
B26: Exception
D27: ResourceNotFoundException: Không tìm thấy chuyên ngành với ID: 99 | H27: O
B28: Log message
A30: Result | B30: Type(N : Normal, A : Abnormal, B : Boundary) | F30: N | G30: N | H30: A | I30: B
B31: Passed/Failed | F31: P | G31: P | H31: P | I31: P
B32: Executed Date | F32: 46253 | G32: 46253 | H32: 46253 | I32: 46253
B33: Defect ID

Sheet FE-07
A2: Function Code | C2: FE-07 | F2: Function Name | L2: FE-07_Manage Career Timeline
A3: Created By | C3: AnNH | F3: Executed By | L3: MinhVB
A4: Lines of code | C4: 109 | F4: Lack of test cases | L4: =IF(Functions!E6<>"N/A",SUM(C4*Functions!E6/1000,-O7),"N/A") -> N/A
A5: Test requirement | C5: Add, edit, delete and promote career experiences
A6: Passed | C6: Failed | F6: Untested | L6: N/A/B | O6: Total Test Cases
A7: =COUNTIF(F67:X67,"P") -> 19 | C7: =COUNTIF(F67:X67,"F") -> 0 | F7: =SUM(O7,-A7,-C7) -> 0 | L7: =COUNTIF(F66:X66,"N") -> 6 | M7: =COUNTIF(F66:X66,"A") -> 8 | N7: =COUNTIF(F66:X66,"B") -> 5 | O7: =COUNTA(F9:X9) -> 19
F9: UTCID01 | G9: UTCID02 | H9: UTCID03 | I9: UTCID04 | J9: UTCID05 | K9: UTCID06 | L9: UTCID07 | M9: UTCID08 | N9: UTCID09 | O9: UTCID10 | P9: UTCID11 | Q9: UTCID12 | R9: UTCID13 | S9: UTCID14 | T9: UTCID15 | U9: UTCID16 | V9: UTCID17 | W9: UTCID18 | X9: UTCID19
A10: Condition | B10: Precondition
D11: User has 2 experiences | F11: O
D12: User has no primary experience | G12: O
D13: User exists | H13: O | I13: O | J13: O | K13: O | L13: O | M13: O | N13: O | O13: O | P13: O | Q13: O
D14: Experience id 5 belongs to the user | R14: O
D15: Experience id 404 does not belong to the user / does not exist | S15: O
D16: Experience id 5 is the primary one | T16: O
D17: Another current experience exists | T17: O
D18: Experience id 404 does not exist for the user | U18: O
D19: Experience id 5 is current and primary (started 2022-01-01) | V19: O
D20: Experience id 5 already ended (isCurrent = false) | W20: O
D21: Experience id 5 is current, started 2022-01-01 | X21: O
B22: Input
D23: email | F23: O
D24: ExperienceRequest(isCurrent = true, startDate, no endDate) | G24: O
D25: ExperienceRequest(isCurrent = false, startDate 2020-01-01, endDate 2021-01-01) | H25: O
D26: ExperienceRequest(startDate = null) | I26: O
D27: ExperienceRequest(isCurrent = false, endDate = null) | J27: O
D28: ExperienceRequest(endDate 2019-12-31 < startDate 2020-01-01) | K28: O
D29: ExperienceRequest(endDate = startDate = 2020-01-01) | L29: O
D30: ExperienceRequest(isPrimary = true, isCurrent = false) | M30: O
D31: ExperienceRequest(latitude = 10.5, longitude = null) | N31: O
D32: ExperienceRequest(latitude = 90, longitude = 180) - upper bounds | O32: O
D33: ExperienceRequest(latitude = 90.1) - just above the upper bound | P33: O
D34: ExperienceRequest(longitude = -180.1) - just below the lower bound | Q34: O
D35: id = 5, ExperienceRequest(title = Lead Developer, isCurrent = true) | R35: O
D36: id = 404, ExperienceRequest | S36: O
D37: id = 5 | T37: O
D38: id = 404 | U38: O
D39: id = 5, PromotionRequest(newTitle = Tech Lead, newStartDate = 2024-01-01) | V39: O
D40: id = 5, PromotionRequest | W40: O
D41: PromotionRequest(newStartDate = 2022-01-01) - equal to the old start date | X41: O
A43: Confirm | B43: Return
D44: List of 2 ExperienceResponse ordered by start date descending | F44: O
D45: Experience saved as primary + current with endDate = null | G45: O
D46: Experience saved as non-primary | H46: O
D47: Accepted: experience saved (end date may equal start date) | L47: O
D48: Accepted: experience saved | O48: O
D49: ExperienceResponse; experience updated and saved, endDate cleared for current job | R49: O
D50: Void; experience deleted and the latest current experience is promoted to primary | T50: O
D51: Old experience ended on 2023-12-31 and no longer primary | V51: O
D52: New current experience with the same company becomes primary | V52: O
B53: Exception
D54: BadRequestException: Ngày bắt đầu không được để trống | I54: O
D55: BadRequestException: Ngày kết thúc không được để trống khi đã kết thúc công việc | J55: O
D56: BadRequestException: Ngày kết thúc không được trước ngày bắt đầu | K56: O
D57: BadRequestException: Chỉ kinh nghiệm hiện tại mới được đặt làm chính (primary) | M57: O
D58: BadRequestException: Vĩ độ và kinh độ phải cùng tồn tại hoặc cùng trống | N58: O
D59: BadRequestException: Vĩ độ phải nằm trong khoảng -90 đến 90 | P59: O
D60: BadRequestException: Kinh độ phải nằm trong khoảng -180 đến 180 | Q60: O
D61: ResourceNotFoundException: Không tìm thấy kinh nghiệm làm việc với ID: 404 | S61: O | U61: O
D62: BadRequestException: Không thể thăng chức cho kinh nghiệm làm việc đã kết thúc | W62: O
D63: BadRequestException: Ngày bắt đầu vai trò mới phải sau ngày bắt đầu vai trò cũ | X63: O
B64: Log message
A66: Result | B66: Type(N : Normal, A : Abnormal, B : Boundary) | F66: N | G66: N | H66: N | I66: A | J66: A | K66: A | L66: B | M66: A | N66: A | O66: B | P66: B | Q66: B | R66: N | S66: A | T66: N | U66: A | V66: N | W66: A | X66: B
B67: Passed/Failed | F67: P | G67: P | H67: P | I67: P | J67: P | K67: P | L67: P | M67: P | N67: P | O67: P | P67: P | Q67: P | R67: P | S67: P | T67: P | U67: P | V67: P | W67: P | X67: P
B68: Executed Date | F68: 46255 | G68: 46255 | H68: 46255 | I68: 46255 | J68: 46255 | K68: 46255 | L68: 46255 | M68: 46255 | N68: 46255 | O68: 46255 | P68: 46255 | Q68: 46255 | R68: 46255 | S68: 46255 | T68: 46255 | U68: 46255 | V68: 46255 | W68: 46255 | X68: 46255
B69: Defect ID

Sheet FE-08
A2: Function Code | C2: FE-08 | F2: Function Name | L2: FE-08_Search Users & Alumni Directory
A3: Created By | C3: AnNH | F3: Executed By | L3: AnNH
A4: Lines of code | C4: 117 | F4: Lack of test cases | L4: =IF(Functions!E6<>"N/A",SUM(C4*Functions!E6/1000,-O7),"N/A") -> N/A
A5: Test requirement | C5: Search and filter the alumni directory
A6: Passed | C6: Failed | F6: Untested | L6: N/A/B | O6: Total Test Cases
A7: =COUNTIF(F49:T49,"P") -> 11 | C7: =COUNTIF(F49:T49,"F") -> 0 | F7: =SUM(O7,-A7,-C7) -> 0 | L7: =COUNTIF(F48:T48,"N") -> 9 | M7: =COUNTIF(F48:T48,"A") -> 0 | N7: =COUNTIF(F48:T48,"B") -> 2 | O7: =COUNTA(F9:T9) -> 11
F9: UTCID01 | G9: UTCID02 | H9: UTCID03 | I9: UTCID04 | J9: UTCID05 | K9: UTCID06 | L9: UTCID07 | M9: UTCID08 | N9: UTCID09 | O9: UTCID10 | P9: UTCID11
A10: Condition | B10: Precondition
D11: Anonymous visitor (no authentication) | F11: O
D12: Repository returns 2 users with profile | F12: O
D13: Repository returns users | G13: O | H13: O | I13: O
D14: No user matches the filters | J14: O
D15: Viewer is logged in (id 99) | K15: O
D16: Viewer follows user 1 and has 3 mutual connections with user 1 | K16: O
D17: User 1 has 5 followers, 2 following | K17: O
D18: A matched user has no profile row | L18: O
D19: Repository returns 1 user | M19: O
D20: Two primary experiences exist for the same user (duplicate rows) | N20: O
D21: Database has cohorts [2018, 2019] and cities [Ha Noi, Da Nang] | O21: O
D22: Database has no profile data | P22: O
B23: Input
D24: query="nguyen", role=ALUMNI, majorId=1, cohort=2018, city="Ha Noi", skill=Java, company=FPT, page=0, size=10, sortBy=createdAt, sortDirection=DESC | F24: O
D25: sortBy=fullName, sortDirection=asc (lower-case) | G25: O
D26: sortBy=cohort, sortDirection=DESC | H26: O
D27: sortBy=unknownField, sortDirection=null | I27: O
D28: query="zzz-no-match" | J28: O
D29: default search | K29: O | L29: O | N29: O
D30: page = 0, size = 1 (smallest page) | M30: O
D31: (no input) | O31: O | P31: O
A33: Confirm | B33: Return
D34: PageResponse with 2 UserDirectoryResponse, totalElements=2, followersCount defaults to 0, isFollowing=false | F34: O
D35: Pageable sorted by profile.fullName ASC | G35: O
D36: Pageable sorted by profile.cohort DESC | H36: O
D37: Falls back to createdAt DESC | I37: O
D38: Empty PageResponse (content = [], totalElements = 0); no batch queries executed | J38: O
D39: Item of user 1: isFollowing=true, mutualFollowsCount=3, followersCount=5, followingCount=2 | K39: O
D40: Fallback item built from the User (email, role, isAccountVerified) instead of failing | L40: O
D41: PageResponse with pageNumber = 0, pageSize = 1 | M41: O
D42: No exception; the first primary experience is kept (merge function) | N42: O
D43: UserFilterOptionsResponse(cohorts=[2018,2019], cities=[Ha Noi, Da Nang]) | O43: O
D44: UserFilterOptionsResponse with empty cohorts and cities | P44: O
B45: Exception
B46: Log message
A48: Result | B48: Type(N : Normal, A : Abnormal, B : Boundary) | F48: N | G48: N | H48: N | I48: B | J48: N | K48: N | L48: N | M48: B | N48: N | O48: N | P48: N
B49: Passed/Failed | F49: P | G49: P | H49: P | I49: P | J49: P | K49: P | L49: P | M49: P | N49: P | O49: P | P49: P
B50: Executed Date | F50: 46263 | G50: 46263 | H50: 46263 | I50: 46263 | J50: 46263 | K50: 46263 | L50: 46263 | M50: 46263 | N50: 46263 | O50: 46263 | P50: 46263
B51: Defect ID

Sheet FE-09
A2: Function Code | C2: FE-09 | F2: Function Name | L2: FE-09_View Connection Suggestions
A3: Created By | C3: AnNH | F3: Executed By | L3: TrietNH
A4: Lines of code | C4: 216 | F4: Lack of test cases | L4: =IF(Functions!E6<>"N/A",SUM(C4*Functions!E6/1000,-O7),"N/A") -> N/A
A5: Test requirement | C5: Show connection suggestions and follow members
A6: Passed | C6: Failed | F6: Untested | L6: N/A/B | O6: Total Test Cases
A7: =COUNTIF(F56:T56,"P") -> 13 | C7: =COUNTIF(F56:T56,"F") -> 0 | F7: =SUM(O7,-A7,-C7) -> 0 | L7: =COUNTIF(F55:T55,"N") -> 8 | M7: =COUNTIF(F55:T55,"A") -> 1 | N7: =COUNTIF(F55:T55,"B") -> 4 | O7: =COUNTA(F9:T9) -> 13
F9: UTCID01 | G9: UTCID02 | H9: UTCID03 | I9: UTCID04 | J9: UTCID05 | K9: UTCID06 | L9: UTCID07 | M9: UTCID08 | N9: UTCID09 | O9: UTCID10 | P9: UTCID11 | Q9: UTCID12 | R9: UTCID13
A10: Condition | B10: Precondition
D11: Visitor not logged in (email = null) | F11: O
D12: Guest candidate is verified and has primary experience 'Dev @ FPT' and 4 followers | F12: O
D13: Viewer logged in with major SE | G13: O
D14: Candidate has the same major SE | G14: O
D15: Viewer cohort 2018 | H15: O | I15: O | J15: O
D16: Candidate cohort 2018 | H16: O
D17: Candidate cohort 2019 (difference = 1) | I17: O
D18: Candidate cohort 2021 (difference = 3, outside the 0..2 window) | J18: O
D19: Viewer city Ha Noi | K19: O
D20: Candidate city "ha noi" (case-insensitive match) | K20: O
D21: Viewer owns skills Java, React | L21: O
D22: Candidate owns skills java, react, go | L22: O
D23: Candidate A has 0 mutual connections but a high score | M23: O
D24: Candidate B has 2 mutual connections | M24: O
D25: Viewer follows users 7 and 8 | N25: O
D26: 60 candidates available | O26: O | P26: O
D27: No candidate is available | Q27: O
D28: Email does not belong to any account | R28: O
B29: Input
D30: email = null, limit = 5 | F30: O
D31: email = viewer@fpt.edu.vn, limit = 5 | G31: O
D32: email, limit = 5 | H32: O | I32: O | J32: O | K32: O | L32: O | M32: O | N32: O | Q32: O
D33: limit = 0 (non-positive) | O33: O
D34: limit = 100 (above the maximum) | P34: O
D35: email = ghost@fpt.edu.vn | R35: O
A37: Confirm | B37: Return
D38: 1 suggestion; matchScore = 40 (experience) + 30 (verified) + 4 (followers) = 74 | F38: O
D39: reason badges: "Dev @ FPT", "Cựu sinh viên tiêu biểu" | F39: O
D40: Badge "Cùng ngành SE" and score includes +30 | G40: O
D41: Badge "Cùng khóa K2018" and score +25 | H41: O
D42: Badge "Sát khóa (K2019)" and score +15 | I42: O
D43: No cohort score; fallback badge "Thành viên cộng đồng FPTU", matchScore = 0 | J43: O
D44: Badge "Đang ở ha noi" and score +15 | K44: O
D45: Badge "2 kỹ năng chung" and score +10 (5 per shared skill) | L45: O
D46: Candidate B is listed first (mutual connections take priority), badge "2 kết nối chung" | M46: O
D47: Candidates are requested excluding the viewer (99) and followed users (7, 8) | N47: O
D48: Limit defaults to 5 -> 5 suggestions | O48: O
D49: Limit capped to 50 -> 50 suggestions | P49: O
D50: Empty list and no batch queries | Q50: O
D51: Treated as guest: findGuestCandidates is used instead of personalised candidates | R51: O
B52: Exception
B53: Log message
A55: Result | B55: Type(N : Normal, A : Abnormal, B : Boundary) | F55: N | G55: N | H55: N | I55: B | J55: B | K55: N | L55: N | M55: N | N55: N | O55: B | P55: B | Q55: N | R55: A
B56: Passed/Failed | F56: P | G56: P | H56: P | I56: P | J56: P | K56: P | L56: P | M56: P | N56: P | O56: P | P56: P | Q56: P | R56: P
B57: Executed Date | F57: 46263 | G57: 46263 | H57: 46263 | I57: 46263 | J57: 46263 | K57: 46263 | L57: 46263 | M57: 46263 | N57: 46263 | O57: 46263 | P57: 46263 | Q57: 46263 | R57: 46263
B58: Defect ID

Sheet FE-10
A2: Function Code | C2: FE-10 | F2: Function Name | L2: FE-10_Manage Social Connections (Follow / Followers / Following)
A3: Created By | C3: AnNH | F3: Executed By | L3: HieuPT
A4: Lines of code | C4: 154 | F4: Lack of test cases | L4: =IF(Functions!E6<>"N/A",SUM(C4*Functions!E6/1000,-O7),"N/A") -> N/A
A5: Test requirement | C5: Follow / unfollow members and view followers / following
A6: Passed | C6: Failed | F6: Untested | L6: N/A/B | O6: Total Test Cases
A7: =COUNTIF(F66:V66,"P") -> 17 | C7: =COUNTIF(F66:V66,"F") -> 0 | F7: =SUM(O7,-A7,-C7) -> 0 | L7: =COUNTIF(F65:V65,"N") -> 5 | M7: =COUNTIF(F65:V65,"A") -> 11 | N7: =COUNTIF(F65:V65,"B") -> 1 | O7: =COUNTA(F9:V9) -> 17
F9: UTCID01 | G9: UTCID02 | H9: UTCID03 | I9: UTCID04 | J9: UTCID05 | K9: UTCID06 | L9: UTCID07 | M9: UTCID08 | N9: UTCID09 | O9: UTCID10 | P9: UTCID11 | Q9: UTCID12 | R9: UTCID13 | S9: UTCID14 | T9: UTCID15 | U9: UTCID16 | V9: UTCID17
A10: Condition | B10: Precondition
D11: Both accounts ACTIVE | F11: O
D12: Not following yet | F12: O
D13: Follower email does not exist | G13: O
D14: Target user id 404 does not exist | H14: O | O14: O
D15: Logged-in user id = 1 | I15: O
D16: Follower account is LOCKED | J16: O
D17: Target account is LOCKED | K17: O
D18: Follow relation already exists | L18: O
D19: Two concurrent requests: unique constraint is violated while saving | M19: O
D20: Follow relation exists | N20: O
D21: Target exists but is not followed by the user | P21: O
D22: Target user 2 is ACTIVE | Q22: O
D23: Follower 3 has primary experience 'Dev @ FPT' and no declared headline | Q23: O
D24: Logged-in viewer follows follower 3 | Q24: O
D25: Target user is LOCKED | R25: O
D26: User id 404 does not exist | S26: O
D27: User 2 follows user 3 who has no profile row and no experience | T27: O
D28: Viewer is anonymous | T28: O
D29: Followed user declared headline "Backend Engineer" | U29: O
D30: Target user 2 has no followers | V30: O
B31: Input
D32: followerEmail = me@fpt.edu.vn, followingId = 2 | F32: O
D33: followerEmail = ghost@fpt.edu.vn, followingId = 2 | G33: O
D34: followerEmail, followingId = 404 | H34: O | O34: O
D35: followingId = 1 (self) | I35: O
D36: followerEmail, followingId = 2 | J36: O | K36: O | L36: O | M36: O | N36: O | P36: O
D37: viewerEmail = me@fpt.edu.vn, userId = 2, Pageable(0, 10) | Q37: O
D38: viewerEmail, userId = 2, Pageable | R38: O
D39: viewerEmail, userId = 404, Pageable | S39: O
D40: viewerEmail = null, userId = 2, Pageable(0, 10) | T40: O | V40: O
D41: viewerEmail = null, userId = 2, Pageable | U41: O
A43: Confirm | B43: Return
D44: Void; Follow row saved (saveAndFlush) | F44: O
D45: Void; Follow row deleted | N45: O
D46: PageResponse with 1 FollowUserResponse: headline = "Dev @ FPT", isFollowing = true | Q46: O
D47: fullName = "Thành viên AlumNect", headline = "Cựu sinh viên FPTU", isFollowing = false | T47: O
D48: headline = "Backend Engineer" (declared headline has priority over experience) | U48: O
D49: Empty PageResponse (content = [], totalElements = 0, last = true) | V49: O
B50: Exception
D51: ResourceNotFoundException: Không tìm thấy tài khoản người thực hiện theo dõi. | G51: O
D52: ResourceNotFoundException: Không tìm thấy tài khoản người dùng cần theo dõi. | H52: O
D53: BadRequestException: Bạn không thể tự theo dõi chính mình. | I53: O
D54: BadRequestException: Tài khoản của bạn chưa được kích hoạt hoặc đã bị khóa. | J54: O
D55: BadRequestException: Tài khoản người dùng cần theo dõi chưa được kích hoạt hoặc đã bị khóa. | K55: O
D56: ConflictException: Bạn đã theo dõi người dùng này từ trước. | L56: O
D57: ConflictException: Bạn đã theo dõi người dùng này từ trước. (DataIntegrityViolationException mapped to 409) | M57: O
D58: ResourceNotFoundException: Không tìm thấy tài khoản người dùng cần hủy theo dõi. | O58: O
D59: BadRequestException: Bạn chưa theo dõi người dùng này. | P59: O
D60: BadRequestException: Người dùng này chưa được kích hoạt hoặc đã bị khóa. | R60: O
D61: ResourceNotFoundException: Không tìm thấy người dùng. | S61: O
B62: Log message
D63: Follow notification sent to the followed user | F63: O
A65: Result | B65: Type(N : Normal, A : Abnormal, B : Boundary) | F65: N | G65: A | H65: A | I65: A | J65: A | K65: A | L65: A | M65: A | N65: N | O65: A | P65: A | Q65: N | R65: A | S65: A | T65: N | U65: N | V65: B
B66: Passed/Failed | F66: P | G66: P | H66: P | I66: P | J66: P | K66: P | L66: P | M66: P | N66: P | O66: P | P66: P | Q66: P | R66: P | S66: P | T66: P | U66: P | V66: P
B67: Executed Date | F67: 46235 | G67: 46235 | H67: 46235 | I67: 46235 | J67: 46235 | K67: 46235 | L67: 46235 | M67: 46235 | N67: 46235 | O67: 46235 | P67: 46235 | Q67: 46235 | R67: 46235 | S67: 46235 | T67: 46235 | U67: 46235 | V67: 46235
B68: Defect ID

Sheet FE-11
A2: Function Code | C2: FE-11 | F2: Function Name | L2: FE-11_Admin Console Shell, Access Control & Navigation
A3: Created By | C3: AnNH | F3: Executed By | L3: HuyLTN
A4: Lines of code | C4: 77 | F4: Lack of test cases | L4: =IF(Functions!E6<>"N/A",SUM(C4*Functions!E6/1000,-O7),"N/A") -> N/A
A5: Test requirement | C5: Admin access control, sidebar navigation and logout
A6: Passed | C6: Failed | F6: Untested | L6: N/A/B | O6: Total Test Cases
A7: =COUNTIF(F80:AA80,"P") -> 22 | C7: =COUNTIF(F80:AA80,"F") -> 0 | F7: =SUM(O7,-A7,-C7) -> 0 | L7: =COUNTIF(F79:AA79,"N") -> 9 | M7: =COUNTIF(F79:AA79,"A") -> 11 | N7: =COUNTIF(F79:AA79,"B") -> 2 | O7: =COUNTA(F9:AA9) -> 22
F9: UTCID01 | G9: UTCID02 | H9: UTCID03 | I9: UTCID04 | J9: UTCID05 | K9: UTCID06 | L9: UTCID07 | M9: UTCID08 | N9: UTCID09 | O9: UTCID10 | P9: UTCID11 | Q9: UTCID12 | R9: UTCID13 | S9: UTCID14 | T9: UTCID15 | U9: UTCID16 | V9: UTCID17 | W9: UTCID18 | X9: UTCID19 | Y9: UTCID20 | Z9: UTCID21 | AA9: UTCID22
A10: Condition | B10: Precondition
D11: User ADMIN, id=1, accountVerified = true | F11: O
D12: Access-token lifetime configured to 24 hours (86400000 ms) | G12: O
D13: Refresh-token lifetime configured to 7 days | H13: O
D14: Fresh token issued for admin@fpt.edu.vn | I14: O
D15: Token belongs to admin@fpt.edu.vn | J15: O
D16: Token lifetime is negative, so the token is already expired | K16: O
D17: Token payload/signature altered after signing | L17: O
D18: Token is not a JWT | M18: O
D19: Authorization: Bearer <valid token> of an ADMIN | N19: O
D20: validateToken returns true | N20: O
D21: Request has no Authorization header (guest) | O21: O
D22: Authorization header uses another scheme (Basic abc) | P22: O
D23: Bearer token is garbage; JwtService throws while parsing | Q23: O
D24: Token valid but the user no longer exists | R24: O
D25: Token fails validation (expired or user mismatch): validateToken returns false | S25: O
D26: ACTIVE, email-verified ADMIN account | T26: O
D27: Role name already stored with the ROLE_ prefix | U27: O
D28: Account status LOCKED | V28: O
D29: Email not verified | W29: O
D30: No account for the email | X30: O
D31: Google account with passwordHash = null | Y31: O
D32: Endpoints constants used by SecurityConfiguration | Z32: O | AA32: O
B33: Input
D34: generateToken(user) | F34: O | G34: O
D35: generateRefreshToken(user) | H35: O
D36: validateToken(token, UserDetails admin@fpt.edu.vn) | I36: O
D37: validateToken(token, UserDetails other@fpt.edu.vn) | J37: O
D38: extractUsername(expiredToken) | K38: O
D39: extractUsername(tamperedToken) | L39: O
D40: extractUsername("not-a-jwt") | M40: O
D41: HTTP GET /api/v1/admin/dashboard | N41: O
D42: HTTP GET | O42: O | P42: O
D43: HTTP GET with Authorization: Bearer garbage | Q43: O
D44: HTTP GET with Authorization: Bearer tok | R44: O | S44: O
D45: loadUserByUsername("admin@fpt.edu.vn") | T45: O
D46: loadUserByUsername(email) | U46: O | V46: O | W46: O | Y46: O
D47: loadUserByUsername("ghost@fpt.edu.vn") | X47: O
D48: Endpoints.ADMIN_ENDPOINT | Z48: O
D49: Endpoints.PUBLIC_POST | AA49: O
A51: Confirm | B51: Return
D52: HS256 JWT with subject = email and claims id, email, role=ADMIN, isAccountVerified=true | F52: O
D53: exp - iat equals 24 hours (within 1 second) | G53: O
D54: JWT valid for 7 days, carries role claim but no isAccountVerified claim | H54: O
D55: true | I55: O
D56: false (token subject does not match the user) | J56: O
D57: SecurityContext authenticated as admin@fpt.edu.vn with authority ROLE_ADMIN | N57: O
D58: Filter chain continues | N58: O
D59: No authentication in SecurityContext; filter chain continues | O59: O
D60: Header ignored: no authentication, JwtService never called | P60: O
D61: Exception swallowed and logged; no authentication; filter chain still continues | Q61: O
D62: UsernameNotFoundException swallowed; no authentication; chain continues | R62: O
D63: No authentication in SecurityContext | S63: O
D64: UserDetails: authority ROLE_ADMIN, enabled = true, accountNonLocked = true | T64: O
D65: Authority stays "ROLE_ADMIN" (prefix is not duplicated) | U65: O
D66: UserDetails.accountNonLocked = false and enabled = false | V66: O
D67: UserDetails.enabled = false | W67: O
D68: UserDetails with empty password "" (no NullPointerException) | Y68: O
D69: Contains "/api/v1/admin/**" (all admin APIs require ROLE_ADMIN) | Z69: O
D70: Contains login / register / refresh / forgot-password routes, and no admin route | AA70: O
B71: Exception
D72: ExpiredJwtException | K72: O
D73: JwtException (signature does not match) | L73: O
D74: MalformedJwtException | M74: O
D75: UsernameNotFoundException: Không tìm thấy người dùng với email: ghost@fpt.edu.vn | X75: O
B76: Log message
D77: Không thể thiết lập thông tin xác thực người dùng | Q77: O
A79: Result | B79: Type(N : Normal, A : Abnormal, B : Boundary) | F79: N | G79: B | H79: N | I79: N | J79: A | K79: A | L79: A | M79: A | N79: N | O79: N | P79: A | Q79: A | R79: A | S79: A | T79: N | U79: B | V79: A | W79: A | X79: A | Y79: N | Z79: N | AA79: N
B80: Passed/Failed | F80: P | G80: P | H80: P | I80: P | J80: P | K80: P | L80: P | M80: P | N80: P | O80: P | P80: P | Q80: P | R80: P | S80: P | T80: P | U80: P | V80: P | W80: P | X80: P | Y80: P | Z80: P | AA80: P
B81: Executed Date | F81: 46227 | G81: 46227 | H81: 46227 | I81: 46227 | J81: 46227 | K81: 46227 | L81: 46227 | M81: 46227 | N81: 46227 | O81: 46227 | P81: 46227 | Q81: 46227 | R81: 46227 | S81: 46227 | T81: 46227 | U81: 46227 | V81: 46227 | W81: 46227 | X81: 46227 | Y81: 46227 | Z81: 46227 | AA81: 46227
B82: Defect ID

Sheet FE-12
A2: Function Code | C2: FE-12 | F2: Function Name | L2: FE-12_Admin Overview Dashboard & Operations
A3: Created By | C3: AnNH | F3: Executed By | L3: MinhVB
A4: Lines of code | C4: 79 | F4: Lack of test cases | L4: =IF(Functions!E6<>"N/A",SUM(C4*Functions!E6/1000,-O7),"N/A") -> N/A
A5: Test requirement | C5: Admin dashboard KPIs, registration chart and action items
A6: Passed | C6: Failed | F6: Untested | L6: N/A/B | O6: Total Test Cases
A7: =COUNTIF(F38:T38,"P") -> 9 | C7: =COUNTIF(F38:T38,"F") -> 0 | F7: =SUM(O7,-A7,-C7) -> 0 | L7: =COUNTIF(F37:T37,"N") -> 5 | M7: =COUNTIF(F37:T37,"A") -> 0 | N7: =COUNTIF(F37:T37,"B") -> 4 | O7: =COUNTA(F9:T9) -> 9
F9: UTCID01 | G9: UTCID02 | H9: UTCID03 | I9: UTCID04 | J9: UTCID05 | K9: UTCID06 | L9: UTCID07 | M9: UTCID08 | N9: UTCID09
A10: Condition | B10: Precondition
D11: DB: 100 users (60 students, 35 alumni, 5 admins), 90 ACTIVE, 4 LOCKED, 7 pending verification requests | F11: O
D12: No registrations in the last 7 days | G12: O
D13: DB returns 3 registrations for today (row date type = java.sql.Date) and 2 for yesterday (row date type = LocalDate) | H13: O
D14: DB returns a row with a date given as String and a row with null date | I14: O
D15: No registration data by month | J15: O
D16: DB returns 8 registrations in month 3 and 5 in month 12 | K16: O
D17: DB returns registrations per year: 2024 -> 40, 2025 -> 60 | L17: O
D18: DB returns no yearly rows (empty system) | M18: O
D19: Total users = 12 | M19: O
D20: Empty database: every counter returns 0 | N20: O
B21: Input
D22: getDashboardSummary() | F22: O | G22: O | H22: O | I22: O | J22: O | K22: O | L22: O | M22: O | N22: O
A24: Confirm | B24: Return
D25: AdminDashboardSummaryDto with totalUsers=100, totalStudents=60, totalAlumni=35, totalAdmins=5, activeUsers=90, lockedUsers=4, pendingVerifications=7 | F25: O
D26: registrationsLast7Days has exactly 7 entries from today-6 to today, each with count 0 | G26: O
D27: Last entry (today) count = 3, previous entry (yesterday) count = 2, other days 0 | H27: O
D28: String date is mapped to its day; null-date row is ignored without error | I28: O
D29: registrationsByMonth has exactly 12 entries labelled "Tháng 1" ... "Tháng 12", all 0 | J29: O
D30: "Tháng 3" = 8, "Tháng 12" = 5, remaining months 0 | K30: O
D31: registrationsByYear = ["Năm 2024":40, "Năm 2025":60] | L31: O
D32: Fallback: one entry "Năm <current year>" with count = totalUsers = 12 | M32: O
D33: All KPI counters are 0; trend lists still have 7 / 12 / 1 entries (no exception) | N33: O
B34: Exception
B35: Log message
A37: Result | B37: Type(N : Normal, A : Abnormal, B : Boundary) | F37: N | G37: B | H37: N | I37: N | J37: B | K37: N | L37: N | M37: B | N37: B
B38: Passed/Failed | F38: P | G38: P | H38: P | I38: P | J38: P | K38: P | L38: P | M38: P | N38: P
B39: Executed Date | F39: 46210 | G39: 46210 | H39: 46210 | I39: 46210 | J39: 46210 | K39: 46210 | L39: 46210 | M39: 46210 | N39: 46210
B40: Defect ID

Sheet FE-13
A2: Function Code | C2: FE-13 | F2: Function Name | L2: FE-13_User Account Management
A3: Created By | C3: AnNH | F3: Executed By | L3: AnNH
A4: Lines of code | C4: 88 | F4: Lack of test cases | L4: =IF(Functions!E6<>"N/A",SUM(C4*Functions!E6/1000,-O7),"N/A") -> N/A
A5: Test requirement | C5: Admin user list, filters, detail and lock / unlock
A6: Passed | C6: Failed | F6: Untested | L6: N/A/B | O6: Total Test Cases
A7: =COUNTIF(F50:T50,"P") -> 12 | C7: =COUNTIF(F50:T50,"F") -> 0 | F7: =SUM(O7,-A7,-C7) -> 0 | L7: =COUNTIF(F49:T49,"N") -> 7 | M7: =COUNTIF(F49:T49,"A") -> 4 | N7: =COUNTIF(F49:T49,"B") -> 1 | O7: =COUNTA(F9:T9) -> 12
F9: UTCID01 | G9: UTCID02 | H9: UTCID03 | I9: UTCID04 | J9: UTCID05 | K9: UTCID06 | L9: UTCID07 | M9: UTCID08 | N9: UTCID09 | O9: UTCID10 | P9: UTCID11 | Q9: UTCID12
A10: Condition | B10: Precondition
D11: 2 users match; user 1 owns a mentor profile (id 55), user 2 does not | F11: O
D12: No user matches the filters | G12: O
D13: One mentor with two mentor-profile rows (duplicates) | H13: O
D14: Exactly 1 user in the system | I14: O
D15: User 1 and profile exist; user owns mentor profile id 55 | J15: O
D16: User 1 and profile exist; no mentor profile | K16: O
D17: No user with id 999 | L17: O | Q17: O
D18: User 1 exists but has no profile row | M18: O
D19: ACTIVE user 1 exists | N19: O
D20: LOCKED user 1 exists | O20: O
D21: User 1 exists | P21: O
B22: Input
D23: query="nguyen", role=STUDENT, status=ACTIVE, majorId=1, cohort=2020, page=0, size=10 | F23: O
D24: query="zzz", page=0, size=10 | G24: O
D25: page=0, size=10 | H25: O
D26: page=0, size=1 | I26: O
D27: id = 1 | J27: O | K27: O | M27: O
D28: id = 999 | L28: O
D29: id = 1, AdminUpdateUserStatusDto(status = LOCKED) | N29: O
D30: id = 1, status = "active" (lower-case) | O30: O
D31: id = 1, status = "BANNED" (not an AccountStatus) | P31: O
D32: id = 999, status = LOCKED | Q32: O
A34: Confirm | B34: Return
D35: PageResponse with 2 AdminUserDto; user 1 hasMentorProfile=true & mentorProfileId=55; user 2 hasMentorProfile=false | F35: O
D36: Empty PageResponse; profile and mentor-profile lookups are skipped | G36: O
D37: No exception (merge function keeps the first); mentorProfileId = first row id | H37: O
D38: PageResponse pageNumber=0, pageSize=1, totalPages=1, last=true | I38: O
D39: AdminUserDto with hasMentorProfile=true, mentorProfileId=55 | J39: O
D40: AdminUserDto with hasMentorProfile=false | K40: O
D41: Void; user.accountStatus = LOCKED and the user is saved | N41: O
D42: Void; user.accountStatus = ACTIVE (status is case-insensitive) | O42: O
B43: Exception
D44: ResourceNotFoundException: Không tìm thấy người dùng với ID: 999 | L44: O | Q44: O
D45: ResourceNotFoundException: Không tìm thấy hồ sơ cho người dùng với ID: 1 | M45: O
D46: BadRequestException: Trạng thái tài khoản không hợp lệ: BANNED | P46: O
B47: Log message
A49: Result | B49: Type(N : Normal, A : Abnormal, B : Boundary) | F49: N | G49: N | H49: N | I49: B | J49: N | K49: N | L49: A | M49: A | N49: N | O49: N | P49: A | Q49: A
B50: Passed/Failed | F50: P | G50: P | H50: P | I50: P | J50: P | K50: P | L50: P | M50: P | N50: P | O50: P | P50: P | Q50: P
B51: Executed Date | F51: 46210 | G51: 46210 | H51: 46210 | I51: 46210 | J51: 46210 | K51: 46210 | L51: 46210 | M51: 46210 | N51: 46210 | O51: 46210 | P51: 46210 | Q51: 46210
B52: Defect ID

Sheet FE-14
A2: Function Code | C2: FE-14 | F2: Function Name | L2: FE-14_View & Filter Community Posts
A3: Created By | C3: AnNH | F3: Executed By | L3: TrietNH
A4: Lines of code | C4: 41 | F4: Lack of test cases | L4: =IF(Functions!E6<>"N/A",SUM(C4*Functions!E6/1000,-O7),"N/A") -> N/A
A5: Test requirement | C5: Admin post list with type, status and search filters
A6: Passed | C6: Failed | F6: Untested | L6: N/A/B | O6: Total Test Cases
A7: =COUNTIF(F29:T29,"P") -> 4 | C7: =COUNTIF(F29:T29,"F") -> 0 | F7: =SUM(O7,-A7,-C7) -> 0 | L7: =COUNTIF(F28:T28,"N") -> 3 | M7: =COUNTIF(F28:T28,"A") -> 0 | N7: =COUNTIF(F28:T28,"B") -> 1 | O7: =COUNTA(F9:T9) -> 4
F9: UTCID01 | G9: UTCID02 | H9: UTCID03 | I9: UTCID04
A10: Condition | B10: Precondition
D11: 2 posts match; post 1 is a recruitment post linked to job 7, post 2 an event post linked to event 9 | F11: O
D12: No post matches the filters | G12: O
D13: Two posts reference the same job id 7 | H13: O
D14: Posts without job / event | I14: O
B15: Input
D16: query="fpt", author="", status="ACTIVE", type="RECRUITMENT", page=0, size=10 | F16: O
D17: query="zzz", page=0, size=10 | G17: O
D18: page=0, size=10 | H18: O | I18: O
A20: Confirm | B20: Return
D21: PageResponse with 2 AdminPostResponse; mapper receives the matching JobPosting / Event for each post | F21: O
D22: Empty PageResponse (content=[], totalElements=0); no job/event lookup | G22: O
D23: Job ids are de-duplicated: JobPostingRepository.findAllById is called once with [7] | H23: O
D24: Mapper is called with job = null, event = null; repositories are not queried | I24: O
B25: Exception
B26: Log message
A28: Result | B28: Type(N : Normal, A : Abnormal, B : Boundary) | F28: N | G28: N | H28: B | I28: N
B29: Passed/Failed | F29: P | G29: P | H29: P | I29: P
B30: Executed Date | F30: 46227 | G30: 46227 | H30: 46227 | I30: 46227
B31: Defect ID

Sheet FE-15
A2: Function Code | C2: FE-15 | F2: Function Name | L2: FE-15_View Community Post Detail
A3: Created By | C3: AnNH | F3: Executed By | L3: HieuPT
A4: Lines of code | C4: 7 | F4: Lack of test cases | L4: =IF(Functions!E6<>"N/A",SUM(C4*Functions!E6/1000,-O7),"N/A") -> N/A
A5: Test requirement | C5: Admin post detail, event card and job listing card
A6: Passed | C6: Failed | F6: Untested | L6: N/A/B | O6: Total Test Cases
A7: =COUNTIF(F26:T26,"P") -> 3 | C7: =COUNTIF(F26:T26,"F") -> 0 | F7: =SUM(O7,-A7,-C7) -> 0 | L7: =COUNTIF(F25:T25,"N") -> 2 | M7: =COUNTIF(F25:T25,"A") -> 1 | N7: =COUNTIF(F25:T25,"B") -> 0 | O7: =COUNTA(F9:T9) -> 3
F9: UTCID01 | G9: UTCID02 | H9: UTCID03
A10: Condition | B10: Precondition
D11: Post 1 exists, linked to job 7 and event 9 | F11: O
D12: Post 1 exists without job/event | G12: O
D13: No post with id 404 | H13: O
B14: Input
D15: id = 1 | F15: O | G15: O
D16: id = 404 | H16: O
A18: Confirm | B18: Return
D19: AdminPostResponse built with the job and the event | F19: O
D20: AdminPostResponse built with job = null and event = null | G20: O
B21: Exception
D22: ResourceNotFoundException: Không tìm thấy bài viết với ID: 404 | H22: O
B23: Log message
A25: Result | B25: Type(N : Normal, A : Abnormal, B : Boundary) | F25: N | G25: N | H25: A
B26: Passed/Failed | F26: P | G26: P | H26: P
B27: Executed Date | F27: 46252 | G27: 46252 | H27: 46252
B28: Defect ID

Sheet FE-16
A2: Function Code | C2: FE-16 | F2: Function Name | L2: FE-16_Hide / Unhide Violating Posts
A3: Created By | C3: AnNH | F3: Executed By | L3: HuyLTN
A4: Lines of code | C4: 12 | F4: Lack of test cases | L4: =IF(Functions!E6<>"N/A",SUM(C4*Functions!E6/1000,-O7),"N/A") -> N/A
A5: Test requirement | C5: Admin hide / unhide violating posts
A6: Passed | C6: Failed | F6: Untested | L6: N/A/B | O6: Total Test Cases
A7: =COUNTIF(F30:T30,"P") -> 4 | C7: =COUNTIF(F30:T30,"F") -> 0 | F7: =SUM(O7,-A7,-C7) -> 0 | L7: =COUNTIF(F29:T29,"N") -> 2 | M7: =COUNTIF(F29:T29,"A") -> 2 | N7: =COUNTIF(F29:T29,"B") -> 0 | O7: =COUNTA(F9:T9) -> 4
F9: UTCID01 | G9: UTCID02 | H9: UTCID03 | I9: UTCID04
A10: Condition | B10: Precondition
D11: Post 1 is ACTIVE | F11: O
D12: Post 1 is HIDDEN | G12: O
D13: Post 1 is DELETED | H13: O
D14: No post with id 404 | I14: O
B15: Input
D16: id = 1, isHidden = true | F16: O | H16: O
D17: id = 1, isHidden = false | G17: O
D18: id = 404, isHidden = true | I18: O
A20: Confirm | B20: Return
D21: Void; post status = HIDDEN and saved | F21: O
D22: Void; post status = ACTIVE and saved; no notification | G22: O
B23: Exception
D24: BadRequestException: Bài viết này đã bị xóa khỏi hệ thống, không thể thực hiện thao tác ẩn hoặc mở ẩn. | H24: O
D25: ResourceNotFoundException: Không tìm thấy bài viết với ID: 404 | I25: O
B26: Log message
D27: Report-resolved notification sent to the post author | F27: O
A29: Result | B29: Type(N : Normal, A : Abnormal, B : Boundary) | F29: N | G29: N | H29: A | I29: A
B30: Passed/Failed | F30: P | G30: P | H30: P | I30: P
B31: Executed Date | F31: 46273 | G31: 46273 | H31: 46273 | I31: 46273
B32: Defect ID

Sheet FE-17
A2: Function Code | C2: FE-17 | F2: Function Name | L2: FE-17_Alumni Verification Management Queue
A3: Created By | C3: AnNH | F3: Executed By | L3: MinhVB
A4: Lines of code | C4: 62 | F4: Lack of test cases | L4: =IF(Functions!E6<>"N/A",SUM(C4*Functions!E6/1000,-O7),"N/A") -> N/A
A5: Test requirement | C5: Alumni verification queue, proof viewer, approve / reject
A6: Passed | C6: Failed | F6: Untested | L6: N/A/B | O6: Total Test Cases
A7: =COUNTIF(F53:T53,"P") -> 12 | C7: =COUNTIF(F53:T53,"F") -> 0 | F7: =SUM(O7,-A7,-C7) -> 0 | L7: =COUNTIF(F52:T52,"N") -> 5 | M7: =COUNTIF(F52:T52,"A") -> 5 | N7: =COUNTIF(F52:T52,"B") -> 2 | O7: =COUNTA(F9:T9) -> 12
F9: UTCID01 | G9: UTCID02 | H9: UTCID03 | I9: UTCID04 | J9: UTCID05 | K9: UTCID06 | L9: UTCID07 | M9: UTCID08 | N9: UTCID09 | O9: UTCID10 | P9: UTCID11 | Q9: UTCID12
A10: Condition | B10: Precondition
D11: 2 PENDING requests exist | F11: O
D12: No request matches | G12: O
D13: Requests exist | H13: O
D14: Request 9 is PENDING for a WAITING_APPROVAL alumni | I14: O
D15: Request 9 is PENDING | J15: O | K15: O | N15: O
D16: No verification request with id 404 | L16: O
D17: Request 9 is already APPROVED | M17: O
D18: Validator applied to AdminReviewVerificationDto | O18: O | P18: O | Q18: O
B19: Input
D20: status = "PENDING", page = 0, size = 10 | F20: O
D21: status = "APPROVED", page = 0, size = 10 | G21: O
D22: status = "UNKNOWN" (invalid filter) | H22: O
D23: id = 9, AdminReviewVerificationDto(status = APPROVED, reviewNote = "Proof is valid"), adminUser | I23: O
D24: id = 9, AdminReviewVerificationDto(status = REJECTED, reviewNote = "Blurry proof") | J24: O
D25: AdminReviewVerificationDto(status = "approved" lower-case, reviewNote = null) | K25: O
D26: id = 404, AdminReviewVerificationDto(APPROVED) | L26: O
D27: id = 9, AdminReviewVerificationDto(REJECTED) | M27: O
D28: AdminReviewVerificationDto(status = "MAYBE") | N28: O
D29: reviewNote length = 500 (maximum) | O29: O
D30: reviewNote length = 501 (above maximum) | P30: O
D31: status = "PENDING" (only APPROVED|REJECTED allowed) | Q31: O
A33: Confirm | B33: Return
D34: PageResponse with 2 AdminVerificationRequestDto, profiles loaded in a single batch query | F34: O
D35: Empty PageResponse; profile query skipped | G35: O
D36: Invalid status filter is ignored (no exception); full list is returned | H36: O
D37: Void; request APPROVED with reviewer, note and reviewedAt | I37: O
D38: User becomes ACTIVE and accountVerified = true | I38: O
D39: Void; request REJECTED with note | J39: O
D40: User accountVerified = false and account is LOCKED | J40: O
D41: Decision is case-insensitive: request APPROVED, reviewNote stays null | K41: O
D42: No constraint violation | O42: O
B43: Exception
D44: ResourceNotFoundException: Không tìm thấy phiếu yêu cầu xác minh với ID: 404 | L44: O
D45: BadRequestException: Phiếu yêu cầu xác minh này đã được xử lý từ trước | M45: O
D46: BadRequestException: Quyết định phê duyệt không hợp lệ: MAYBE | N46: O
D47: ConstraintViolation: Nhận xét phê duyệt tối đa 500 ký tự | P47: O
D48: ConstraintViolation: Trạng thái phê duyệt chỉ có thể là APPROVED hoặc REJECTED | Q48: O
B49: Log message
D50: Welcome notification sent to the alumni | I50: O
A52: Result | B52: Type(N : Normal, A : Abnormal, B : Boundary) | F52: N | G52: N | H52: A | I52: N | J52: N | K52: N | L52: A | M52: A | N52: A | O52: B | P52: B | Q52: A
B53: Passed/Failed | F53: P | G53: P | H53: P | I53: P | J53: P | K53: P | L53: P | M53: P | N53: P | O53: P | P53: P | Q53: P
B54: Executed Date | F54: 46210 | G54: 46210 | H54: 46210 | I54: 46210 | J54: 46210 | K54: 46210 | L54: 46210 | M54: 46210 | N54: 46210 | O54: 46210 | P54: 46210 | Q54: 46210
B55: Defect ID

Sheet FE-18
A2: Function Code | C2: FE-18 | F2: Function Name | L2: FE-18_Violation Reports & Content Moderation Queue
A3: Created By | C3: AnNH | F3: Executed By | L3: AnNH
A4: Lines of code | C4: 42 | F4: Lack of test cases | L4: =IF(Functions!E6<>"N/A",SUM(C4*Functions!E6/1000,-O7),"N/A") -> N/A
A5: Test requirement | C5: Violation report queue, filters, resolve / dismiss
A6: Passed | C6: Failed | F6: Untested | L6: N/A/B | O6: Total Test Cases
A7: =COUNTIF(F37:T37,"P") -> 7 | C7: =COUNTIF(F37:T37,"F") -> 0 | F7: =SUM(O7,-A7,-C7) -> 0 | L7: =COUNTIF(F36:T36,"N") -> 4 | M7: =COUNTIF(F36:T36,"A") -> 3 | N7: =COUNTIF(F36:T36,"B") -> 0 | O7: =COUNTA(F9:T9) -> 7
F9: UTCID01 | G9: UTCID02 | H9: UTCID03 | I9: UTCID04 | J9: UTCID05 | K9: UTCID06 | L9: UTCID07
A10: Condition | B10: Precondition
D11: 2 reports match the filters | F11: O
D12: No report matches | G12: O
D13: Report 3 is PENDING | H13: O | I13: O
D14: Report 3 exists | J14: O | K14: O
D15: No report with id 404 | L15: O
B16: Input
D17: query="spam", author="", reason="SPAM", status="PENDING", type="GENERAL", postId=10, page=0, size=10 | F17: O
D18: all filters null, page=0, size=10 | G18: O
D19: id = 3, status = "RESOLVED" | H19: O
D20: id = 3, status = " dismissed " (lower-case with spaces) | I20: O
D21: id = 3, status = "PENDING" | J21: O
D22: id = 3, status = "FOO" | K22: O
D23: id = 404, status = "RESOLVED" | L23: O
A25: Confirm | B25: Return
D26: PageResponse with 2 AdminReportResponse and totalElements = 2 | F26: O
D27: Empty PageResponse (content=[], totalElements=0); mapper never called | G27: O
D28: Void; report.status = RESOLVED and saved | H28: O
D29: Void; status is trimmed and case-insensitive: report.status = DISMISSED | I29: O
B30: Exception
D31: BadRequestException: Không thể cập nhật báo cáo quay lại trạng thái PENDING. | J31: O
D32: BadRequestException: Trạng thái báo cáo không hợp lệ: FOO | K32: O
D33: ResourceNotFoundException: Không tìm thấy báo cáo vi phạm với ID: 404 | L33: O
B34: Log message
A36: Result | B36: Type(N : Normal, A : Abnormal, B : Boundary) | F36: N | G36: N | H36: N | I36: N | J36: A | K36: A | L36: A
B37: Passed/Failed | F37: P | G37: P | H37: P | I37: P | J37: P | K37: P | L37: P
B38: Executed Date | F38: 46265 | G38: 46265 | H38: 46265 | I38: 46265 | J38: 46265 | K38: 46265 | L38: 46265
B39: Defect ID

Sheet FE-19
A2: Function Code | C2: FE-19 | F2: Function Name | L2: FE-19_Broadcast & System Notifications Management
A3: Created By | C3: AnNH | F3: Executed By | L3: TrietNH
A4: Lines of code | C4: 163 | F4: Lack of test cases | L4: =IF(Functions!E6<>"N/A",SUM(C4*Functions!E6/1000,-O7),"N/A") -> N/A
A5: Test requirement | C5: System notification history, create, schedule, cancel, archive
A6: Passed | C6: Failed | F6: Untested | L6: N/A/B | O6: Total Test Cases
A7: =COUNTIF(F95:AH95,"P") -> 29 | C7: =COUNTIF(F95:AH95,"F") -> 0 | F7: =SUM(O7,-A7,-C7) -> 0 | L7: =COUNTIF(F94:AH94,"N") -> 13 | M7: =COUNTIF(F94:AH94,"A") -> 12 | N7: =COUNTIF(F94:AH94,"B") -> 4 | O7: =COUNTA(F9:AH9) -> 29
F9: UTCID01 | G9: UTCID02 | H9: UTCID03 | I9: UTCID04 | J9: UTCID05 | K9: UTCID06 | L9: UTCID07 | M9: UTCID08 | N9: UTCID09 | O9: UTCID10 | P9: UTCID11 | Q9: UTCID12 | R9: UTCID13 | S9: UTCID14 | T9: UTCID15 | U9: UTCID16 | V9: UTCID17 | W9: UTCID18 | X9: UTCID19 | Y9: UTCID20 | Z9: UTCID21 | AA9: UTCID22 | AB9: UTCID23 | AC9: UTCID24 | AD9: UTCID25 | AE9: UTCID26 | AF9: UTCID27 | AG9: UTCID28 | AH9: UTCID29
A10: Condition | B10: Precondition
D11: Admin exists | F11: O | G11: O | H11: O | I11: O | J11: O | K11: O | M11: O | N11: O | O11: O | P11: O | Q11: O | R11: O | S11: O | T11: O | U11: O
D12: 2 ACTIVE users in the system | F12: O
D13: Alumni users exist | G13: O
D14: User 11 exists | H14: O
D15: No admin account for the email | L15: O
D16: User 404 does not exist | N16: O
D17: No ACTIVE user for the target role | T17: O
D18: WebSocket push throws for every recipient | U18: O
D19: Notification 7 is SCHEDULED | V19: O | Z19: O
D20: Notification 7 already SENT | W20: O
D21: No notification with id 404 | X21: O
D22: Notification 7 is SENT | Y22: O
D23: Notification 7 is already ARCHIVED | AA23: O
D24: One SCHEDULED notification (ONE_DAY) is due | AB24: O
D25: No scheduled notification is due | AC25: O
D26: Two due notifications; dispatching the first one fails (user lookup throws) | AD26: O
D27: Two SENT/ACTIVE notifications are past their expiry | AE27: O
D28: No overdue notification | AF28: O
D29: 2 notifications exist | AG29: O
D30: No notification exists | AH30: O
B31: Input
D32: title/content with spaces, recipientType=ALL_USERS, durationType=ONE_DAY, isScheduled=false | F32: O
D33: recipientType=USER_ROLE, recipientRole=" alumni " (lower-case), durationType=ONE_WEEK | G33: O
D34: recipientType=SPECIFIC_USER, recipientUserId=11 | H34: O
D35: isScheduled=true, scheduledAt = now + 2 hours, durationType=ONE_DAY | I35: O
D36: durationType = FOREVER | J36: O
D37: durationType = CUSTOM, expiresAt = now + 3 days | K37: O
D38: adminEmail = ghost@fpt.edu.vn | L38: O
D39: recipientType=SPECIFIC_USER, recipientUserId = null | M39: O
D40: recipientType=SPECIFIC_USER, recipientUserId=404 | N40: O
D41: recipientType=USER_ROLE, recipientRole = " " (blank) | O41: O
D42: isScheduled=true, scheduledAt = null | P42: O
D43: isScheduled=true, scheduledAt = now - 1 second (just in the past) | Q43: O
D44: durationType = CUSTOM, expiresAt = null | R44: O
D45: isScheduled=true, scheduledAt = now + 1h, durationType = CUSTOM, expiresAt = scheduledAt (equal) | S45: O
D46: recipientType=USER_ROLE, recipientRole=STUDENT | T46: O
D47: recipientType=ALL_USERS | U47: O
D48: adminEmail, notificationId = 7 | V48: O
D49: notificationId = 7 | W49: O | Y49: O | Z49: O | AA49: O
D50: notificationId = 404 | X50: O
D51: executeScheduledNotifications() | AB51: O | AC51: O | AD51: O
D52: expireOverdueNotifications() | AE52: O | AF52: O
D53: timeFilter = "THIS_WEEK", status = SENT, page = 0, size = 10 | AG53: O
D54: timeFilter = "TODAY", page = -1, size = 0 (invalid paging values) | AH54: O
A56: Confirm | B56: Return
D57: SystemNotificationResponse; saved with trimmed title/content, status SENT, sentAt set, expiresAt = sentAt + 1 day | F57: O
D58: 2 user Notifications (SYSTEM_BROADCAST) saved and pushed over WebSocket | F58: O
D59: Role stored as "ALUMNI"; recipients loaded by role + ACTIVE status; expiresAt = sentAt + 7 days | G59: O
D60: Exactly one Notification saved for user 11 | H60: O
D61: Saved with status SCHEDULED, sentAt = null, expiresAt = scheduledAt + 1 day | I61: O
D62: Nothing is dispatched yet | I62: O
D63: expiresAt = null (notification never expires) | J63: O
D64: expiresAt kept as provided | K64: O
D65: SystemNotification is saved as SENT but no user Notification is created (warning logged) | T65: O
D66: No exception is propagated; notifications are still persisted | U66: O
D67: Void; status = CANCELLED and saved | V67: O
D68: Void; status = ARCHIVED and archivedAt set | Y68: O
D69: Notification becomes SENT with sentAt and expiresAt = sentAt + 1 day; delivered to all active users | AB69: O
D70: Nothing is saved or dispatched | AC70: O
D71: Exception is caught per item; the second notification is still processed (SENT) | AD71: O
D72: Both notifications are marked EXPIRED and saved in one saveAll | AE72: O
D73: saveAll is not called | AF73: O
D74: PageResponse with 2 SystemNotificationResponse | AG74: O
D75: Paging is clamped to page 0 / size 1; empty PageResponse is returned without exception | AH75: O
B76: Exception
D77: ResourceNotFoundException: Không tìm thấy tài khoản quản trị viên. | L77: O
D78: BadRequestException: Vui lòng chọn người dùng nhận thông báo. | M78: O
D79: ResourceNotFoundException: Không tìm thấy người dùng với ID: 404 | N79: O
D80: BadRequestException: Vui lòng chọn nhóm vai trò nhận thông báo. | O80: O
D81: BadRequestException: Vui lòng chọn thời điểm hẹn giờ gửi. | P81: O
D82: BadRequestException: Thời điểm hẹn giờ gửi phải nằm ở tương lai. | Q82: O
D83: BadRequestException: Vui lòng chọn ngày và giờ hết hạn cụ thể khi chọn thời hạn tùy chỉnh. | R83: O
D84: BadRequestException: Thời điểm hết hiệu lực (expiresAt) phải sau thời điểm gửi. | S84: O
D85: BadRequestException: Chỉ có thể hủy thông báo đang ở trạng thái hẹn giờ (SCHEDULED). | W85: O
D86: ResourceNotFoundException: Không tìm thấy thông báo hệ thống ID: 404 | X86: O
D87: BadRequestException: Không thể lưu trữ thông báo đang hẹn giờ gửi. Vui lòng hủy lịch nếu không muốn phát hành. | Z87: O
D88: BadRequestException: Thông báo này đã được lưu trữ trong kho lưu trữ trước đó. | AA88: O
B89: Log message
D90: Không có người nhận phù hợp cho thông báo hệ thống ID: 500 | T90: O
D91: Lỗi WebSocket khi gửi thông báo tới User ID ... | U91: O
D92: Lỗi khi phát hành thông báo hẹn giờ ID ... | AD92: O
A94: Result | B94: Type(N : Normal, A : Abnormal, B : Boundary) | F94: N | G94: N | H94: N | I94: N | J94: B | K94: N | L94: A | M94: A | N94: A | O94: A | P94: A | Q94: B | R94: A | S94: B | T94: N | U94: A | V94: N | W94: A | X94: A | Y94: N | Z94: A | AA94: A | AB94: N | AC94: N | AD94: A | AE94: N | AF94: N | AG94: N | AH94: B
B95: Passed/Failed | F95: P | G95: P | H95: P | I95: P | J95: P | K95: P | L95: P | M95: P | N95: P | O95: P | P95: P | Q95: P | R95: P | S95: P | T95: P | U95: P | V95: P | W95: P | X95: P | Y95: P | Z95: P | AA95: P | AB95: P | AC95: P | AD95: P | AE95: P | AF95: P | AG95: P | AH95: P
B96: Executed Date | F96: 46273 | G96: 46273 | H96: 46273 | I96: 46273 | J96: 46273 | K96: 46273 | L96: 46273 | M96: 46273 | N96: 46273 | O96: 46273 | P96: 46273 | Q96: 46273 | R96: 46273 | S96: 46273 | T96: 46273 | U96: 46273 | V96: 46273 | W96: 46273 | X96: 46273 | Y96: 46273 | Z96: 46273 | AA96: 46273 | AB96: 46273 | AC96: 46273 | AD96: 46273 | AE96: 46273 | AF96: 46273 | AG96: 46273 | AH96: 46273
B97: Defect ID

Sheet FE-20
A2: Function Code | C2: FE-20 | F2: Function Name | L2: FE-20_Create a Post on the Feed
A3: Created By | C3: AnNH | F3: Executed By | L3: HieuPT
A4: Lines of code | C4: 89 | F4: Lack of test cases | L4: =IF(Functions!E6<>"N/A",SUM(C4*Functions!E6/1000,-O7),"N/A") -> N/A
A5: Test requirement | C5: Create posts of every category with validation
A6: Passed | C6: Failed | F6: Untested | L6: N/A/B | O6: Total Test Cases
A7: =COUNTIF(F57:V57,"P") -> 17 | C7: =COUNTIF(F57:V57,"F") -> 0 | F7: =SUM(O7,-A7,-C7) -> 0 | L7: =COUNTIF(F56:V56,"N") -> 6 | M7: =COUNTIF(F56:V56,"A") -> 7 | N7: =COUNTIF(F56:V56,"B") -> 4 | O7: =COUNTA(F9:V9) -> 17
F9: UTCID01 | G9: UTCID02 | H9: UTCID03 | I9: UTCID04 | J9: UTCID05 | K9: UTCID06 | L9: UTCID07 | M9: UTCID08 | N9: UTCID09 | O9: UTCID10 | P9: UTCID11 | Q9: UTCID12 | R9: UTCID13 | S9: UTCID14 | T9: UTCID15 | U9: UTCID16 | V9: UTCID17
A10: Condition | B10: Precondition
D11: STUDENT account exists | F11: O | I11: O | J11: O | K11: O | N11: O | S11: O
D12: ALUMNI account exists | G12: O | H12: O | O12: O | P12: O | Q12: O | R12: O
D13: No account for the email | L13: O
D14: Account role is ADMIN | M14: O
D15: Database save fails | S15: O
D16: Validator applied to CreatePostRequest | T16: O | U16: O | V16: O
B17: Input
D18: CreatePostRequest(type=GENERAL, content=" Hello alumni ") | F18: O
D19: type=RECRUITMENT with JobDto(title, company, salaryMin, salaryMax, applyUrl) | G19: O
D20: type=EVENT with EventDto(title, startTime = now+2d, endTime = now+2d+2h, capacity = 50) | H20: O
D21: mediaUrls = [" a.png ", "", "b.png"] (one blank entry) | I21: O
D22: legacy imageUrl = "cover.png", mediaUrls = null | J22: O
D23: type = "normal" (legacy alias) | K23: O
D24: email = ghost@fpt.edu.vn | L24: O
D25: CreatePostRequest(GENERAL) | M25: O | S25: O
D26: type = "FOO" | N26: O
D27: type=EVENT, startTime = now - 1 day | O27: O
D28: type=EVENT, endTime earlier than startTime | P28: O
D29: type=EVENT, capacity = 0 (just below the minimum of 1) | Q29: O
D30: type=EVENT, capacity = 1 (minimum accepted) | R30: O
D31: content length = 5000 (maximum) | T31: O
D32: content length = 5001 (above maximum) | U32: O
D33: content = " " (blank) | V33: O
A35: Confirm | B35: Return
D36: PostResponse returned; Post saved ACTIVE with trimmed content, category GENERAL, 0 likes/comments/reposts | F36: O
D37: JobPosting saved with poster = author and linked through post.jobId = 80 | G37: O
D38: Event saved with organizer = author and linked through post.eventId = 70 | H38: O
D39: 2 PostMedia attached, URLs trimmed, blank skipped; sortOrder = position in the list (0 and 2) | I39: O
D40: 1 PostMedia created from imageUrl | J40: O
D41: Category mapped to GENERAL | K41: O
D42: Event saved with capacity 1 | R42: O
D43: No constraint violation | T43: O
B44: Exception
D45: ResourceNotFoundException: Không tìm thấy tài khoản người dùng | L45: O
D46: ForbiddenException: Chỉ sinh viên và cựu sinh viên mới được đăng bài viết | M46: O
D47: BadRequestException: Loại bài viết không hợp lệ: FOO | N47: O
D48: BadRequestException: Thời gian bắt đầu sự kiện không thể ở trong quá khứ. | O48: O
D49: BadRequestException: Thời gian kết thúc phải sau thời gian bắt đầu. | P49: O
D50: BadRequestException: Sức chứa sự kiện phải lớn hơn hoặc bằng 1. | Q50: O
D51: RuntimeException: Lỗi hệ thống: Không thể tạo bài viết | S51: O
D52: ConstraintViolation: Nội dung bài viết không được vượt quá 5000 ký tự | U52: O
D53: ConstraintViolation: Nội dung bài viết không được để trống | V53: O
B54: Log message
A56: Result | B56: Type(N : Normal, A : Abnormal, B : Boundary) | F56: N | G56: N | H56: N | I56: N | J56: N | K56: N | L56: A | M56: A | N56: A | O56: A | P56: A | Q56: B | R56: B | S56: A | T56: B | U56: B | V56: A
B57: Passed/Failed | F57: P | G57: P | H57: P | I57: P | J57: P | K57: P | L57: P | M57: P | N57: P | O57: P | P57: P | Q57: P | R57: P | S57: P | T57: P | U57: P | V57: P
B58: Executed Date | F58: 46223 | G58: 46223 | H58: 46223 | I58: 46223 | J58: 46223 | K58: 46223 | L58: 46223 | M58: 46223 | N58: 46223 | O58: 46223 | P58: 46223 | Q58: 46223 | R58: 46223 | S58: 46223 | T58: 46223 | U58: 46223 | V58: 46223
B59: Defect ID

Sheet FE-21
A2: Function Code | C2: FE-21 | F2: Function Name | L2: FE-21_View Feed & Post Detail
A3: Created By | C3: AnNH | F3: Executed By | L3: HuyLTN
A4: Lines of code | C4: 215 | F4: Lack of test cases | L4: =IF(Functions!E6<>"N/A",SUM(C4*Functions!E6/1000,-O7),"N/A") -> N/A
A5: Test requirement | C5: Browse and filter the feed, open post detail
A6: Passed | C6: Failed | F6: Untested | L6: N/A/B | O6: Total Test Cases
A7: =COUNTIF(F53:T53,"P") -> 13 | C7: =COUNTIF(F53:T53,"F") -> 0 | F7: =SUM(O7,-A7,-C7) -> 0 | L7: =COUNTIF(F52:T52,"N") -> 6 | M7: =COUNTIF(F52:T52,"A") -> 4 | N7: =COUNTIF(F52:T52,"B") -> 3 | O7: =COUNTA(F9:T9) -> 13
F9: UTCID01 | G9: UTCID02 | H9: UTCID03 | I9: UTCID04 | J9: UTCID05 | K9: UTCID06 | L9: UTCID07 | M9: UTCID08 | N9: UTCID09 | O9: UTCID10 | P9: UTCID11 | Q9: UTCID12 | R9: UTCID13
A10: Condition | B10: Precondition
D11: - | F11: O | G11: O | O11: O
D12: No active post matches | H12: O
D13: Two candidate posts with identical stats; viewer follows the author of post 2 | I13: O
D14: Post 1 is pinned (old), post 2 is newer and more engaging | J14: O
D15: 200 active posts exist | K15: O | L15: O
D16: Posts exist | M16: O
D17: Upcoming events exist: event 70 with its post 900 | N17: O
D18: ACTIVE post 5 exists; viewer liked and saved it | P18: O
D19: No post with id 404 | Q19: O
D20: Post 5 exists but status is HIDDEN | R20: O
B21: Input
D22: page = -1 | F22: O
D23: size = 0 (below minimum of 1) | G23: O
D24: page=0, size=10, type=ALL, keyword=null | H24: O
D25: page=0, size=10 for a logged-in viewer | I25: O
D26: page=0, size=10 | J26: O
D27: page = 15, size = 10 (first index = 150 = end of the smart-ranking window) | K27: O
D28: page = 14, size = 10 (first index = 140, still inside the smart window) | L28: O
D29: keyword = " Nguyễn Văn " (accented, spaces) | M29: O
D30: type=EVENT, eventFilter="upcoming" | N30: O
D31: type = "FOO" | O31: O
D32: id = 5, isAuthenticated = true, viewerEmail | P32: O
D33: id = 404 | Q33: O
D34: id = 5 | R34: O
A36: Confirm | B36: Return
D37: Empty PageResponse (totalElements=0, totalPages=0, last=true) | H37: O
D38: Post of the followed author (id 2) is ranked before post 1 (+100 affinity score) | I38: O
D39: Pinned post 1 is listed first regardless of score | J39: O
D40: Deep chronological feed is queried instead of smart ranking | K40: O
D41: Smart ranking is used (findCandidatesForSmartFeed), not the chronological query | L41: O
D42: Search patterns "%nguyễn văn%" and the accent-free "%nguyen van%" are passed to the repository | M42: O
D43: Events are loaded with findUpcomingEvents; the response keeps the order of events with their posts | N43: O
D44: PostResponse built with liked = true and saved = true | P44: O
B45: Exception
D46: BadRequestException: Tham số page phải là số nguyên không âm | F46: O
D47: BadRequestException: Tham số size phải là số nguyên dương | G47: O
D48: BadRequestException: Loại bài viết không hợp lệ: FOO | O48: O
D49: ResourceNotFoundException: Bài viết này không còn khả dụng | Q49: O | R49: O
B50: Log message
A52: Result | B52: Type(N : Normal, A : Abnormal, B : Boundary) | F52: A | G52: B | H52: N | I52: N | J52: N | K52: B | L52: B | M52: N | N52: N | O52: A | P52: N | Q52: A | R52: A
B53: Passed/Failed | F53: P | G53: P | H53: P | I53: P | J53: P | K53: P | L53: P | M53: P | N53: P | O53: P | P53: P | Q53: P | R53: P
B54: Executed Date | F54: 46217 | G54: 46217 | H54: 46217 | I54: 46217 | J54: 46217 | K54: 46217 | L54: 46217 | M54: 46217 | N54: 46217 | O54: 46217 | P54: 46217 | Q54: 46217 | R54: 46217
B55: Defect ID

Sheet FE-22
A2: Function Code | C2: FE-22 | F2: Function Name | L2: FE-22_Edit a Post
A3: Created By | C3: AnNH | F3: Executed By | L3: MinhVB
A4: Lines of code | C4: 135 | F4: Lack of test cases | L4: =IF(Functions!E6<>"N/A",SUM(C4*Functions!E6/1000,-O7),"N/A") -> N/A
A5: Test requirement | C5: Edit own posts
A6: Passed | C6: Failed | F6: Untested | L6: N/A/B | O6: Total Test Cases
A7: =COUNTIF(F40:T40,"P") -> 8 | C7: =COUNTIF(F40:T40,"F") -> 0 | F7: =SUM(O7,-A7,-C7) -> 0 | L7: =COUNTIF(F39:T39,"N") -> 3 | M7: =COUNTIF(F39:T39,"A") -> 3 | N7: =COUNTIF(F39:T39,"B") -> 2 | O7: =COUNTA(F9:T9) -> 8
F9: UTCID01 | G9: UTCID02 | H9: UTCID03 | I9: UTCID04 | J9: UTCID05 | K9: UTCID06 | L9: UTCID07 | M9: UTCID08
A10: Condition | B10: Precondition
D11: Alumni owns ACTIVE general post 5 | F11: O
D12: Post 5 belongs to the alumni; editor is a different student | G12: O
D13: Post 5 is linked to a CANCELLED event | H13: O
D14: Event of post 5 ended yesterday | I14: O
D15: Event of post 5 already has 10 attendees and is still upcoming | J15: O
D16: Event of post 5 has 10 attendees and is upcoming | K16: O
D17: Post 5 is an EVENT post that has no ended/cancelled event | L17: O
D18: Alumni owns post 5 with one existing image | M18: O
B19: Input
D20: id = 5, EditPostRequest(content = " Updated text ", category = GENERAL) | F20: O
D21: id = 5, EditPostRequest | G21: O | H21: O | I21: O
D22: EditPostRequest(event.capacity = 9) (one below the attendee count) | J22: O
D23: EditPostRequest(event.capacity = 10) (equal to the attendee count) | K23: O
D24: EditPostRequest(category = GENERAL) | L24: O
D25: EditPostRequest(mediaUrls = ["n1.png", "n2.png"]) | M25: O
A27: Confirm | B27: Return
D28: PostResponse; content trimmed and saved | F28: O
D29: Accepted: event capacity updated to 10 | K29: O
D30: Category changed to GENERAL and the event link (eventId) is cleared | L30: O
D31: Existing media replaced by the 2 new images with sortOrder 0 and 1 | M31: O
B32: Exception
D33: ForbiddenException: Bạn chỉ được chỉnh sửa bài viết của chính mình | G33: O
D34: BadRequestException: Sự kiện đã bị hủy, không thể chỉnh sửa thông tin. | H34: O
D35: BadRequestException: Sự kiện đã kết thúc, không thể chỉnh sửa thông tin sự kiện. | I35: O
D36: BadRequestException: Sức chứa tối đa không thể nhỏ hơn số người đã đăng ký tham gia (10 người)... | J36: O
B37: Log message
A39: Result | B39: Type(N : Normal, A : Abnormal, B : Boundary) | F39: N | G39: A | H39: A | I39: A | J39: B | K39: B | L39: N | M39: N
B40: Passed/Failed | F40: P | G40: P | H40: P | I40: P | J40: P | K40: P | L40: P | M40: P
B41: Executed Date | F41: 46245 | G41: 46245 | H41: 46245 | I41: 46245 | J41: 46245 | K41: 46245 | L41: 46245 | M41: 46245
B42: Defect ID

Sheet FE-23
A2: Function Code | C2: FE-23 | F2: Function Name | L2: FE-23_Like & Report a Post
A3: Created By | C3: AnNH | F3: Executed By | L3: AnNH
A4: Lines of code | C4: 49 | F4: Lack of test cases | L4: =IF(Functions!E6<>"N/A",SUM(C4*Functions!E6/1000,-O7),"N/A") -> N/A
A5: Test requirement | C5: Like, unlike and report posts
A6: Passed | C6: Failed | F6: Untested | L6: N/A/B | O6: Total Test Cases
A7: =COUNTIF(F59:V59,"P") -> 17 | C7: =COUNTIF(F59:V59,"F") -> 0 | F7: =SUM(O7,-A7,-C7) -> 0 | L7: =COUNTIF(F58:V58,"N") -> 5 | M7: =COUNTIF(F58:V58,"A") -> 7 | N7: =COUNTIF(F58:V58,"B") -> 5 | O7: =COUNTA(F9:V9) -> 17
F9: UTCID01 | G9: UTCID02 | H9: UTCID03 | I9: UTCID04 | J9: UTCID05 | K9: UTCID06 | L9: UTCID07 | M9: UTCID08 | N9: UTCID09 | O9: UTCID10 | P9: UTCID11 | Q9: UTCID12 | R9: UTCID13 | S9: UTCID14 | T9: UTCID15 | U9: UTCID16 | V9: UTCID17
A10: Condition | B10: Precondition
D11: Member has not liked ACTIVE post 5 (likeCount = 3) | F11: O
D12: Member already liked post 5 | G12: O
D13: Account role is ADMIN | H13: O | T13: O
D14: Post 5 is HIDDEN | I14: O | S14: O
D15: Member liked post 5 (likeCount = 3) | J15: O
D16: Member liked post 5 but the cached likeCount is already 0 | K16: O
D17: Member never liked post 5 | L17: O
D18: Member (not the author) can see ACTIVE post 5 | M18: O
D19: Member made 0 reports in the last 10 minutes | M19: O
D20: The reporter is the author of post 5 | N20: O
D21: Member already sent 5 reports within the last 10 minutes | O21: O
D22: Member sent 4 reports within the last 10 minutes (one below the limit) | P22: O
D23: Member under the rate limit | Q23: O | R23: O
D24: Validator applied to CreatePostReportRequest | U24: O | V24: O
B25: Input
D26: email, postId = 5 | F26: O | G26: O | H26: O | I26: O | J26: O | K26: O | L26: O
D27: postId = 5, CreatePostReportRequest(reason = SPAM, description = " link spam ") | M27: O
D28: email of the author, postId = 5 | N28: O
D29: postId = 5, reason = SPAM | O29: O | S29: O
D30: postId = 5, reason = SCAM_OR_FRAUD | P30: O
D31: reason = OTHER, description = " " (blank) | Q31: O
D32: reason = "HATE" (not in ReportReason) | R32: O
D33: postId = 5 | T33: O
D34: description length = 500 (maximum) | U34: O
D35: description length = 501 (above maximum) | V35: O
A37: Confirm | B37: Return
D38: LikeResponse(liked = true, likeCount = 4); PostLike saved and like counter incremented | F38: O
D39: Idempotent: LikeResponse(liked = true) with unchanged count; nothing saved, no notification | G39: O
D40: LikeResponse(liked = false, likeCount = 2); PostLike deleted and counter decremented | J40: O
D41: likeCount never goes negative (stays 0) | K41: O
D42: No-op: LikeResponse(liked = false) and no delete is executed | L42: O
D43: ReportResponse; Report saved with status PENDING, reason SPAM and trimmed description (post is NOT hidden automatically) | M43: O
D44: Report accepted and saved | P44: O
D45: No constraint violation | U45: O
B46: Exception
D47: ForbiddenException: Chỉ sinh viên và cựu sinh viên mới được thích bài viết | H47: O
D48: ResourceNotFoundException: Bài viết này không còn khả dụng | I48: O | S48: O
D49: ForbiddenException: Bạn không thể báo cáo bài viết của chính mình | N49: O
D50: BadRequestException: Bạn đã gửi quá nhiều báo cáo. Vui lòng thử lại sau 10 phút | O50: O
D51: BadRequestException: Vui lòng mô tả lý do báo cáo khác | Q51: O
D52: BadRequestException: Vui lòng chọn lý do báo cáo | R52: O
D53: ForbiddenException: Chỉ sinh viên và cựu sinh viên mới được báo cáo bài viết | T53: O
D54: ConstraintViolation: Mô tả báo cáo không được vượt quá 500 ký tự | V54: O
B55: Log message
D56: Like notification sent to the author | F56: O
A58: Result | B58: Type(N : Normal, A : Abnormal, B : Boundary) | F58: N | G58: N | H58: A | I58: A | J58: N | K58: B | L58: N | M58: N | N58: A | O58: B | P58: B | Q58: A | R58: A | S58: A | T58: A | U58: B | V58: B
B59: Passed/Failed | F59: P | G59: P | H59: P | I59: P | J59: P | K59: P | L59: P | M59: P | N59: P | O59: P | P59: P | Q59: P | R59: P | S59: P | T59: P | U59: P | V59: P
B60: Executed Date | F60: 46265 | G60: 46265 | H60: 46265 | I60: 46265 | J60: 46265 | K60: 46265 | L60: 46265 | M60: 46265 | N60: 46265 | O60: 46265 | P60: 46265 | Q60: 46265 | R60: 46265 | S60: 46265 | T60: 46265 | U60: 46265 | V60: 46265
B61: Defect ID

Sheet FE-24
A2: Function Code | C2: FE-24 | F2: Function Name | L2: FE-24_Comment on a Post
A3: Created By | C3: AnNH | F3: Executed By | L3: TrietNH
A4: Lines of code | C4: 82 | F4: Lack of test cases | L4: =IF(Functions!E6<>"N/A",SUM(C4*Functions!E6/1000,-O7),"N/A") -> N/A
A5: Test requirement | C5: Comment, edit and delete comments
A6: Passed | C6: Failed | F6: Untested | L6: N/A/B | O6: Total Test Cases
A7: =COUNTIF(F62:W62,"P") -> 18 | C7: =COUNTIF(F62:W62,"F") -> 0 | F7: =SUM(O7,-A7,-C7) -> 0 | L7: =COUNTIF(F61:W61,"N") -> 5 | M7: =COUNTIF(F61:W61,"A") -> 8 | N7: =COUNTIF(F61:W61,"B") -> 5 | O7: =COUNTA(F9:W9) -> 18
F9: UTCID01 | G9: UTCID02 | H9: UTCID03 | I9: UTCID04 | J9: UTCID05 | K9: UTCID06 | L9: UTCID07 | M9: UTCID08 | N9: UTCID09 | O9: UTCID10 | P9: UTCID11 | Q9: UTCID12 | R9: UTCID13 | S9: UTCID14 | T9: UTCID15 | U9: UTCID16 | V9: UTCID17 | W9: UTCID18
A10: Condition | B10: Precondition
D11: Member can view ACTIVE post 5 | F11: O
D12: Comment 20 is a reply of root comment 10 on the same post | G12: O
D13: Parent comment id 404 does not exist | H13: O
D14: Parent comment 20 belongs to a different post (id 6) | I14: O
D15: Account role is ADMIN | J15: O
D16: Post 5 has 2 active comments | K16: O
D17: Post 5 exists | L17: O | M17: O
D18: Member owns ACTIVE comment 10 on post 5 | N18: O
D19: Comment 10 belongs to another user | O19: O | T19: O
D20: Comment 10 belongs to post 6, but the URL uses post 5 | P20: O
D21: Comment 10 has status DELETED | Q21: O
D22: Member owns root comment 10 with 2 ACTIVE replies | R22: O
D23: Member owns reply comment 11 (has a parent) | S23: O
D24: Post of the comment is HIDDEN | U24: O
D25: Validator applied to CreateCommentRequest | V25: O | W25: O
B26: Input
D27: CreateCommentRequest(content = " Great post ", parentId = null) | F27: O
D28: CreateCommentRequest(parentId = 20) | G28: O
D29: CreateCommentRequest(parentId = 404) | H29: O
D30: postId = 5, CreateCommentRequest(parentId = 20) | I30: O
D31: CreateCommentRequest(content) | J31: O
D32: postId = 5, page = 0, size = 10, isAuthenticated = false | K32: O
D33: page = -1 | L33: O
D34: size = 0 | M34: O
D35: postId = 5, commentId = 10, UpdateCommentRequest(content = " edited ") | N35: O
D36: postId = 5, commentId = 10 | O36: O | P36: O | Q36: O | R36: O | T36: O | U36: O
D37: postId = 5, commentId = 11 | S37: O
D38: content length = 2000 (maximum) | V38: O
D39: content length = 2001 (above maximum) | W39: O
A41: Confirm | B41: Return
D42: CommentResponse; Comment saved ACTIVE with trimmed content and no parent; comment counter incremented | F42: O
D43: New comment is attached to the root comment 10 (replies are flattened to one level) | G43: O
D44: PageResponse with 2 CommentResponse (guest can read comments) | K44: O
D45: CommentResponse; content trimmed and saved | N45: O
D46: Void; comment deleted and the comment counter decremented by 3 (root + 2 replies) | R46: O
D47: Counter decremented by exactly 1 (replies of a reply are not counted) | S47: O
D48: No constraint violation | V48: O
B49: Exception
D50: ResourceNotFoundException: Bình luận cần trả lời không còn khả dụng | H50: O | I50: O
D51: ForbiddenException: Chỉ sinh viên và cựu sinh viên mới được bình luận | J51: O
D52: BadRequestException: Tham số page phải là số nguyên không âm | L52: O
D53: BadRequestException: Tham số size phải là số nguyên dương | M53: O
D54: ForbiddenException: Bạn chỉ được chỉnh sửa bình luận của chính mình | O54: O
D55: ResourceNotFoundException: Bình luận này không còn khả dụng | P55: O | Q55: O | U55: O
D56: ForbiddenException: Bạn chỉ được xóa bình luận của chính mình | T56: O
D57: ConstraintViolation: Nội dung bình luận không được vượt quá 2000 ký tự | W57: O
B58: Log message
D59: Comment notification sent to the post author | F59: O
A61: Result | B61: Type(N : Normal, A : Abnormal, B : Boundary) | F61: N | G61: N | H61: A | I61: A | J61: A | K61: N | L61: B | M61: B | N61: N | O61: A | P61: A | Q61: A | R61: N | S61: B | T61: A | U61: A | V61: B | W61: B
B62: Passed/Failed | F62: P | G62: P | H62: P | I62: P | J62: P | K62: P | L62: P | M62: P | N62: P | O62: P | P62: P | Q62: P | R62: P | S62: P | T62: P | U62: P | V62: P | W62: P
B63: Executed Date | F63: 46266 | G63: 46266 | H63: 46266 | I63: 46266 | J63: 46266 | K63: 46266 | L63: 46266 | M63: 46266 | N63: 46266 | O63: 46266 | P63: 46266 | Q63: 46266 | R63: 46266 | S63: 46266 | T63: 46266 | U63: 46266 | V63: 46266 | W63: 46266
B64: Defect ID

Sheet FE-25
A2: Function Code | C2: FE-25 | F2: Function Name | L2: FE-25_Bookmark Posts (Save / View Saved)
A3: Created By | C3: AnNH | F3: Executed By | L3: HieuPT
A4: Lines of code | C4: 67 | F4: Lack of test cases | L4: =IF(Functions!E6<>"N/A",SUM(C4*Functions!E6/1000,-O7),"N/A") -> N/A
A5: Test requirement | C5: Save posts and view saved posts
A6: Passed | C6: Failed | F6: Untested | L6: N/A/B | O6: Total Test Cases
A7: =COUNTIF(F31:T31,"P") -> 5 | C7: =COUNTIF(F31:T31,"F") -> 0 | F7: =SUM(O7,-A7,-C7) -> 0 | L7: =COUNTIF(F30:T30,"N") -> 4 | M7: =COUNTIF(F30:T30,"A") -> 1 | N7: =COUNTIF(F30:T30,"B") -> 0 | O7: =COUNTA(F9:T9) -> 5
F9: UTCID01 | G9: UTCID02 | H9: UTCID03 | I9: UTCID04 | J9: UTCID05
A10: Condition | B10: Precondition
D11: Member has not saved post 5 | F11: O
D12: Member already saved post 5 | G12: O
D13: Member saved post 5 | H13: O
D14: Member has 2 saved ACTIVE posts | I14: O
D15: - | J15: O
B16: Input
D17: email, postId = 5 | F17: O | G17: O | H17: O
D18: email, page = 0, size = 10 | I18: O
D19: page = -1 | J19: O
A21: Confirm | B21: Return
D22: SavePostResponse(saved = true); PostSave row created | F22: O
D23: Idempotent: SavePostResponse(saved = true), no duplicate row | G23: O
D24: SavePostResponse(saved = false); bookmark removed | H24: O
D25: PageResponse with 2 PostResponse, each mapped with saved = true | I25: O
B26: Exception
D27: BadRequestException: Tham số page phải là số nguyên không âm | J27: O
B28: Log message
A30: Result | B30: Type(N : Normal, A : Abnormal, B : Boundary) | F30: N | G30: N | H30: N | I30: N | J30: A
B31: Passed/Failed | F31: P | G31: P | H31: P | I31: P | J31: P
B32: Executed Date | F32: 46265 | G32: 46265 | H32: 46265 | I32: 46265 | J32: 46265
B33: Defect ID

Sheet FE-26
A2: Function Code | C2: FE-26 | F2: Function Name | L2: FE-26_Event Attendance & RSVP Management
A3: Created By | C3: AnNH | F3: Executed By | L3: HuyLTN
A4: Lines of code | C4: 149 | F4: Lack of test cases | L4: =IF(Functions!E6<>"N/A",SUM(C4*Functions!E6/1000,-O7),"N/A") -> N/A
A5: Test requirement | C5: RSVP to events, cancel RSVP and view attendees
A6: Passed | C6: Failed | F6: Untested | L6: N/A/B | O6: Total Test Cases
A7: =COUNTIF(F79:AH79,"P") -> 29 | C7: =COUNTIF(F79:AH79,"F") -> 0 | F7: =SUM(O7,-A7,-C7) -> 0 | L7: =COUNTIF(F78:AH78,"N") -> 11 | M7: =COUNTIF(F78:AH78,"A") -> 11 | N7: =COUNTIF(F78:AH78,"B") -> 7 | O7: =COUNTA(F9:AH9) -> 29
F9: UTCID01 | G9: UTCID02 | H9: UTCID03 | I9: UTCID04 | J9: UTCID05 | K9: UTCID06 | L9: UTCID07 | M9: UTCID08 | N9: UTCID09 | O9: UTCID10 | P9: UTCID11 | Q9: UTCID12 | R9: UTCID13 | S9: UTCID14 | T9: UTCID15 | U9: UTCID16 | V9: UTCID17 | W9: UTCID18 | X9: UTCID19 | Y9: UTCID20 | Z9: UTCID21 | AA9: UTCID22 | AB9: UTCID23 | AC9: UTCID24 | AD9: UTCID25 | AE9: UTCID26 | AF9: UTCID27 | AG9: UTCID28 | AH9: UTCID29
A10: Condition | B10: Precondition
D11: STUDENT is not registered | F11: O
D12: Event ACTIVE, upcoming, capacity 10, 3 attendees | F12: O
D13: STUDENT previously cancelled (registration status CANCELLED) | G13: O
D14: STUDENT already REGISTERED | H14: O
D15: Event status is CANCELLED | I15: O
D16: Event started 1 second ago | J16: O | S16: O
D17: Capacity 10 and attendeeCount = 10 (full) | K17: O
D18: Capacity 10 and attendeeCount = 9 (one seat left) | L18: O
D19: Event capacity = null (unlimited) with 500 attendees | M19: O
D20: Counter update affects 0 rows because another user took the last seat concurrently | N20: O
D21: Account role is ADMIN | O21: O | W21: O
D22: Event id 404 does not exist | P22: O | Z22: O | AH22: O
D23: STUDENT is REGISTERED; event upcoming with 3 attendees | Q23: O
D24: Event is CANCELLED | R24: O
D25: STUDENT never registered | T25: O
D26: Registration already CANCELLED | U26: O
D27: Registration REGISTERED but cached attendeeCount = 0 | V27: O
D28: STUDENT is REGISTERED for event 70 | X28: O
D29: Guest visitor (email = null) | Y29: O
D30: 2 REGISTERED attendees: alumni with headline, student without headline but with major | AA30: O
D31: Attendees: 1 ALUMNI and 1 STUDENT | AB31: O | AC31: O
D32: Attendees named "Nguyen Van A" and "Tran Thi B" | AD32: O
D33: Attendee has no profile row | AE33: O
D34: Event is CANCELLED and has both REGISTERED and CANCELLED registrations | AF34: O
D35: Event has no registration | AG35: O
B36: Input
D37: eventId = 70, email | F37: O | G37: O | H37: O | I37: O | J37: O | K37: O | L37: O | M37: O | N37: O | Q37: O | R37: O | S37: O | T37: O | U37: O | V37: O | X37: O
D38: eventId = 70, email of admin | O38: O | W38: O
D39: eventId = 404, email | P39: O
D40: eventId = 70, email = null | Y40: O
D41: eventId = 404 | Z41: O | AH41: O
D42: eventId = 70 | AA42: O | AE42: O | AF42: O | AG42: O
D43: eventId = 70, role = "alumni", search = null | AB43: O
D44: eventId = 70, role = "ALL" | AC44: O
D45: eventId = 70, search = " NGUYEN " | AD45: O
A47: Confirm | B47: Return
D48: EventRegistrationResponse(registered = true, attendeeCount = 4, capacity = 10, message "Đăng ký tham gia sự kiện thành công!") | F48: O
D49: EventRegistration saved with status REGISTERED; attendee counter incremented atomically | F49: O
D50: Existing registration reused: status back to REGISTERED, no second row is created | G50: O
D51: Registration accepted; attendeeCount in the response = 10 | L51: O
D52: Registration accepted; capacity in response is null | M52: O
D53: EventRegistrationResponse(registered = false, attendeeCount = 2, message "Hủy đăng ký tham gia sự kiện thành công!") | Q53: O
D54: Registration status = CANCELLED, attendee counter decremented | Q54: O
D55: Returned attendeeCount never negative (0) | V55: O
D56: registered = true, attendeeCount = 3, capacity = 10 | X56: O
D57: registered = false with attendee counters (no user lookup) | Y57: O
D58: List of 2 EventAttendeeResponse ordered by registration time; student headline falls back to the major name | AA58: O
D59: Only the ALUMNI attendee is returned (role filter is case-insensitive) | AB59: O
D60: "ALL" means no role filter: both attendees returned | AC60: O
D61: Case-insensitive, trimmed search keeps only "Nguyen Van A" | AD61: O
D62: fullName falls back to the e-mail address, headline empty | AE62: O
D63: All registrations are listed (findByEventIdOrderByCreatedAtAsc) so the organiser still sees who had registered | AF63: O
D64: Empty list without querying profiles | AG64: O
B65: Exception
D66: ConflictException: Bạn đã đăng ký tham gia sự kiện này rồi. | H66: O
D67: BadRequestException: Sự kiện này đã bị hủy, không thể đăng ký. | I67: O
D68: BadRequestException: Sự kiện đã bắt đầu, không thể đăng ký tham gia. | J68: O
D69: BadRequestException: Sự kiện đã đủ số lượng người tham gia. | K69: O | N69: O
D70: ForbiddenException: Chỉ sinh viên và cựu sinh viên mới được đăng ký tham gia sự kiện | O70: O
D71: ResourceNotFoundException: Không tìm thấy sự kiện | P71: O | Z71: O | AH71: O
D72: BadRequestException: Sự kiện này đã bị hủy. | R72: O
D73: BadRequestException: Sự kiện đã bắt đầu hoặc đã kết thúc, không thể hủy đăng ký. | S73: O
D74: BadRequestException: Bạn chưa đăng ký tham gia sự kiện này. | T74: O | U74: O
D75: ForbiddenException: Chỉ sinh viên và cựu sinh viên mới được hủy đăng ký tham gia sự kiện | W75: O
B76: Log message
A78: Result | B78: Type(N : Normal, A : Abnormal, B : Boundary) | F78: N | G78: N | H78: A | I78: A | J78: B | K78: B | L78: B | M78: B | N78: A | O78: A | P78: A | Q78: N | R78: A | S78: B | T78: A | U78: A | V78: B | W78: A | X78: N | Y78: N | Z78: A | AA78: N | AB78: N | AC78: B | AD78: N | AE78: N | AF78: N | AG78: N | AH78: A
B79: Passed/Failed | F79: P | G79: P | H79: P | I79: P | J79: P | K79: P | L79: P | M79: P | N79: P | O79: P | P79: P | Q79: P | R79: P | S79: P | T79: P | U79: P | V79: P | W79: P | X79: P | Y79: P | Z79: P | AA79: P | AB79: P | AC79: P | AD79: P | AE79: P | AF79: P | AG79: P | AH79: P
B80: Executed Date | F80: 46273 | G80: 46273 | H80: 46273 | I80: 46273 | J80: 46273 | K80: 46273 | L80: 46273 | M80: 46273 | N80: 46273 | O80: 46273 | P80: 46273 | Q80: 46273 | R80: 46273 | S80: 46273 | T80: 46273 | U80: 46273 | V80: 46273 | W80: 46273 | X80: 46273 | Y80: 46273 | Z80: 46273 | AA80: 46273 | AB80: 46273 | AC80: 46273 | AD80: 46273 | AE80: 46273 | AF80: 46273 | AG80: 46273 | AH80: 46273
B81: Defect ID

Sheet FE-27
A2: Function Code | C2: FE-27 | F2: Function Name | L2: FE-27_Event Lifecycle & Attendance History
A3: Created By | C3: AnNH | F3: Executed By | L3: MinhVB
A4: Lines of code | C4: 121 | F4: Lack of test cases | L4: =IF(Functions!E6<>"N/A",SUM(C4*Functions!E6/1000,-O7),"N/A") -> N/A
A5: Test requirement | C5: Cancel events and view attended-event history
A6: Passed | C6: Failed | F6: Untested | L6: N/A/B | O6: Total Test Cases
A7: =COUNTIF(F73:Z73,"P") -> 21 | C7: =COUNTIF(F73:Z73,"F") -> 0 | F7: =SUM(O7,-A7,-C7) -> 0 | L7: =COUNTIF(F72:Z72,"N") -> 10 | M7: =COUNTIF(F72:Z72,"A") -> 7 | N7: =COUNTIF(F72:Z72,"B") -> 4 | O7: =COUNTA(F9:Z9) -> 21
F9: UTCID01 | G9: UTCID02 | H9: UTCID03 | I9: UTCID04 | J9: UTCID05 | K9: UTCID06 | L9: UTCID07 | M9: UTCID08 | N9: UTCID09 | O9: UTCID10 | P9: UTCID11 | Q9: UTCID12 | R9: UTCID13 | S9: UTCID14 | T9: UTCID15 | U9: UTCID16 | V9: UTCID17 | W9: UTCID18 | X9: UTCID19 | Y9: UTCID20 | Z9: UTCID21
A10: Condition | B10: Precondition
D11: The ALUMNI organiser owns upcoming ACTIVE event 70 with registrations | F11: O
D12: Logged-in user is an ADMIN who is not the organiser | G12: O
D13: Logged-in user is a STUDENT | H13: O
D14: Another ALUMNI (not the organiser) tries to cancel event 70 | I14: O
D15: Event 70 is already CANCELLED | J15: O
D16: Event started 1 second ago | K16: O
D17: Event id 404 does not exist | L17: O
D18: No account for the email | M18: O
D19: Registered event starts in 2 days | N19: O
D20: Registered event ended yesterday | O20: O
D21: Registered event started 1 hour ago and ends in 1 hour | P21: O
D22: The event itself is CANCELLED | Q22: O
D23: Event ACTIVE but the member cancelled the registration | R23: O
D24: Member never joined any event | S24: O
D25: - | T25: O | U25: O | V25: O | W25: O | X25: O
D26: The event has an ACTIVE post with 2 images | Y26: O
D27: Account role is ADMIN | Z27: O
B28: Input
D29: eventId = 70, email of the organiser | F29: O
D30: eventId = 70, email of admin | G30: O
D31: eventId = 70, email of student | H31: O
D32: eventId = 70, email of another alumni | I32: O
D33: eventId = 70, organiser email | J33: O | K33: O
D34: eventId = 404, organiser email | L34: O
D35: eventId = 70, email = ghost@fpt.edu.vn | M35: O
D36: email, page = 0, size = 10, filter = "all" | N36: O
D37: email, filter = "all" | O37: O | P37: O | Q37: O | R37: O | Y37: O
D38: email, page = 0, size = 10 | S38: O
D39: size = 51 (above the maximum of 50) | T39: O
D40: size = 50 (maximum accepted) | U40: O
D41: page = -3 | V41: O
D42: filter = "banana" (unsupported) | W42: O
D43: filter = " PAST " (upper-case with spaces) | X43: O
D44: email of admin | Z44: O
A46: Confirm | B46: Return
D47: EventCancelResponse(status = CANCELLED, message "Hủy sự kiện thành công!") | F47: O
D48: Event status = CANCELLED; all registrations are cancelled (cancelAllByEventId) | F48: O
D49: Admin may cancel any event: status = CANCELLED | G49: O
D50: attendanceState = UPCOMING | N50: O
D51: attendanceState = PAST | O51: O
D52: attendanceState = ONGOING | P52: O
D53: attendanceState = EVENT_CANCELLED (takes priority over the registration status) | Q53: O
D54: attendanceState = REGISTRATION_CANCELLED | R54: O
D55: Empty PageResponse (content = [], last = true); organiser/post lookups skipped | S55: O
D56: Page size falls back to the default 10 | T56: O
D57: Page size is kept at 50 | U57: O
D58: Negative page index is clamped to 0 | V58: O
D59: Filter normalised to "all" before querying the repository | W59: O
D60: Filter normalised to "past" | X60: O
D61: EventHistoryResponse carries postId and coverUrl = first image of the post, organizer name from profile | Y61: O
B62: Exception
D63: ForbiddenException: Chỉ cựu sinh viên (người tổ chức) mới có quyền hủy sự kiện. | H63: O
D64: ForbiddenException: Bạn không có quyền hủy sự kiện này vì không phải là người tổ chức. | I64: O
D65: BadRequestException: Sự kiện này đã bị hủy trước đó. | J65: O
D66: BadRequestException: Sự kiện đã kết thúc hoặc đang diễn ra, không thể hủy. | K66: O
D67: ResourceNotFoundException: Không tìm thấy sự kiện | L67: O
D68: ResourceNotFoundException: Không tìm thấy tài khoản người dùng | M68: O
D69: ForbiddenException: Chỉ sinh viên và cựu sinh viên mới có lịch sử tham gia sự kiện | Z69: O
B70: Log message
A72: Result | B72: Type(N : Normal, A : Abnormal, B : Boundary) | F72: N | G72: N | H72: A | I72: A | J72: A | K72: B | L72: A | M72: A | N72: N | O72: N | P72: N | Q72: N | R72: N | S72: N | T72: B | U72: B | V72: B | W72: A | X72: N | Y72: N | Z72: A
B73: Passed/Failed | F73: P | G73: P | H73: P | I73: P | J73: P | K73: P | L73: P | M73: P | N73: P | O73: P | P73: P | Q73: P | R73: P | S73: P | T73: P | U73: P | V73: P | W73: P | X73: P | Y73: P | Z73: P
B74: Executed Date | F74: 46273 | G74: 46273 | H74: 46273 | I74: 46273 | J74: 46273 | K74: 46273 | L74: 46273 | M74: 46273 | N74: 46273 | O74: 46273 | P74: 46273 | Q74: 46273 | R74: 46273 | S74: 46273 | T74: 46273 | U74: 46273 | V74: 46273 | W74: 46273 | X74: 46273 | Y74: 46273 | Z74: 46273
B75: Defect ID

Sheet FE-28
A2: Function Code | C2: FE-28 | F2: Function Name | L2: FE-28_Manage Notifications (View & Manage Notifications)
A3: Created By | C3: AnNH | F3: Executed By | L3: AnNH
A4: Lines of code | C4: 245 | F4: Lack of test cases | L4: =IF(Functions!E6<>"N/A",SUM(C4*Functions!E6/1000,-O7),"N/A") -> N/A
A5: Test requirement | C5: View notifications, unread counter and mark as read
A6: Passed | C6: Failed | F6: Untested | L6: N/A/B | O6: Total Test Cases
A7: =COUNTIF(F97:AG97,"P") -> 28 | C7: =COUNTIF(F97:AG97,"F") -> 0 | F7: =SUM(O7,-A7,-C7) -> 0 | L7: =COUNTIF(F96:AG96,"N") -> 13 | M7: =COUNTIF(F96:AG96,"A") -> 5 | N7: =COUNTIF(F96:AG96,"B") -> 10 | O7: =COUNTA(F9:AG9) -> 28
F9: UTCID01 | G9: UTCID02 | H9: UTCID03 | I9: UTCID04 | J9: UTCID05 | K9: UTCID06 | L9: UTCID07 | M9: UTCID08 | N9: UTCID09 | O9: UTCID10 | P9: UTCID11 | Q9: UTCID12 | R9: UTCID13 | S9: UTCID14 | T9: UTCID15 | U9: UTCID16 | V9: UTCID17 | W9: UTCID18 | X9: UTCID19 | Y9: UTCID20 | Z9: UTCID21 | AA9: UTCID22 | AB9: UTCID23 | AC9: UTCID24 | AD9: UTCID25 | AE9: UTCID26 | AF9: UTCID27 | AG9: UTCID28
A10: Condition | B10: Precondition
D11: User has 2 valid (non-expired) notifications | F11: O
D12: User exists | G12: O
D13: No account for the email | H13: O
D14: User has 7 valid unread notifications | I14: O
D15: Notification 9 belongs to the user | J15: O
D16: Notification 404 does not exist or belongs to someone else | K16: O
D17: User has several unread notifications | L17: O
D18: No unread like-notification exists for post 5 | M18: O
D19: An unread like-notification already exists for post 5 with senderCount = 1 | N19: O
D20: The liker is the author of the post | O20: O
D21: - | P21: O
D22: Unread like-notification with senderCount = 1 | Q22: O
D23: Unread like-notification with senderCount = 2 | R23: O
D24: Unread like-notification with senderCount = 4 | S24: O
D25: Another member comments "Great post" on the author's post 5 | T25: O
D26: Comment text length = 60 (maximum shown without truncation) | U26: O
D27: Comment text length = 61 (just above the limit) | V27: O
D28: The commenter is the author of the post | W28: O
D29: Actor follows author | X29: O
D30: Follower and following are the same user | Y30: O
D31: Question title has 60 characters | Z31: O
D32: The answerer is the author of the question | AA32: O
D33: Admin hid post 5 | AB33: O
D34: New user without welcome notification | AC34: O
D35: An unread WELCOME notification already exists | AD35: O
D36: WebSocket broker throws while pushing | AE36: O
D37: Cron tick every minute | AF37: O
D38: executeScheduledNotifications() throws | AG38: O
B39: Input
D40: email, page = 0, size = 10 | F40: O
D41: page = -5, size = 0 (invalid paging values) | G41: O
D42: email = ghost@fpt.edu.vn | H42: O
D43: email | I43: O | L43: O
D44: email, notificationId = 9 | J44: O
D45: email, notificationId = 404 | K45: O
D46: liker (full name "Nguyen Actor"), post 5 of author 1 | M46: O
D47: second liker, post 5 | N47: O
D48: liker = author, post 5 | O48: O
D49: liker = null | P49: O
D50: unliker, post 5 | Q50: O | R50: O | S50: O
D51: commenter, comment, post | T51: O
D52: commenter, comment (60 characters), post | U52: O
D53: commenter, comment (61 characters), post | V53: O
D54: commenter = author | W54: O
D55: follower = actor, following = author | X55: O | AE55: O
D56: follower = following = author | Y56: O
D57: answerer = actor, question of author, answer | Z57: O
D58: answerer = author | AA58: O
D59: post 5 of author 1 | AB59: O
D60: user | AC60: O | AD60: O
D61: processScheduledAndExpiredNotifications() | AF61: O | AG61: O
A63: Confirm | B63: Return
D64: PageResponse with 2 NotificationResponse; only non-expired notifications are queried (expiresAt >= now) | F64: O
D65: Paging clamped to page 0 / size 1; no exception | G65: O
D66: UnreadNotificationCountResponse(unreadCount = 7) | I66: O
D67: Void; one row updated (markAsReadByIdAndRecipientId returns 1) | J67: O
D68: Void; markAllAsReadByRecipientId executed for the user | L68: O
D69: New POST_LIKE notification: "Nguyen Actor đã thích bài viết của bạn.", senderCount 1, unread | M69: O
D70: Pushed to the author through WebSocket | M70: O
D71: Notifications are grouped: same row updated with senderCount = 2 and content "Nguyen Actor và 1 người khác đã thích bài viết của bạn." | N71: O
D72: No notification is created and nothing is pushed | O72: O
D73: No-op without exception | P73: O
D74: The notification row is deleted (nobody likes the post any more) | Q74: O
D75: senderCount = 1 and content "Một thành viên đã thích bài viết của bạn." | R75: O
D76: senderCount = 3 and content "Một thành viên và 2 người khác đã thích bài viết của bạn." | S76: O
D77: POST_COMMENT notification: content contains the commenter name and the comment text, targetId "5#comment-8" | T77: O
D78: Whole 60-character text is quoted, no ellipsis | U78: O
D79: Text truncated to 57 characters followed by "..." | V79: O
D80: No notification created | W80: O | Y80: O | AA80: O
D81: USER_FOLLOW notification "Nguyen Actor đã bắt đầu theo dõi bạn." with targetType USER, targetId = actor id; pushed in real time | X81: O
D82: FORUM_ANSWER notification; the title is truncated to 47 characters + "..." (limit 50) | Z82: O
D83: REPORT_RESOLVED notification sent by the system (sender = null) with the community-standard violation message | AB83: O
D84: WELCOME notification (SYSTEM / WELCOME) created and pushed | AC84: O
D85: No duplicate welcome notification is created | AD85: O
D86: No exception reaches the caller; the notification is still persisted | AE86: O
D87: executeScheduledNotifications() and expireOverdueNotifications() are both invoked | AF87: O
D88: Failure is logged and expireOverdueNotifications() still runs | AG88: O
B89: Exception
D90: ResourceNotFoundException: Không tìm thấy người dùng với email: ghost@fpt.edu.vn | H90: O
D91: ResourceNotFoundException: Không tìm thấy thông báo hoặc bạn không có quyền thao tác. | K91: O
B92: Log message
D93: Lỗi khi đẩy thông báo WebSocket tới User ID 1: ... | AE93: O
D94: Lỗi khi chạy cron job phát thông báo hẹn giờ: ... | AG94: O
A96: Result | B96: Type(N : Normal, A : Abnormal, B : Boundary) | F96: N | G96: B | H96: A | I96: N | J96: N | K96: A | L96: N | M96: N | N96: N | O96: B | P96: A | Q96: B | R96: B | S96: N | T96: N | U96: B | V96: B | W96: B | X96: N | Y96: B | Z96: N | AA96: B | AB96: N | AC96: N | AD96: B | AE96: A | AF96: N | AG96: A
B97: Passed/Failed | F97: P | G97: P | H97: P | I97: P | J97: P | K97: P | L97: P | M97: P | N97: P | O97: P | P97: P | Q97: P | R97: P | S97: P | T97: P | U97: P | V97: P | W97: P | X97: P | Y97: P | Z97: P | AA97: P | AB97: P | AC97: P | AD97: P | AE97: P | AF97: P | AG97: P
B98: Executed Date | F98: 46272 | G98: 46272 | H98: 46272 | I98: 46272 | J98: 46272 | K98: 46272 | L98: 46272 | M98: 46272 | N98: 46272 | O98: 46272 | P98: 46272 | Q98: 46272 | R98: 46272 | S98: 46272 | T98: 46272 | U98: 46272 | V98: 46272 | W98: 46272 | X98: 46272 | Y98: 46272 | Z98: 46272 | AA98: 46272 | AB98: 46272 | AC98: 46272 | AD98: 46272 | AE98: 46272 | AF98: 46272 | AG98: 46272
B99: Defect ID

Sheet FE-29
A2: Function Code | C2: FE-29 | F2: Function Name | L2: FE-29_View Conversation List (Inbox)
A3: Created By | C3: AnNH | F3: Executed By | L3: TrietNH
A4: Lines of code | C4: 227 | F4: Lack of test cases | L4: =IF(Functions!E6<>"N/A",SUM(C4*Functions!E6/1000,-O7),"N/A") -> N/A
A5: Test requirement | C5: Conversation inbox, search and message requests
A6: Passed | C6: Failed | F6: Untested | L6: N/A/B | O6: Total Test Cases
A7: =COUNTIF(F69:Z69,"P") -> 21 | C7: =COUNTIF(F69:Z69,"F") -> 0 | F7: =SUM(O7,-A7,-C7) -> 0 | L7: =COUNTIF(F68:Z68,"N") -> 14 | M7: =COUNTIF(F68:Z68,"A") -> 5 | N7: =COUNTIF(F68:Z68,"B") -> 2 | O7: =COUNTA(F9:Z9) -> 21
F9: UTCID01 | G9: UTCID02 | H9: UTCID03 | I9: UTCID04 | J9: UTCID05 | K9: UTCID06 | L9: UTCID07 | M9: UTCID08 | N9: UTCID09 | O9: UTCID10 | P9: UTCID11 | Q9: UTCID12 | R9: UTCID13 | S9: UTCID14 | T9: UTCID15 | U9: UTCID16 | V9: UTCID17 | W9: UTCID18 | X9: UTCID19 | Y9: UTCID20 | Z9: UTCID21
A10: Condition | B10: Precondition
D11: Accepted direct conversation with last message "Hello" and 3 unread messages | F11: O
D12: Conversation not yet accepted by the current user (message request from a stranger) | G12: O
D13: Same non-accepted conversation | H13: O
D14: Accepted conversation has no message yet | I14: O
D15: User has no conversation at all | J15: O
D16: Last message has no text, only an IMAGE attachment | K16: O
D17: Last message has only a VIDEO attachment | L17: O
D18: Last message has only a FILE attachment | M18: O
D19: A direct conversation between user 1 and 2 already exists (directKey "1_2") | N19: O
D20: No conversation between the two users yet | O20: O
D21: - | P21: O | Y21: O | Z21: O
D22: User 404 does not exist | Q22: O
D23: Current user id 5, target id 3 | R23: O
D24: Pending message request in conversation 10 | S24: O
D25: User is not a participant of conversation 10 | T25: O | V25: O
D26: Participant of direct conversation 10 | U26: O
D27: Conversation 99 does not exist | W27: O
D28: Native search returns 2 users (one followed, one with isFollowing = null) | X28: O
B29: Input
D30: email, tab = "primary" | F30: O | H30: O | J30: O | K30: O | L30: O | M30: O
D31: email, tab = "requests" | G31: O
D32: email, tab = null (defaults to primary) | I32: O
D33: email, targetUserId = 2 | N33: O | O33: O
D34: targetUserId = own id (1) | P34: O
D35: targetUserId = 404 | Q35: O
D36: targetUserId = 3 (smaller than own id) | R36: O
D37: email, conversationId = 10 | S37: O | T37: O | U37: O | V37: O
D38: email, conversationId = 99 | W38: O
D39: email, keyword = "nguyen" | X39: O
D40: keyword = " " (blank) | Y40: O
D41: keyword = "Nguyễn" (accented) | Z41: O
A43: Confirm | B43: Return
D44: 1 ConversationResponse: lastMessage = "Hello", unreadCount = 3, isAccepted = true | F44: O
D45: The request conversation is listed in the requests tab | G45: O
D46: Request is hidden from the primary inbox (empty list) | H46: O
D47: Conversation without messages is not listed | I47: O
D48: Empty list; no further repository queries | J48: O
D49: Preview text = "[Hình ảnh]" | K49: O
D50: Preview text = "[Video]" | L50: O
D51: Preview text = "[Tệp đính kèm]" | M51: O
D52: Existing conversation returned with last message preview and the user's accepted flag | N52: O
D53: Draft ConversationResponse (id = null, recipientId = 2, recipientName from profile); nothing is saved in the database | O53: O
D54: Direct key is built as min_max = "3_5" regardless of who opens the chat | R54: O
D55: Void; participant.isAccepted = true and saved (request moves to the primary inbox) | S55: O
D56: Void; the whole direct conversation (and its messages) is deleted | U56: O
D57: 2 ChatUserResponse; null isFollowing is mapped to false | X57: O
D58: Keyword passed to the query is null (no keyword filter), result size limit = 25 | Y58: O
D59: Accent-free patterns "nguyen%" and "% nguyen%" plus e-mail pattern "nguyễn%" are used | Z59: O
B60: Exception
D61: BadRequestException: Bạn không thể tạo cuộc trò chuyện với chính mình. | P61: O
D62: ResourceNotFoundException: Không tìm thấy người dùng với mã: 404 | Q62: O
D63: ResourceNotFoundException: Bạn không phải là thành viên của cuộc hội thoại này. | T63: O
D64: ForbiddenException: Bạn không có quyền xóa cuộc hội thoại này. | V64: O
D65: ResourceNotFoundException: Không tìm thấy cuộc hội thoại. | W65: O
B66: Log message
A68: Result | B68: Type(N : Normal, A : Abnormal, B : Boundary) | F68: N | G68: N | H68: N | I68: N | J68: N | K68: N | L68: N | M68: N | N68: N | O68: N | P68: A | Q68: A | R68: B | S68: N | T68: A | U68: N | V68: A | W68: A | X68: N | Y68: B | Z68: N
B69: Passed/Failed | F69: P | G69: P | H69: P | I69: P | J69: P | K69: P | L69: P | M69: P | N69: P | O69: P | P69: P | Q69: P | R69: P | S69: P | T69: P | U69: P | V69: P | W69: P | X69: P | Y69: P | Z69: P
B70: Executed Date | F70: 46271 | G70: 46271 | H70: 46271 | I70: 46271 | J70: 46271 | K70: 46271 | L70: 46271 | M70: 46271 | N70: 46271 | O70: 46271 | P70: 46271 | Q70: 46271 | R70: 46271 | S70: 46271 | T70: 46271 | U70: 46271 | V70: 46271 | W70: 46271 | X70: 46271 | Y70: 46271 | Z70: 46271
B71: Defect ID

Sheet FE-30
A2: Function Code | C2: FE-30 | F2: Function Name | L2: FE-30_Send a Direct Message & Chat History
A3: Created By | C3: AnNH | F3: Executed By | L3: HieuPT
A4: Lines of code | C4: 149 | F4: Lack of test cases | L4: =IF(Functions!E6<>"N/A",SUM(C4*Functions!E6/1000,-O7),"N/A") -> N/A
A5: Test requirement | C5: Send direct messages with attachments and view history
A6: Passed | C6: Failed | F6: Untested | L6: N/A/B | O6: Total Test Cases
A7: =COUNTIF(F67:W67,"P") -> 18 | C7: =COUNTIF(F67:W67,"F") -> 0 | F7: =SUM(O7,-A7,-C7) -> 0 | L7: =COUNTIF(F66:W66,"N") -> 8 | M7: =COUNTIF(F66:W66,"A") -> 9 | N7: =COUNTIF(F66:W66,"B") -> 1 | O7: =COUNTA(F9:W9) -> 18
F9: UTCID01 | G9: UTCID02 | H9: UTCID03 | I9: UTCID04 | J9: UTCID05 | K9: UTCID06 | L9: UTCID07 | M9: UTCID08 | N9: UTCID09 | O9: UTCID10 | P9: UTCID11 | Q9: UTCID12 | R9: UTCID13 | S9: UTCID14 | T9: UTCID15 | U9: UTCID16 | V9: UTCID17 | W9: UTCID18
A10: Condition | B10: Precondition
D11: Current user is a participant of conversation 10 which holds 2 messages | F11: O
D12: Current user is not a participant of conversation 10 | G12: O
D13: Sender is a participant of conversation 10 with Bob | H13: O
D14: No conversation with Bob yet | I14: O | J14: O
D15: Bob already follows the sender | I15: O
D16: Bob does NOT follow the sender (stranger) | J16: O
D17: - | K17: O | L17: O | M17: O | N17: O
D18: Recipient 404 does not exist | O18: O
D19: Conversation 99 does not exist | P19: O
D20: Conversation 10 exists but the sender is not a participant | Q20: O
D21: Sender is a participant | R21: O | S21: O
D22: The sender's participant is still a pending request (isAccepted = false) | T22: O
D23: WebSocket push to the recipient throws | U23: O
D24: Participant of conversation 10; latest message exists | V24: O
D25: User is not a participant of conversation 10 | W25: O
B26: Input
D27: email, conversationId = 10, Pageable(0, 20) | F27: O
D28: email, conversationId = 10 | G28: O | V28: O | W28: O
D29: SendMessageRequest(conversationId = 10, content = " Hi Bob ") | H29: O
D30: SendMessageRequest(recipientId = 2, content = "Hello") | I30: O | J30: O
D31: SendMessageRequest(content = null, attachments = null) | K31: O
D32: SendMessageRequest(content = " " only spaces, attachments = []) | L32: O
D33: SendMessageRequest(content = "Hi", conversationId = null, recipientId = null) | M33: O
D34: SendMessageRequest(recipientId = own id 1) | N34: O
D35: SendMessageRequest(recipientId = 404) | O35: O
D36: SendMessageRequest(conversationId = 99) | P36: O
D37: SendMessageRequest(conversationId = 10) | Q37: O
D38: content = null, attachments = [IMAGE a.png, IMAGE b.png] | R38: O
D39: content = null, attachments = [IMAGE a.png, FILE doc.pdf] | S39: O
D40: SendMessageRequest(conversationId = 10, content = "Thanks") | T40: O
D41: SendMessageRequest(conversationId = 10, content = "Hi") | U41: O
A43: Confirm | B43: Return
D44: PageResponse with 2 MessageResponse (newest first) | F44: O
D45: MessageResponse; Message saved as TEXT with trimmed content, conversation lastMessageAt updated | H45: O
D46: WebSocket push sent to Bob only | H46: O
D47: New DIRECT conversation (directKey "1_2") with 2 participants; Bob's participant isAccepted = true | I47: O
D48: Bob's participant isAccepted = false: the chat appears in Bob's message requests; sender's participant is accepted | J48: O
D49: Message type IMAGE (all attachments are images); 2 attachments saved | R49: O
D50: Message type FILE (not every attachment is an image) | S50: O
D51: Replying auto-accepts the conversation: sender participant isAccepted = true, lastReadMessage = the new message | T51: O
D52: No exception for the sender; the message remains stored | U52: O
D53: Void; participant.lastReadMessage = latest message and saved (unread counter resets) | V53: O
B54: Exception
D55: ForbiddenException: Bạn không có quyền xem tin nhắn trong cuộc hội thoại này. | G55: O
D56: BadRequestException: Tin nhắn phải có nội dung văn bản hoặc ít nhất một tệp đính kèm. | K56: O | L56: O
D57: BadRequestException: Vui lòng cung cấp mã cuộc hội thoại hoặc mã người nhận. | M57: O
D58: BadRequestException: Bạn không thể gửi tin nhắn cho chính mình. | N58: O
D59: ResourceNotFoundException: Không tìm thấy người nhận với mã: 404 | O59: O
D60: ResourceNotFoundException: Không tìm thấy cuộc hội thoại với mã: 99 | P60: O
D61: ForbiddenException: Bạn không phải là thành viên của cuộc hội thoại này. | Q61: O
D62: ForbiddenException: Bạn không phải thành viên của cuộc hội thoại này. | W62: O
B63: Log message
D64: WebSocket push failed for User 2: ... | U64: O
A66: Result | B66: Type(N : Normal, A : Abnormal, B : Boundary) | F66: N | G66: A | H66: N | I66: N | J66: N | K66: A | L66: B | M66: A | N66: A | O66: A | P66: A | Q66: A | R66: N | S66: N | T66: N | U66: A | V66: N | W66: A
B67: Passed/Failed | F67: P | G67: P | H67: P | I67: P | J67: P | K67: P | L67: P | M67: P | N67: P | O67: P | P67: P | Q67: P | R67: P | S67: P | T67: P | U67: P | V67: P | W67: P
B68: Executed Date | F68: 46270 | G68: 46270 | H68: 46270 | I68: 46270 | J68: 46270 | K68: 46270 | L68: 46270 | M68: 46270 | N68: 46270 | O68: 46270 | P68: 46270 | Q68: 46270 | R68: 46270 | S68: 46270 | T68: 46270 | U68: 46270 | V68: 46270 | W68: 46270
B69: Defect ID

Sheet FE-31
A2: Function Code | C2: FE-31 | F2: Function Name | L2: FE-31_Alumni Map (View, Filter & Profile Navigation)
A3: Created By | C3: AnNH | F3: Executed By | L3: HuyLTN
A4: Lines of code | C4: 38 | F4: Lack of test cases | L4: =IF(Functions!E6<>"N/A",SUM(C4*Functions!E6/1000,-O7),"N/A") -> N/A
A5: Test requirement | C5: View and filter the alumni map, open profiles
A6: Passed | C6: Failed | F6: Untested | L6: N/A/B | O6: Total Test Cases
A7: =COUNTIF(F36:T36,"P") -> 7 | C7: =COUNTIF(F36:T36,"F") -> 0 | F7: =SUM(O7,-A7,-C7) -> 0 | L7: =COUNTIF(F35:T35,"N") -> 5 | M7: =COUNTIF(F35:T35,"A") -> 0 | N7: =COUNTIF(F35:T35,"B") -> 2 | O7: =COUNTA(F9:T9) -> 7
F9: UTCID01 | G9: UTCID02 | H9: UTCID03 | I9: UTCID04 | J9: UTCID05 | K9: UTCID06 | L9: UTCID07
A10: Condition | B10: Precondition
D11: Guest or member opens the map without any filter | F11: O
D12: - | G12: O | H12: O | L12: O
D13: One alumnus with valid coordinates (21.0285, 105.8542) and primary job Software Engineer @ FPT Software | I13: O
D14: Three alumni are returned by the repository | J14: O
D15: No alumnus matches the filter | K15: O
B16: Input
D17: search = null, title = null, company = null, location = null, cohort = null, majorId = null | F17: O
D18: search = " Nguyen ", title = "Engineer", company = "FPT", location = "Ha Noi", cohort = 2018, majorId = 1 | G18: O
D19: search = " ", title = "", company = " ", location = "" (blank strings) | H19: O
D20: no filter | I20: O | J20: O
D21: company = "No Such Company" | K21: O
D22: title = " \t " (only whitespace characters) | L22: O
A24: Confirm | B24: Return
D25: Repository is queried with all-null filters; empty list returned when nobody has coordinates | F25: O
D26: Text filters are trimmed, lower-cased and wrapped as "%value%"; cohort and majorId are passed unchanged | G26: O
D27: Blank text filters are converted to null (no filtering) | H27: O
D28: 1 AlumniMapResponse with fullName, title, company, latitude, longitude, verifiedStatus = true, cohort 2018 and profileIdentifier = userId as text | I28: O
D29: 3 markers in the same order as the repository result | J29: O
D30: Empty list (the UI shows the empty state), no exception | K30: O
D31: Treated as blank: title pattern = null | L31: O
B32: Exception
B33: Log message
A35: Result | B35: Type(N : Normal, A : Abnormal, B : Boundary) | F35: N | G35: N | H35: B | I35: N | J35: N | K35: N | L35: B
B36: Passed/Failed | F36: P | G36: P | H36: P | I36: P | J36: P | K36: P | L36: P
B37: Executed Date | F37: 46246 | G37: 46246 | H37: 46246 | I37: 46246 | J37: 46246 | K37: 46246 | L37: 46246
B38: Defect ID

Sheet FE-32
A2: Function Code | C2: FE-32 | F2: Function Name | L2: FE-32_Manage Career Path (View & Explore Alumni Career Journey)
A3: Created By | C3: AnNH | F3: Executed By | L3: MinhVB
A4: Lines of code | C4: 110 | F4: Lack of test cases | L4: =IF(Functions!E6<>"N/A",SUM(C4*Functions!E6/1000,-O7),"N/A") -> N/A
A5: Test requirement | C5: Explore and filter alumni career paths
A6: Passed | C6: Failed | F6: Untested | L6: N/A/B | O6: Total Test Cases
A7: =COUNTIF(F55:T55,"P") -> 15 | C7: =COUNTIF(F55:T55,"F") -> 0 | F7: =SUM(O7,-A7,-C7) -> 0 | L7: =COUNTIF(F54:T54,"N") -> 8 | M7: =COUNTIF(F54:T54,"A") -> 3 | N7: =COUNTIF(F54:T54,"B") -> 4 | O7: =COUNTA(F9:T9) -> 15
F9: UTCID01 | G9: UTCID02 | H9: UTCID03 | I9: UTCID04 | J9: UTCID05 | K9: UTCID06 | L9: UTCID07 | M9: UTCID08 | N9: UTCID09 | O9: UTCID10 | P9: UTCID11 | Q9: UTCID12 | R9: UTCID13 | S9: UTCID14 | T9: UTCID15
A10: Condition | B10: Precondition
D11: 2 active alumni (ids 5, 3) match; repository returns profiles in a different order | F11: O
D12: Alumnus 5 has a primary experience "Tech Lead @ FPT Software" | G12: O
D13: Alumnus has no primary experience but two current ones started in 2020 and 2023 | H13: O
D14: Alumnus has only ended experiences (no current, no primary) | I14: O
D15: Two consecutive experiences with the same title and company (case-insensitive) | J15: O
D16: Alumnus has 5 distinct career steps | K16: O
D17: - | L17: O | M17: O
D18: No alumnus matches the filter | N18: O
D19: Matched id 9 has no profile row | O19: O
D20: Alumnus 5 is ACTIVE with 2 experiences | P20: O
D21: No profile with id 404 | Q21: O
D22: User 6 is an ACTIVE STUDENT (not an alumnus) | R22: O
D23: Alumnus 7 account is LOCKED | S23: O
D24: ACTIVE alumnus who has not entered any experience | T24: O
B25: Input
D26: search = null, ..., page = 0, size = 10 | F26: O
D27: page = 0, size = 10 | G27: O | H27: O | I27: O | J27: O | K27: O | O27: O
D28: size = 51 (above the maximum page size of 50) | L28: O
D29: size = 50 (the maximum) | M29: O
D30: company = "No Such Company" | N30: O
D31: userId = 5 | P31: O | T31: O
D32: userId = 404 | Q32: O
D33: userId = 6 | R33: O
D34: userId = 7 | S34: O
A36: Confirm | B36: Return
D37: PageResponse with 2 summaries in the order of the matched ids [5, 3], not the order of the profile query | F37: O
D38: currentTitle = Tech Lead, currentCompany = FPT Software, currentLocation = Hanoi, totalExperiences = 2 | G38: O
D39: Fallback: the most recently started current experience (2023) is the current position | H39: O
D40: currentTitle / currentCompany stay null | I40: O
D41: Consecutive duplicates are merged: career preview contains 2 steps for 3 experiences | J41: O
D42: careerPreview is limited to 4 steps while totalExperiences = 5 | K42: O
D43: Page size is capped to 50 in the repository call | L43: O
D44: Page size stays 50 | M44: O
D45: Empty PageResponse; profile and experience queries are skipped | N45: O
D46: The id without profile is skipped; remaining alumni are returned | O46: O
D47: CareerPathDetailResponse(userId = 5, fullName, experiences = 2 items) | P47: O
D48: CareerPathDetailResponse with an empty experiences list (UI shows the empty state) | T48: O
B49: Exception
D50: ResourceNotFoundException: Không tìm thấy hồ sơ người dùng với ID: 404 | Q50: O
D51: BadRequestException: Người dùng này không hoạt động hoặc không phải là cựu sinh viên | R51: O | S51: O
B52: Log message
A54: Result | B54: Type(N : Normal, A : Abnormal, B : Boundary) | F54: N | G54: N | H54: N | I54: N | J54: N | K54: B | L54: B | M54: B | N54: N | O54: N | P54: N | Q54: A | R54: A | S54: A | T54: B
B55: Passed/Failed | F55: P | G55: P | H55: P | I55: P | J55: P | K55: P | L55: P | M55: P | N55: P | O55: P | P55: P | Q55: P | R55: P | S55: P | T55: P
B56: Executed Date | F56: 46255 | G56: 46255 | H56: 46255 | I56: 46255 | J56: 46255 | K56: 46255 | L56: 46255 | M56: 46255 | N56: 46255 | O56: 46255 | P56: 46255 | Q56: 46255 | R56: 46255 | S56: 46255 | T56: 46255
B57: Defect ID

Sheet FE-33
A2: Function Code | C2: FE-33 | F2: Function Name | L2: FE-33_Manage Posts (Share, Delete & Search Posts)
A3: Created By | C3: AnNH | F3: Executed By | L3: AnNH
A4: Lines of code | C4: 274 | F4: Lack of test cases | L4: =IF(Functions!E6<>"N/A",SUM(C4*Functions!E6/1000,-O7),"N/A") -> N/A
A5: Test requirement | C5: Share, delete and search posts
A6: Passed | C6: Failed | F6: Untested | L6: N/A/B | O6: Total Test Cases
A7: =COUNTIF(F62:U62,"P") -> 16 | C7: =COUNTIF(F62:U62,"F") -> 0 | F7: =SUM(O7,-A7,-C7) -> 0 | L7: =COUNTIF(F61:U61,"N") -> 8 | M7: =COUNTIF(F61:U61,"A") -> 5 | N7: =COUNTIF(F61:U61,"B") -> 3 | O7: =COUNTA(F9:U9) -> 16
F9: UTCID01 | G9: UTCID02 | H9: UTCID03 | I9: UTCID04 | J9: UTCID05 | K9: UTCID06 | L9: UTCID07 | M9: UTCID08 | N9: UTCID09 | O9: UTCID10 | P9: UTCID11 | Q9: UTCID12 | R9: UTCID13 | S9: UTCID14 | T9: UTCID15 | U9: UTCID16
A10: Condition | B10: Precondition
D11: Alumni owns ACTIVE post 5 (no event) | F11: O
D12: Post 5 is an EVENT post linked to event 70 with registrations | G12: O
D13: Post 5 belongs to another user | H13: O
D14: Account role is ADMIN | I14: O
D15: Post 404 does not exist | J15: O
D16: Post 5 was already DELETED | K16: O
D17: Feed contains posts | L17: O | M17: O | N17: O
D18: No post matches the keyword | O18: O
D19: User 1 has one post | P19: O
D20: Anonymous viewer | P20: O
D21: User 1 has posts | Q21: O
D22: Viewer logged in and saved post 5 | Q22: O
D23: - | R23: O | S23: O | T23: O
D24: User 99 has no post | U24: O
B25: Input
D26: email of the owner, postId = 5 | F26: O | G26: O | K26: O
D27: email of a different student, postId = 5 | H27: O
D28: email of an admin, postId = 5 | I28: O
D29: email, postId = 404 | J29: O
D30: keyword = null | L30: O
D31: keyword = " " (only spaces) | M31: O
D32: keyword = "Hà Nội", type = "RECRUITMENT" | N32: O
D33: keyword = "zzz-no-match" | O33: O
D34: userId = 1, category = "all", page = 0, size = 10, viewerEmail = null | P34: O
D35: userId = 1, category = "achievement" (lower-case), viewerEmail | Q35: O
D36: category = "FOO" | R36: O
D37: page = -1 | S37: O
D38: size = 0 | T38: O
D39: userId = 99, page = 0, size = 10 | U39: O
A41: Confirm | B41: Return
D42: Void; post status = DELETED (soft delete) and saved | F42: O
D43: Event status = CANCELLED, all registrations cancelled (cancelAllByEventId), post status = DELETED | G43: O
D44: Empty search patterns ("", "") are used: no filtering by keyword | L44: O
D45: Blank keyword is treated like no keyword (empty patterns) | M45: O
D46: Patterns "%hà nội%" and accent-free "%ha noi%" are searched in category RECRUITMENT | N46: O
D47: Empty PageResponse with totalElements = 0 and last = true | O47: O
D48: PageResponse with 1 PostResponse; no category filter, no like/save lookup | P48: O
D49: Category parsed case-insensitively (ACHIEVEMENT); saved flag of post 5 = true | Q49: O
D50: Empty PageResponse (content = [], totalElements = 0) | U50: O
B51: Exception
D52: ForbiddenException: Bạn chỉ được xóa bài viết của chính mình | H52: O
D53: ForbiddenException: Chỉ sinh viên và cựu sinh viên mới được xóa bài viết | I53: O
D54: ResourceNotFoundException: Bài viết này không còn khả dụng | J54: O
D55: ResourceNotFoundException: Bài viết này không còn khả dụng (cannot delete twice) | K55: O
D56: BadRequestException: Loại bài viết không hợp lệ: FOO | R56: O
D57: BadRequestException: Tham số page phải là số nguyên không âm | S57: O
D58: BadRequestException: Tham số size phải là số nguyên dương | T58: O
B59: Log message
A61: Result | B61: Type(N : Normal, A : Abnormal, B : Boundary) | F61: N | G61: N | H61: A | I61: A | J61: A | K61: A | L61: N | M61: B | N61: N | O61: N | P61: N | Q61: N | R61: A | S61: B | T61: B | U61: N
B62: Passed/Failed | F62: P | G62: P | H62: P | I62: P | J62: P | K62: P | L62: P | M62: P | N62: P | O62: P | P62: P | Q62: P | R62: P | S62: P | T62: P | U62: P
B63: Executed Date | F63: 46266 | G63: 46266 | H63: 46266 | I63: 46266 | J63: 46266 | K63: 46266 | L63: 46266 | M63: 46266 | N63: 46266 | O63: 46266 | P63: 46266 | Q63: 46266 | R63: 46266 | S63: 46266 | T63: 46266 | U63: 46266
B64: Defect ID

Sheet FE-34
A2: Function Code | C2: FE-34 | F2: Function Name | L2: FE-34_Forum Q&A - View, Search & Filter Questions
A3: Created By | C3: AnNH | F3: Executed By | L3: TrietNH
A4: Lines of code | C4: 61 | F4: Lack of test cases | L4: =IF(Functions!E6<>"N/A",SUM(C4*Functions!E6/1000,-O7),"N/A") -> N/A
A5: Test requirement | C5: View, search and filter forum questions
A6: Passed | C6: Failed | F6: Untested | L6: N/A/B | O6: Total Test Cases
A7: =COUNTIF(F62:V62,"P") -> 17 | C7: =COUNTIF(F62:V62,"F") -> 0 | F7: =SUM(O7,-A7,-C7) -> 0 | L7: =COUNTIF(F61:V61,"N") -> 10 | M7: =COUNTIF(F61:V61,"A") -> 3 | N7: =COUNTIF(F61:V61,"B") -> 4 | O7: =COUNTA(F9:V9) -> 17
F9: UTCID01 | G9: UTCID02 | H9: UTCID03 | I9: UTCID04 | J9: UTCID05 | K9: UTCID06 | L9: UTCID07 | M9: UTCID08 | N9: UTCID09 | O9: UTCID10 | P9: UTCID11 | Q9: UTCID12 | R9: UTCID13 | S9: UTCID14 | T9: UTCID15 | U9: UTCID16 | V9: UTCID17
A10: Condition | B10: Precondition
D11: 2 ACTIVE questions exist; guest visitor | F11: O
D12: Questions exist | G12: O | M12: O | N12: O
D13: - | H13: O | I13: O | J13: O | K13: O | L13: O | O13: O
D14: Logged-in viewer already voted question 2 but not question 1 | P14: O
D15: Question 1 has two images | Q15: O
D16: No question matches | R16: O
D17: ACTIVE question 5 with 1 image | S17: O
D18: Question 404 does not exist or is not ACTIVE | T18: O
D19: Viewer voted question 5 | U19: O
D20: Two forum topics exist | V20: O
B21: Input
D22: page=0, size=10, sort=null, keyword=null, topicIds=null, majorIds=null, viewerEmail=null | F22: O
D23: keyword = " Java " | G23: O
D24: keyword = "50%_off\" containing the LIKE wildcards % _ and the escape character \ | H24: O
D25: keyword length = 250 (maximum) | I25: O
D26: keyword length = 251 (above maximum) | J26: O
D27: page = -1 | K27: O
D28: size = 0 | L28: O
D29: topicIds = [1, 2], majorIds = [3] | M29: O
D30: sort = "votes,answers" | N30: O
D31: sort = "foo" | O31: O
D32: viewerEmail = viewer@fpt.edu.vn | P32: O
D33: viewerEmail = null | Q33: O
D34: keyword = "zzz" | R34: O
D35: id = 5, viewerEmail = null | S35: O
D36: id = 404 | T36: O
D37: id = 5, viewerEmail | U37: O
D38: (no input) | V38: O
A40: Confirm | B40: Return
D41: PageResponse with 2 QuestionResponse; no keyword/topic/major filter, sorted by createdAt DESC (recent) | F41: O
D42: filterByKeyword = true and LIKE pattern "%java%" (trimmed, lower-case) | G42: O
D43: Wildcards are escaped: pattern "%50\%\_off\\%" so they are matched literally | H43: O
D44: Accepted and searched | I44: O
D45: filterByTopic = true with [1,2] and filterByMajor = true with [3] | M45: O
D46: Order: voteCount DESC, answerCount DESC, then createdAt DESC appended for stability | N46: O
D47: Mapper receives voted = true only for question 2 | P47: O
D48: Images are loaded in one batch and passed to the mapper in sort order | Q48: O
D49: Empty PageResponse (content=[], totalElements=0) | R49: O
D50: QuestionDetailResponse built with the question, author profile, images and voted = false | S50: O
D51: voted = true is passed to the mapper | U51: O
D52: 2 TopicResponse ordered by id ascending | V52: O
B53: Exception
D54: BadRequestException: Từ khóa tìm kiếm không được vượt quá 250 ký tự | J54: O
D55: BadRequestException: Tham số page phải là số nguyên không âm | K55: O
D56: BadRequestException: Tham số size phải là số nguyên dương | L56: O
D57: BadRequestException: Tiêu chí sắp xếp không hợp lệ: foo | O57: O
D58: ResourceNotFoundException: Không tìm thấy câu hỏi với id: 404 | T58: O
B59: Log message
A61: Result | B61: Type(N : Normal, A : Abnormal, B : Boundary) | F61: N | G61: N | H61: B | I61: B | J61: B | K61: A | L61: B | M61: N | N61: N | O61: A | P61: N | Q61: N | R61: N | S61: N | T61: A | U61: N | V61: N
B62: Passed/Failed | F62: P | G62: P | H62: P | I62: P | J62: P | K62: P | L62: P | M62: P | N62: P | O62: P | P62: P | Q62: P | R62: P | S62: P | T62: P | U62: P | V62: P
B63: Executed Date | F63: 46266 | G63: 46266 | H63: 46266 | I63: 46266 | J63: 46266 | K63: 46266 | L63: 46266 | M63: 46266 | N63: 46266 | O63: 46266 | P63: 46266 | Q63: 46266 | R63: 46266 | S63: 46266 | T63: 46266 | U63: 46266 | V63: 46266
B64: Defect ID

Sheet FE-35
A2: Function Code | C2: FE-35 | F2: Function Name | L2: FE-35_Forum Q&A - Create & Manage Questions
A3: Created By | C3: AnNH | F3: Executed By | L3: HieuPT
A4: Lines of code | C4: 82 | F4: Lack of test cases | L4: =IF(Functions!E6<>"N/A",SUM(C4*Functions!E6/1000,-O7),"N/A") -> N/A
A5: Test requirement | C5: Ask, edit and delete forum questions
A6: Passed | C6: Failed | F6: Untested | L6: N/A/B | O6: Total Test Cases
A7: =COUNTIF(F69:Z69,"P") -> 21 | C7: =COUNTIF(F69:Z69,"F") -> 0 | F7: =SUM(O7,-A7,-C7) -> 0 | L7: =COUNTIF(F68:Z68,"N") -> 5 | M7: =COUNTIF(F68:Z68,"A") -> 11 | N7: =COUNTIF(F68:Z68,"B") -> 5 | O7: =COUNTA(F9:Z9) -> 21
F9: UTCID01 | G9: UTCID02 | H9: UTCID03 | I9: UTCID04 | J9: UTCID05 | K9: UTCID06 | L9: UTCID07 | M9: UTCID08 | N9: UTCID09 | O9: UTCID10 | P9: UTCID11 | Q9: UTCID12 | R9: UTCID13 | S9: UTCID14 | T9: UTCID15 | U9: UTCID16 | V9: UTCID17 | W9: UTCID18 | X9: UTCID19 | Y9: UTCID20 | Z9: UTCID21
A10: Condition | B10: Precondition
D11: STUDENT account exists | F11: O
D12: Topic 1 and major 2 exist | G12: O
D13: No account for the email | H13: O
D14: Account role is ADMIN | I14: O
D15: Topic 99 does not exist | J15: O
D16: Major 99 does not exist | K16: O
D17: Database save fails | L17: O
D18: - | M18: O | N18: O
D19: Validator applied to CreateQuestionRequest | O19: O | P19: O | Q19: O | R19: O | S19: O
D20: The author owns ACTIVE question 7 | T20: O | X20: O
D21: Question 7 belongs to a different user | U21: O | Y21: O
D22: Question 404 does not exist or is not ACTIVE | V22: O
D23: Owner updates with topicId 99 which does not exist | W23: O
D24: Question 404 is not found / already deleted | Z24: O
B25: Input
D26: CreateQuestionRequest(title = " How to prepare? ", body = " Details ", no topic/major/images) | F26: O
D27: CreateQuestionRequest(topicId = 1, majorId = 2, imageUrls = [a.png, b.png]) | G27: O
D28: email = ghost@fpt.edu.vn | H28: O
D29: CreateQuestionRequest | I29: O | L29: O
D30: CreateQuestionRequest(topicId = 99) | J30: O
D31: CreateQuestionRequest(majorId = 99) | K31: O
D32: imageUrls with 6 entries (above MAX_IMAGES = 5) bypassing DTO validation | M32: O
D33: imageUrls = ["ok.png", " ", null, <501-character URL>] | N33: O
D34: title length = 250, body length = 10000, 5 images (all maxima) | O34: O
D35: title length = 251 | P35: O
D36: body length = 10001 | Q36: O
D37: imageUrls with 6 entries | R37: O
D38: title = " " (blank), body = "" | S38: O
D39: id = 7, UpdateQuestionRequest(title = " New title ", body = "New body", topicId = null) | T39: O
D40: id = 7 by another user | U40: O | Y40: O
D41: id = 404 | V41: O | Z41: O
D42: id = 7, topicId = 99 | W42: O
D43: id = 7 | X43: O
A45: Confirm | B45: Return
D46: QuestionDetailResponse; Question saved ACTIVE with trimmed title/body, voteCount = 0, answerCount = 0, topic = null, major = null | F46: O
D47: Question linked to the topic and the major; 2 QuestionImage rows saved with sortOrder 0 and 1 | G47: O
D48: Service keeps only the first 5 images | M48: O
D49: Blank, null and over-long (> 500 chars) URLs are discarded; only "ok.png" is stored | N49: O
D50: No constraint violation | O50: O
D51: Question updated with trimmed values, topic cleared; images replaced (old images deleted) | T51: O
D52: Void; status = DELETED (soft delete) and saved | X52: O
B53: Exception
D54: ResourceNotFoundException: Không tìm thấy tài khoản người dùng | H54: O
D55: ForbiddenException: Chỉ sinh viên và cựu sinh viên mới được đặt câu hỏi | I55: O
D56: BadRequestException: Thể loại không tồn tại | J56: O | W56: O
D57: BadRequestException: Ngành không tồn tại | K57: O
D58: RuntimeException: Lỗi hệ thống: Không thể tạo câu hỏi | L58: O
D59: ConstraintViolation: Tiêu đề câu hỏi không được vượt quá 250 ký tự | P59: O
D60: ConstraintViolation: Nội dung câu hỏi không được vượt quá 10000 ký tự | Q60: O
D61: ConstraintViolation: Chỉ được đính kèm tối đa 5 ảnh | R61: O
D62: ConstraintViolation: Tiêu đề câu hỏi không được để trống / Nội dung câu hỏi không được để trống | S62: O
D63: ForbiddenException: Chỉ tác giả mới được chỉnh sửa câu hỏi này | U63: O
D64: ResourceNotFoundException: Không tìm thấy câu hỏi với id: 404 | V64: O | Z64: O
D65: ForbiddenException: Chỉ tác giả mới được xóa câu hỏi này | Y65: O
B66: Log message
A68: Result | B68: Type(N : Normal, A : Abnormal, B : Boundary) | F68: N | G68: N | H68: A | I68: A | J68: A | K68: A | L68: A | M68: B | N68: N | O68: B | P68: B | Q68: B | R68: B | S68: A | T68: N | U68: A | V68: A | W68: A | X68: N | Y68: A | Z68: A
B69: Passed/Failed | F69: P | G69: P | H69: P | I69: P | J69: P | K69: P | L69: P | M69: P | N69: P | O69: P | P69: P | Q69: P | R69: P | S69: P | T69: P | U69: P | V69: P | W69: P | X69: P | Y69: P | Z69: P
B70: Executed Date | F70: 46266 | G70: 46266 | H70: 46266 | I70: 46266 | J70: 46266 | K70: 46266 | L70: 46266 | M70: 46266 | N70: 46266 | O70: 46266 | P70: 46266 | Q70: 46266 | R70: 46266 | S70: 46266 | T70: 46266 | U70: 46266 | V70: 46266 | W70: 46266 | X70: 46266 | Y70: 46266 | Z70: 46266
B71: Defect ID

Sheet FE-36
A2: Function Code | C2: FE-36 | F2: Function Name | L2: FE-36_Forum Q&A - Answer & Manage Answers
A3: Created By | C3: AnNH | F3: Executed By | L3: HuyLTN
A4: Lines of code | C4: 128 | F4: Lack of test cases | L4: =IF(Functions!E6<>"N/A",SUM(C4*Functions!E6/1000,-O7),"N/A") -> N/A
A5: Test requirement | C5: Answer, reply, edit and delete forum answers
A6: Passed | C6: Failed | F6: Untested | L6: N/A/B | O6: Total Test Cases
A7: =COUNTIF(F79:AC79,"P") -> 24 | C7: =COUNTIF(F79:AC79,"F") -> 0 | F7: =SUM(O7,-A7,-C7) -> 0 | L7: =COUNTIF(F78:AC78,"N") -> 7 | M7: =COUNTIF(F78:AC78,"A") -> 12 | N7: =COUNTIF(F78:AC78,"B") -> 5 | O7: =COUNTA(F9:AC9) -> 24
F9: UTCID01 | G9: UTCID02 | H9: UTCID03 | I9: UTCID04 | J9: UTCID05 | K9: UTCID06 | L9: UTCID07 | M9: UTCID08 | N9: UTCID09 | O9: UTCID10 | P9: UTCID11 | Q9: UTCID12 | R9: UTCID13 | S9: UTCID14 | T9: UTCID15 | U9: UTCID16 | V9: UTCID17 | W9: UTCID18 | X9: UTCID19 | Y9: UTCID20 | Z9: UTCID21 | AA9: UTCID22 | AB9: UTCID23 | AC9: UTCID24
A10: Condition | B10: Precondition
D11: Question 10 has top-level answers 1 and 2; answer 3 is a reply of answer 1 | F11: O
D12: - | G12: O | H12: O
D13: Question 404 does not exist or is not ACTIVE | I13: O | N13: O
D14: Question has no answer | J14: O
D15: STUDENT replies to question 10 owned by someone else (answerCount = 2) | K15: O
D16: Top-level answer 1 of question 10 exists | L16: O
D17: Account role is ADMIN | M17: O
D18: Parent answer 404 does not exist | O18: O
D19: Parent answer 1 exists but its status is DELETED | P19: O
D20: Parent answer 1 belongs to another question (id 11) | Q20: O
D21: Answer 3 is already a reply (has a parent): nesting would reach level 3 | R21: O
D22: The student owns ACTIVE answer 5 of question 10 | S22: O
D23: Answer 5 belongs to another user | T23: O | Y23: O
D24: Answer 5 belongs to question 11 while the URL uses question 10 | U24: O
D25: Answer 5 is DELETED | V25: O
D26: The student owns top-level answer 5 which has 2 ACTIVE replies (ids 6, 7); question.answerCount = 2 | W26: O
D27: The student owns reply 6 (has a parent) | X27: O
D28: Top-level answer 5 owned by the student; cached question.answerCount is already 0 | Z28: O
D29: Validator applied to CreateAnswerRequest | AA29: O | AB29: O
D30: Validator applied to UpdateAnswerRequest | AC30: O
B31: Input
D32: questionId = 10, page = 0, size = 10, viewerEmail = null | F32: O
D33: page = -1 | G33: O
D34: size = 0 | H34: O
D35: questionId = 404 | I35: O | N35: O
D36: questionId = 10, page = 0, size = 10 | J36: O
D37: questionId = 10, CreateAnswerRequest(body = " My answer ", parentId = null) | K37: O
D38: CreateAnswerRequest(body = "Reply", parentId = 1) | L38: O
D39: CreateAnswerRequest | M39: O
D40: CreateAnswerRequest(parentId = 404) | O40: O
D41: CreateAnswerRequest(parentId = 1) | P41: O
D42: questionId = 10, parentId = 1 | Q42: O
D43: CreateAnswerRequest(parentId = 3) | R43: O
D44: questionId = 10, answerId = 5, UpdateAnswerRequest(body = " edited ") | S44: O
D45: answerId = 5 | T45: O | V45: O | Y45: O | Z45: O
D46: questionId = 10, answerId = 5 | U46: O | W46: O
D47: questionId = 10, answerId = 6 | X47: O
D48: body length = 10000 (maximum) | AA48: O
D49: body length = 10001 | AB49: O
D50: body = " " (blank) | AC50: O
A52: Confirm | B52: Return
D53: PageResponse with 2 top-level AnswerResponse; the reply is nested inside answer 1 (replies of 2 are empty) | F53: O
D54: Empty PageResponse; replies query is skipped | J54: O
D55: AnswerResponse; Answer saved ACTIVE with trimmed body and 0 votes; question.answerCount = 3 | K55: O
D56: Answer notification sent to the asker | K56: O
D57: Reply saved with parent = answer 1; question.answerCount unchanged (replies are not counted) | L57: O
D58: AnswerResponse; body trimmed and saved | S58: O
D59: Void; votes of answers 5, 6, 7 are removed, replies are deleted first, answer 5 is hard-deleted, question.answerCount = 1 | W59: O
D60: Reply deleted; question.answerCount unchanged; no reply sweep executed | X60: O
D61: answerCount never goes negative (stays 0) | Z61: O
D62: No constraint violation | AA62: O
B63: Exception
D64: BadRequestException: Tham số page phải là số nguyên không âm | G64: O
D65: BadRequestException: Tham số size phải là số nguyên dương | H65: O
D66: ResourceNotFoundException: Không tìm thấy câu hỏi với id: 404 | I66: O | N66: O
D67: ForbiddenException: Chỉ sinh viên và cựu sinh viên mới được trả lời câu hỏi | M67: O
D68: BadRequestException: Câu trả lời cha không tồn tại | O68: O | P68: O
D69: BadRequestException: Câu trả lời cha không thuộc câu hỏi này | Q69: O
D70: BadRequestException: Chỉ được trả lời trực tiếp một câu trả lời gốc | R70: O
D71: ForbiddenException: Chỉ tác giả mới được chỉnh sửa câu trả lời này | T71: O
D72: ResourceNotFoundException: Không tìm thấy câu trả lời với id: 5 | U72: O | V72: O
D73: ForbiddenException: Chỉ tác giả mới được xóa câu trả lời này | Y73: O
D74: ConstraintViolation: Nội dung câu trả lời không được vượt quá 10000 ký tự | AB74: O
D75: ConstraintViolation: Nội dung câu trả lời không được để trống | AC75: O
B76: Log message
A78: Result | B78: Type(N : Normal, A : Abnormal, B : Boundary) | F78: N | G78: A | H78: B | I78: A | J78: N | K78: N | L78: N | M78: A | N78: A | O78: A | P78: A | Q78: A | R78: B | S78: N | T78: A | U78: A | V78: A | W78: N | X78: N | Y78: A | Z78: B | AA78: B | AB78: B | AC78: A
B79: Passed/Failed | F79: P | G79: P | H79: P | I79: P | J79: P | K79: P | L79: P | M79: P | N79: P | O79: P | P79: P | Q79: P | R79: P | S79: P | T79: P | U79: P | V79: P | W79: P | X79: P | Y79: P | Z79: P | AA79: P | AB79: P | AC79: P
B80: Executed Date | F80: 46272 | G80: 46272 | H80: 46272 | I80: 46272 | J80: 46272 | K80: 46272 | L80: 46272 | M80: 46272 | N80: 46272 | O80: 46272 | P80: 46272 | Q80: 46272 | R80: 46272 | S80: 46272 | T80: 46272 | U80: 46272 | V80: 46272 | W80: 46272 | X80: 46272 | Y80: 46272 | Z80: 46272 | AA80: 46272 | AB80: 46272 | AC80: 46272
B81: Defect ID

Sheet FE-37
A2: Function Code | C2: FE-37 | F2: Function Name | L2: FE-37_Forum Q&A - Voting on Questions and Answers
A3: Created By | C3: AnNH | F3: Executed By | L3: MinhVB
A4: Lines of code | C4: 60 | F4: Lack of test cases | L4: =IF(Functions!E6<>"N/A",SUM(C4*Functions!E6/1000,-O7),"N/A") -> N/A
A5: Test requirement | C5: Vote on forum questions and answers
A6: Passed | C6: Failed | F6: Untested | L6: N/A/B | O6: Total Test Cases
A7: =COUNTIF(F50:T50,"P") -> 15 | C7: =COUNTIF(F50:T50,"F") -> 0 | F7: =SUM(O7,-A7,-C7) -> 0 | L7: =COUNTIF(F49:T49,"N") -> 8 | M7: =COUNTIF(F49:T49,"A") -> 5 | N7: =COUNTIF(F49:T49,"B") -> 2 | O7: =COUNTA(F9:T9) -> 15
F9: UTCID01 | G9: UTCID02 | H9: UTCID03 | I9: UTCID04 | J9: UTCID05 | K9: UTCID06 | L9: UTCID07 | M9: UTCID08 | N9: UTCID09 | O9: UTCID10 | P9: UTCID11 | Q9: UTCID12 | R9: UTCID13 | S9: UTCID14 | T9: UTCID15
A10: Condition | B10: Precondition
D11: Member has not voted question 10 (voteCount = 4) | F11: O
D12: Member already voted question 10 | G12: O
D13: Account role is ADMIN | H13: O | Q13: O
D14: Question 404 does not exist or is not ACTIVE | I14: O
D15: Member voted question 10 (voteCount = 4) | J15: O
D16: Member never voted question 10 | K16: O
D17: Member voted but cached voteCount is 0 | L17: O
D18: Member has not voted answer 20 (voteCount = 4) | M18: O
D19: Member already voted answer 20 | N19: O
D20: Answer 20 belongs to question 10 but the URL uses question 99 | O20: O
D21: Answer 20 status is DELETED | P21: O
D22: Member voted answer 20 (voteCount = 4) | R22: O
D23: Member never voted answer 20 | S23: O
D24: Member voted answer 20 but cached voteCount is 0 | T24: O
B25: Input
D26: email, questionId = 10 | F26: O | G26: O | J26: O | K26: O | L26: O
D27: email of admin, questionId = 10 | H27: O
D28: email, questionId = 404 | I28: O
D29: email, questionId = 10, answerId = 20 | M29: O | N29: O | P29: O | R29: O | S29: O | T29: O
D30: email, questionId = 99, answerId = 20 | O30: O
D31: email of admin, questionId = 10, answerId = 20 | Q31: O
A33: Confirm | B33: Return
D34: VoteResponse(voted = true, voteCount = 5); Vote(value = 1, target QUESTION 10) saved; counter incremented in DB | F34: O
D35: Idempotent: voted = true, voteCount stays 4, no new Vote row, counter not incremented | G35: O
D36: VoteResponse(voted = false, voteCount = 3); Vote deleted and counter decremented | J36: O | R36: O
D37: No-op: voted = false, voteCount stays 4, nothing deleted | K37: O
D38: voteCount never negative (stays 0) | L38: O | T38: O
D39: VoteResponse(voted = true, voteCount = 5); Vote(target ANSWER 20) saved; counter incremented | M39: O
D40: Idempotent: voteCount stays 4; nothing saved | N40: O
D41: No-op: voteCount stays 4 | S41: O
B42: Exception
D43: ForbiddenException: Chỉ sinh viên và cựu sinh viên mới được bình chọn câu hỏi | H43: O
D44: ResourceNotFoundException: Không tìm thấy câu hỏi với id: 404 | I44: O
D45: ResourceNotFoundException: Không tìm thấy câu trả lời với id: 20 | O45: O | P45: O
D46: ForbiddenException: Chỉ sinh viên và cựu sinh viên mới được bình chọn câu trả lời | Q46: O
B47: Log message
A49: Result | B49: Type(N : Normal, A : Abnormal, B : Boundary) | F49: N | G49: N | H49: A | I49: A | J49: N | K49: N | L49: B | M49: N | N49: N | O49: A | P49: A | Q49: A | R49: N | S49: N | T49: B
B50: Passed/Failed | F50: P | G50: P | H50: P | I50: P | J50: P | K50: P | L50: P | M50: P | N50: P | O50: P | P50: P | Q50: P | R50: P | S50: P | T50: P
B51: Executed Date | F51: 46269 | G51: 46269 | H51: 46269 | I51: 46269 | J51: 46269 | K51: 46269 | L51: 46269 | M51: 46269 | N51: 46269 | O51: 46269 | P51: 46269 | Q51: 46269 | R51: 46269 | S51: 46269 | T51: 46269
B52: Defect ID

Sheet FE-38
A2: Function Code | C2: FE-38 | F2: Function Name | L2: FE-38_Salary Board - Contribute & View Recent Data
A3: Created By | C3: AnNH | F3: Executed By | L3: AnNH
A4: Lines of code | C4: 46 | F4: Lack of test cases | L4: =IF(Functions!E6<>"N/A",SUM(C4*Functions!E6/1000,-O7),"N/A") -> N/A
A5: Test requirement | C5: Contribute salary data and view recent contributions
A6: Passed | C6: Failed | F6: Untested | L6: N/A/B | O6: Total Test Cases
A7: =COUNTIF(F69:AC69,"P") -> 24 | C7: =COUNTIF(F69:AC69,"F") -> 0 | F7: =SUM(O7,-A7,-C7) -> 0 | L7: =COUNTIF(F68:AC68,"N") -> 8 | M7: =COUNTIF(F68:AC68,"A") -> 6 | N7: =COUNTIF(F68:AC68,"B") -> 10 | O7: =COUNTA(F9:AC9) -> 24
F9: UTCID01 | G9: UTCID02 | H9: UTCID03 | I9: UTCID04 | J9: UTCID05 | K9: UTCID06 | L9: UTCID07 | M9: UTCID08 | N9: UTCID09 | O9: UTCID10 | P9: UTCID11 | Q9: UTCID12 | R9: UTCID13 | S9: UTCID14 | T9: UTCID15 | U9: UTCID16 | V9: UTCID17 | W9: UTCID18 | X9: UTCID19 | Y9: UTCID20 | Z9: UTCID21 | AA9: UTCID22 | AB9: UTCID23 | AC9: UTCID24
A10: Condition | B10: Precondition
D11: ALUMNI account exists | F11: O | G11: O | I11: O | J11: O | K11: O | L11: O | P11: O | Q11: O | R11: O
D12: ALUMNI account exists; industry 4 exists | H12: O
D13: Account role is STUDENT | M13: O
D14: No account for the email | N14: O | AC14: O
D15: Industry 99 does not exist | O15: O
D16: Database save fails | S16: O
D17: Validator applied to CreateSalaryContributionRequest | T17: O | U17: O | V17: O | W17: O | X17: O | Y17: O | Z17: O | AA17: O
D18: The alumnus has 2 contributions | AB18: O
B19: Input
D20: CreateSalaryContributionRequest(jobTitle = " Backend Developer ", grossAmount = 25000000, currency = null) | F20: O
D21: currency = " usd " (lower-case with spaces) | G21: O
D22: industryId = 4, company = " FPT ", region = "Cầu Giấy, Hà Nội", locationCity = null, yearsExperience = 3 | H22: O
D23: region = "Quận 1, TP. HCM", locationCity = "Đà Nẵng" (explicit) | I23: O
D24: region = "Quận 1, TP. HCM" (HCMC abbreviation) | J24: O
D25: region = "Đà Lạt, Tỉnh Lâm Đồng" (not in the known-city list) | K25: O
D26: company = " ", region = "" (blank optional fields) | L26: O
D27: CreateSalaryContributionRequest | M27: O | S27: O
D28: email = ghost@fpt.edu.vn | N28: O | AC28: O
D29: industryId = 99 | O29: O
D30: currency = "US" (2 letters, below the 3-letter ISO format) | P30: O
D31: currency = "USDT" (4 letters, above the 3-letter ISO format) | Q31: O
D32: currency = " " (blank) | R32: O
D33: grossAmount = 0.01 (smallest allowed) | T33: O
D34: grossAmount = 0.00 | U34: O
D35: grossAmount = 1.234 (3 decimal places) | V35: O
D36: grossAmount = null | W36: O
D37: yearsExperience = 0 and 60 (both bounds) | X37: O
D38: yearsExperience = -1 and 61 (just outside the bounds) | Y38: O
D39: jobTitle length = 150 (maximum) | Z39: O
D40: jobTitle length = 151 | AA40: O
D41: email | AB41: O
A43: Confirm | B43: Return
D44: SalaryContributionResponse; contribution saved with trimmed jobTitle and default currency VND | F44: O
D45: Currency normalised to "USD" | G45: O
D46: Industry linked, company trimmed, locationCity derived from the region = "Hà Nội" | H46: O
D47: Explicit locationCity is kept ("Đà Nẵng"), not derived from the region | I47: O
D48: locationCity = "Thành Phố Hồ Chí Minh" | J48: O
D49: City taken from the last comma part with the prefix removed: "Lâm Đồng" | K49: O
D50: Blank optional fields are stored as null | L50: O
D51: Blank currency falls back to VND | R51: O
D52: No constraint violation | T52: O | Z52: O
D53: No constraint violation for 0 and for 60 | X53: O
D54: List of 2 SalaryContributionResponse (newest first, only own data) | AB54: O
B55: Exception
D56: ForbiddenException: Chỉ cựu sinh viên mới được đóng góp dữ liệu lương | M56: O
D57: ResourceNotFoundException: Không tìm thấy tài khoản người dùng | N57: O | AC57: O
D58: BadRequestException: Ngành nghề không tồn tại | O58: O
D59: BadRequestException: Đơn vị tiền tệ phải là mã 3 chữ cái (VD: VND, USD) | P59: O | Q59: O
D60: RuntimeException: Lỗi hệ thống: Không thể lưu dữ liệu lương | S60: O
D61: ConstraintViolation: Mức lương phải lớn hơn 0 | U61: O
D62: ConstraintViolation: Mức lương không hợp lệ | V62: O
D63: ConstraintViolation: Mức lương không được để trống | W63: O
D64: ConstraintViolation: Số năm kinh nghiệm không được âm / Số năm kinh nghiệm không hợp lệ | Y64: O
D65: ConstraintViolation: Chức danh công việc không được vượt quá 150 ký tự | AA65: O
B66: Log message
A68: Result | B68: Type(N : Normal, A : Abnormal, B : Boundary) | F68: N | G68: N | H68: N | I68: N | J68: N | K68: N | L68: N | M68: A | N68: A | O68: A | P68: B | Q68: B | R68: B | S68: A | T68: B | U68: B | V68: B | W68: A | X68: B | Y68: B | Z68: B | AA68: B | AB68: N | AC68: A
B69: Passed/Failed | F69: P | G69: P | H69: P | I69: P | J69: P | K69: P | L69: P | M69: P | N69: P | O69: P | P69: P | Q69: P | R69: P | S69: P | T69: P | U69: P | V69: P | W69: P | X69: P | Y69: P | Z69: P | AA69: P | AB69: P | AC69: P
B70: Executed Date | F70: 46278 | G70: 46278 | H70: 46278 | I70: 46278 | J70: 46278 | K70: 46278 | L70: 46278 | M70: 46278 | N70: 46278 | O70: 46278 | P70: 46278 | Q70: 46278 | R70: 46278 | S70: 46278 | T70: 46278 | U70: 46278 | V70: 46278 | W70: 46278 | X70: 46278 | Y70: 46278 | Z70: 46278 | AA70: 46278 | AB70: 46278 | AC70: 46278
B71: Defect ID

Sheet FE-39
A2: Function Code | C2: FE-39 | F2: Function Name | L2: FE-39_Salary Board - Edit & Delete My Data
A3: Created By | C3: AnNH | F3: Executed By | L3: TrietNH
A4: Lines of code | C4: 52 | F4: Lack of test cases | L4: =IF(Functions!E6<>"N/A",SUM(C4*Functions!E6/1000,-O7),"N/A") -> N/A
A5: Test requirement | C5: Edit and delete own salary contributions
A6: Passed | C6: Failed | F6: Untested | L6: N/A/B | O6: Total Test Cases
A7: =COUNTIF(F34:T34,"P") -> 8 | C7: =COUNTIF(F34:T34,"F") -> 0 | F7: =SUM(O7,-A7,-C7) -> 0 | L7: =COUNTIF(F33:T33,"N") -> 3 | M7: =COUNTIF(F33:T33,"A") -> 5 | N7: =COUNTIF(F33:T33,"B") -> 0 | O7: =COUNTA(F9:T9) -> 8
F9: UTCID01 | G9: UTCID02 | H9: UTCID03 | I9: UTCID04 | J9: UTCID05 | K9: UTCID06 | L9: UTCID07 | M9: UTCID08
A10: Condition | B10: Precondition
D11: The alumnus owns contribution 9 | F11: O | J11: O | K11: O
D12: Contribution 9 belongs to another alumnus | G12: O | L12: O
D13: Contribution 404 does not exist | H13: O | M13: O
D14: Contribution 9 already has locationCity "Hà Nội" | I14: O
B15: Input
D16: id = 9, UpdateSalaryContributionRequest(jobTitle = "Senior Developer", grossAmount = 40000000) | F16: O
D17: id = 9 | G17: O | K17: O | L17: O
D18: id = 404 | H18: O | M18: O
D19: UpdateSalaryContributionRequest(locationCity = null, region = "Quận 1, TP. HCM") | I19: O
D20: currency = "EURO" (4 letters) | J20: O
A22: Confirm | B22: Return
D23: SalaryContributionResponse; jobTitle and amount updated and saved | F23: O
D24: Existing locationCity "Hà Nội" is kept (not overwritten by the region guess) | I24: O
D25: Void; contribution deleted (hard delete) | K25: O
B26: Exception
D27: ForbiddenException: Chỉ chính chủ mới được chỉnh sửa lượt đóng góp này | G27: O
D28: ResourceNotFoundException: Không tìm thấy lượt đóng góp với id: 404 | H28: O | M28: O
D29: BadRequestException: Đơn vị tiền tệ phải là mã 3 chữ cái (VD: VND, USD) | J29: O
D30: ForbiddenException: Chỉ chính chủ mới được xóa lượt đóng góp này | L30: O
B31: Log message
A33: Result | B33: Type(N : Normal, A : Abnormal, B : Boundary) | F33: N | G33: A | H33: A | I33: N | J33: A | K33: N | L33: A | M33: A
B34: Passed/Failed | F34: P | G34: P | H34: P | I34: P | J34: P | K34: P | L34: P | M34: P
B35: Executed Date | F35: 46272 | G35: 46272 | H35: 46272 | I35: 46272 | J35: 46272 | K35: 46272 | L35: 46272 | M35: 46272
B36: Defect ID

Sheet FE-40
A2: Function Code | C2: FE-40 | F2: Function Name | L2: FE-40_Salary Board - Statistics & Filter
A3: Created By | C3: AnNH | F3: Executed By | L3: HieuPT
A4: Lines of code | C4: 80 | F4: Lack of test cases | L4: =IF(Functions!E6<>"N/A",SUM(C4*Functions!E6/1000,-O7),"N/A") -> N/A
A5: Test requirement | C5: View salary statistics and filter by industry / region / job title
A6: Passed | C6: Failed | F6: Untested | L6: N/A/B | O6: Total Test Cases
A7: =COUNTIF(F58:U58,"P") -> 16 | C7: =COUNTIF(F58:U58,"F") -> 0 | F7: =SUM(O7,-A7,-C7) -> 0 | L7: =COUNTIF(F57:U57,"N") -> 9 | M7: =COUNTIF(F57:U57,"A") -> 3 | N7: =COUNTIF(F57:U57,"B") -> 4 | O7: =COUNTA(F9:U9) -> 16
F9: UTCID01 | G9: UTCID02 | H9: UTCID03 | I9: UTCID04 | J9: UTCID05 | K9: UTCID06 | L9: UTCID07 | M9: UTCID08 | N9: UTCID09 | O9: UTCID10 | P9: UTCID11 | Q9: UTCID12 | R9: UTCID13 | S9: UTCID14 | T9: UTCID15 | U9: UTCID16
A10: Condition | B10: Precondition
D11: 12 contributions match; overall median 30,000,000; one group (Backend Developer / Mid / Hà Nội) with 5 samples | F11: O
D12: No contribution matches | G12: O | U12: O
D13: Industry 99 does not exist | H13: O
D14: - | I14: O | K14: O | L14: O | M14: O | N14: O | O14: O
D15: Industry 4 exists | J15: O
D16: 2 contributions exist | P16: O
D17: Contributions exist | Q17: O | R17: O | S17: O
D18: One contribution matches industry 4, region "Hà Nội", search "developer" | T18: O
B19: Input
D20: industryId = null, region = null, jobTitle = null, level = null | F20: O
D21: jobTitle = "No Such Job" | G21: O
D22: industryId = 99 | H22: O
D23: level = "Lead" (not Junior/Mid/Senior) | I23: O
D24: industryId = 4, level = " Senior " (valid with spaces) | J24: O
D25: level = " " (blank), region = " ", jobTitle = "" | K25: O
D26: region = "Hà Nội", jobTitle = "50%_dev" (contains LIKE wildcards) | L26: O
D27: getStatistics(...) with any filter | M27: O
D28: page = -1 | N28: O
D29: size = 0 | O29: O
D30: page = 0, size = 10 (default feed) | P30: O
D31: sortBy = "salaryDesc" | Q31: O
D32: sortBy = "SALARYASC" (case-insensitive) | R32: O
D33: sortBy = "unknown" | S33: O
D34: page = 0, size = 5, industryId = 4, region = " Hà Nội ", search = " developer " | T34: O
D35: search = "zzz" | U35: O
A37: Confirm | B37: Return
D38: SalaryStatisticsResponse(totalContributions = 12, trackedPositions = 1, overallMedian = 30000000, rows[0].role = Backend Developer, samples = 5, p25/median/p75) | F38: O
D39: totalContributions = 0, trackedPositions = 0, overallMedian = null, empty rows | G39: O
D40: Filters industry and level are switched on; level is trimmed to "Senior" | J40: O
D41: Blank filters are ignored: all filter flags false | K41: O
D42: LIKE patterns "%Hà Nội%" and "%50\%\_dev%" (wildcards escaped) | L42: O
D43: Grouped statistics are requested with a minimum sample size of 1 (every valid contribution is visible) | M43: O
D44: PageResponse with 2 anonymised SalaryContributionResponse sorted by createdAt DESC | P44: O
D45: Sorted by grossAmount DESC | Q45: O
D46: Sorted by grossAmount ASC | R46: O
D47: Unknown sort key falls back to createdAt DESC | S47: O
D48: PageResponse(pageNumber = 0, pageSize = 5, totalElements = 1, last = true) with 1 item | T48: O
D49: Empty PageResponse (content = [], totalElements = 0) | U49: O
B50: Exception
D51: BadRequestException: Ngành nghề không tồn tại | H51: O
D52: BadRequestException: Cấp bậc không hợp lệ (chỉ chấp nhận Junior/Mid/Senior) | I52: O
D53: BadRequestException: Tham số page phải là số nguyên không âm | N53: O
D54: BadRequestException: Tham số size phải là số nguyên dương | O54: O
B55: Log message
A57: Result | B57: Type(N : Normal, A : Abnormal, B : Boundary) | F57: N | G57: N | H57: A | I57: A | J57: N | K57: B | L57: N | M57: B | N57: A | O57: B | P57: N | Q57: N | R57: N | S57: B | T57: N | U57: N
B58: Passed/Failed | F58: P | G58: P | H58: P | I58: P | J58: P | K58: P | L58: P | M58: P | N58: P | O58: P | P58: P | Q58: P | R58: P | S58: P | T58: P | U58: P
B59: Executed Date | F59: 46273 | G59: 46273 | H59: 46273 | I59: 46273 | J59: 46273 | K59: 46273 | L59: 46273 | M59: 46273 | N59: 46273 | O59: 46273 | P59: 46273 | Q59: 46273 | R59: 46273 | S59: 46273 | T59: 46273 | U59: 46273
B60: Defect ID

Sheet FE-41
A2: Function Code | C2: FE-41 | F2: Function Name | L2: FE-41_Group Chat - Create & Update Group Profile
A3: Created By | C3: AnNH | F3: Executed By | L3: HuyLTN
A4: Lines of code | C4: 189 | F4: Lack of test cases | L4: =IF(Functions!E6<>"N/A",SUM(C4*Functions!E6/1000,-O7),"N/A") -> N/A
A5: Test requirement | C5: Create a group chat and update its name and avatar
A6: Passed | C6: Failed | F6: Untested | L6: N/A/B | O6: Total Test Cases
A7: =COUNTIF(F44:T44,"P") -> 10 | C7: =COUNTIF(F44:T44,"F") -> 0 | F7: =SUM(O7,-A7,-C7) -> 0 | L7: =COUNTIF(F43:T43,"N") -> 3 | M7: =COUNTIF(F43:T43,"A") -> 5 | N7: =COUNTIF(F43:T43,"B") -> 2 | O7: =COUNTA(F9:T9) -> 10
F9: UTCID01 | G9: UTCID02 | H9: UTCID03 | I9: UTCID04 | J9: UTCID05 | K9: UTCID06 | L9: UTCID07 | M9: UTCID08 | N9: UTCID09 | O9: UTCID10
A10: Condition | B10: Precondition
D11: Creator exists; 2 member ids exist | F11: O
D12: Creator exists; member ids contain the creator | G12: O
D13: Creator exists | H13: O | I13: O | J13: O | K13: O
D14: Creator exists; member id 99 does not exist | L14: O
D15: Group exists; caller is group ADMIN | M15: O
D16: Group exists; caller is a MEMBER | N16: O
D17: Conversation is a DIRECT conversation | O17: O
B18: Input
D19: CreateGroupRequest(title='Team A', memberIds=[2,3]) | F19: O
D20: memberIds=[1,2] (1 = creator) | G20: O
D21: title with 1 character | H21: O
D22: title with 100 characters | I22: O
D23: title with 101 characters | J23: O
D24: memberIds = [] (empty) | K24: O
D25: memberIds=[99] | L25: O
D26: UpdateGroupRequest(title='New name', avatarUrl='a.png') | M26: O
D27: UpdateGroupRequest(title='New name') | N27: O
D28: UpdateGroupRequest(title='x') | O28: O
A30: Confirm | B30: Return
D31: ConversationResponse of type GROUP; creator is ADMIN, 2 MEMBER participants and a system message saved | F31: O
D32: Creator is not duplicated in the participant list | G32: O
D33: Group created successfully | H33: O | I33: O
D34: Group updated and a system message about the change is posted | M34: O
B35: Exception
D36: Validation error: title must be 1-100 characters | J36: O
D37: Validation error: memberIds must not be empty | K37: O
D38: ResourceNotFoundException: user not found | L38: O
D39: ForbiddenException: only group admin can update the group | N39: O
D40: BadRequestException: not a group conversation | O40: O
B41: Log message
A43: Result | B43: Type(N : Normal, A : Abnormal, B : Boundary) | F43: N | G43: N | H43: B | I43: B | J43: A | K43: A | L43: A | M43: N | N43: A | O43: A
B44: Passed/Failed | F44: P | G44: P | H44: P | I44: P | J44: P | K44: P | L44: P | M44: P | N44: P | O44: P
B45: Executed Date | F45: 46294 | G45: 46294 | H45: 46294 | I45: 46294 | J45: 46294 | K45: 46294 | L45: 46294 | M45: 46294 | N45: 46294 | O45: 46294
B46: Defect ID

Sheet FE-42
A2: Function Code | C2: FE-42 | F2: Function Name | L2: FE-42_Group Chat - Manage Group Members
A3: Created By | C3: AnNH | F3: Executed By | L3: MinhVB
A4: Lines of code | C4: 280 | F4: Lack of test cases | L4: =IF(Functions!E6<>"N/A",SUM(C4*Functions!E6/1000,-O7),"N/A") -> N/A
A5: Test requirement | C5: Add / remove / leave members and dissolve a group chat
A6: Passed | C6: Failed | F6: Untested | L6: N/A/B | O6: Total Test Cases
A7: =COUNTIF(F49:T49,"P") -> 12 | C7: =COUNTIF(F49:T49,"F") -> 0 | F7: =SUM(O7,-A7,-C7) -> 0 | L7: =COUNTIF(F48:T48,"N") -> 7 | M7: =COUNTIF(F48:T48,"A") -> 5 | N7: =COUNTIF(F48:T48,"B") -> 0 | O7: =COUNTA(F9:T9) -> 12
F9: UTCID01 | G9: UTCID02 | H9: UTCID03 | I9: UTCID04 | J9: UTCID05 | K9: UTCID06 | L9: UTCID07 | M9: UTCID08 | N9: UTCID09 | O9: UTCID10 | P9: UTCID11 | Q9: UTCID12
A10: Condition | B10: Precondition
D11: Caller is group ADMIN; users 4,5 exist and are not members | F11: O
D12: Caller is a MEMBER | G12: O
D13: User 4 is already a member | H13: O
D14: Caller is ADMIN; target is MEMBER | I14: O
D15: Caller is MEMBER; target is another member | J15: O
D16: Caller is MEMBER | K16: O | P16: O
D17: Caller is ADMIN with 2+ members | L17: O
D18: Target is owner of the linked community group | M18: O
D19: Caller is the only participant | N19: O
D20: Caller is group ADMIN | O20: O
D21: Caller is a participant | Q21: O
B22: Input
D23: addMembers(groupId, [4,5]) | F23: O
D24: addMembers(groupId, [4]) | G24: O | H24: O
D25: removeMember(groupId, targetId) | I25: O | J25: O
D26: removeMember(groupId, callerId) (leave) | K26: O
D27: removeMember(groupId, callerId) | L27: O | N27: O
D28: removeMember(groupId, ownerId) | M28: O
D29: deleteConversation(groupId) | O29: O | P29: O
D30: getGroupMembers(groupId) | Q30: O
A32: Confirm | B32: Return
D33: 2 participants added and a system message posted | F33: O
D34: Already existing member is skipped; no duplicate participant | H34: O
D35: Participant removed and system message posted | I35: O
D36: Caller leaves the group and a system message is posted | K36: O
D37: Admin role is transferred to the next member | L37: O
D38: Conversation is deleted automatically | N38: O
D39: Group conversation deleted for all members | O39: O
D40: List of members with role returned | Q40: O
B41: Exception
D42: ForbiddenException: only admin can add members | G42: O
D43: ForbiddenException: only admin can remove members | J43: O
D44: BadRequestException: cannot remove community group owner | M44: O
D45: ForbiddenException: only admin can dissolve the group | P45: O
B46: Log message
A48: Result | B48: Type(N : Normal, A : Abnormal, B : Boundary) | F48: N | G48: A | H48: A | I48: N | J48: A | K48: N | L48: N | M48: A | N48: N | O48: N | P48: A | Q48: N
B49: Passed/Failed | F49: P | G49: P | H49: P | I49: P | J49: P | K49: P | L49: P | M49: P | N49: P | O49: P | P49: P | Q49: P
B50: Executed Date | F50: 46294 | G50: 46294 | H50: 46294 | I50: 46294 | J50: 46294 | K50: 46294 | L50: 46294 | M50: 46294 | N50: 46294 | O50: 46294 | P50: 46294 | Q50: 46294
B51: Defect ID

Sheet FE-43
A2: Function Code | C2: FE-43 | F2: Function Name | L2: FE-43_Community Groups - View, Search & Group Detail
A3: Created By | C3: AnNH | F3: Executed By | L3: AnNH
A4: Lines of code | C4: 33 | F4: Lack of test cases | L4: =IF(Functions!E6<>"N/A",SUM(C4*Functions!E6/1000,-O7),"N/A") -> N/A
A5: Test requirement | C5: List / search community groups, my groups and group detail
A6: Passed | C6: Failed | F6: Untested | L6: N/A/B | O6: Total Test Cases
A7: =COUNTIF(F38:T38,"P") -> 8 | C7: =COUNTIF(F38:T38,"F") -> 0 | F7: =SUM(O7,-A7,-C7) -> 0 | L7: =COUNTIF(F37:T37,"N") -> 5 | M7: =COUNTIF(F37:T37,"A") -> 2 | N7: =COUNTIF(F37:T37,"B") -> 1 | O7: =COUNTA(F9:T9) -> 8
F9: UTCID01 | G9: UTCID02 | H9: UTCID03 | I9: UTCID04 | J9: UTCID05 | K9: UTCID06 | L9: UTCID07 | M9: UTCID08
A10: Condition | B10: Precondition
D11: Groups exist | F11: O | G11: O | H11: O
D12: No group exists | I12: O
D13: User joined 2 groups | J13: O
D14: Group exists; user is a member | K14: O
D15: Group id 99 does not exist | L15: O
D16: Group is deleted | M16: O
B17: Input
D18: listGroups(keyword=null, category=null, page 0) | F18: O
D19: listGroups(keyword='java') | G19: O
D20: listGroups(category='technology') | H20: O
D21: listGroups(...) | I21: O
D22: getMyGroups(userId) | J22: O
D23: getGroupDetail(groupId, userId) | K23: O | M23: O
D24: getGroupDetail(99, userId) | L24: O
A26: Confirm | B26: Return
D27: Page of non-deleted groups ordered by newest | F27: O
D28: Only groups matching name / description / topics | G28: O
D29: Only groups of the category | H29: O
D30: Empty page returned | I30: O
D31: 2 groups returned | J31: O
D32: GroupResponse with membership state and member count | K32: O
B33: Exception
D34: ResourceNotFoundException: group not found | L34: O | M34: O
B35: Log message
A37: Result | B37: Type(N : Normal, A : Abnormal, B : Boundary) | F37: N | G37: N | H37: N | I37: B | J37: N | K37: N | L37: A | M37: A
B38: Passed/Failed | F38: P | G38: P | H38: P | I38: P | J38: P | K38: P | L38: P | M38: P
B39: Executed Date | F39: 46293 | G39: 46293 | H39: 46293 | I39: 46293 | J39: 46293 | K39: 46293 | L39: 46293 | M39: 46293
B40: Defect ID

Sheet FE-44
A2: Function Code | C2: FE-44 | F2: Function Name | L2: FE-44_Community Groups - Create, Update, Close/Reopen & Delete
A3: Created By | C3: AnNH | F3: Executed By | L3: TrietNH
A4: Lines of code | C4: 84 | F4: Lack of test cases | L4: =IF(Functions!E6<>"N/A",SUM(C4*Functions!E6/1000,-O7),"N/A") -> N/A
A5: Test requirement | C5: Create, update, close / reopen and delete a community group
A6: Passed | C6: Failed | F6: Untested | L6: N/A/B | O6: Total Test Cases
A7: =COUNTIF(F47:T47,"P") -> 13 | C7: =COUNTIF(F47:T47,"F") -> 0 | F7: =SUM(O7,-A7,-C7) -> 0 | L7: =COUNTIF(F46:T46,"N") -> 5 | M7: =COUNTIF(F46:T46,"A") -> 7 | N7: =COUNTIF(F46:T46,"B") -> 1 | O7: =COUNTA(F9:T9) -> 13
F9: UTCID01 | G9: UTCID02 | H9: UTCID03 | I9: UTCID04 | J9: UTCID05 | K9: UTCID06 | L9: UTCID07 | M9: UTCID08 | N9: UTCID09 | O9: UTCID10 | P9: UTCID11 | Q9: UTCID12 | R9: UTCID13
A10: Condition | B10: Precondition
D11: User exists | F11: O | G11: O | H11: O | I11: O
D12: Caller is OWNER | J12: O | O12: O | Q12: O
D13: Caller is MEMBER | K13: O
D14: Group is INACTIVE | L14: O
D15: Caller is OWNER; group ACTIVE | M15: O
D16: Caller is OWNER; group INACTIVE | N16: O
D17: Caller is ADMIN (not owner) | P17: O | R17: O
B18: Input
D19: CreateGroupRequest(name, description, category='technology', topics=[..]) | F19: O
D20: name with 200 characters | G20: O
D21: name with 201 characters | H21: O
D22: topics with 6 items | I22: O
D23: updateGroup(groupId, UpdateGroupRequest) | J23: O
D24: updateGroup(groupId, request) | K24: O | L24: O
D25: updateGroupStatus(groupId, INACTIVE) | M25: O | P25: O
D26: updateGroupStatus(groupId, ACTIVE) | N26: O
D27: updateGroupStatus(groupId, DELETED) | O27: O
D28: deleteGroup(groupId) | Q28: O | R28: O
A30: Confirm | B30: Return
D31: Group saved ACTIVE; creator becomes OWNER member | F31: O
D32: Group created | G32: O
D33: Group information updated | J33: O
D34: Group becomes INACTIVE | M34: O
D35: Group becomes ACTIVE | N35: O
D36: Group soft-deleted | Q36: O
B37: Exception
D38: Validation error: name must not exceed 200 characters | H38: O
D39: Validation error: at most 5 topics | I39: O
D40: ForbiddenException: Bạn không có quyền quản lý hội nhóm này. | K40: O
D41: BadRequestException: Hội nhóm đang tạm ngừng hoạt động. | L41: O
D42: BadRequestException: only INACTIVE or ACTIVE allowed | O42: O
D43: ForbiddenException: Chỉ chủ sở hữu hội nhóm mới có quyền thực hiện thao tác này. | P43: O | R43: O
B44: Log message
A46: Result | B46: Type(N : Normal, A : Abnormal, B : Boundary) | F46: N | G46: B | H46: A | I46: A | J46: N | K46: A | L46: A | M46: N | N46: N | O46: A | P46: A | Q46: N | R46: A
B47: Passed/Failed | F47: P | G47: P | H47: P | I47: P | J47: P | K47: P | L47: P | M47: P | N47: P | O47: P | P47: P | Q47: P | R47: P
B48: Executed Date | F48: 46293 | G48: 46293 | H48: 46293 | I48: 46293 | J48: 46293 | K48: 46293 | L48: 46293 | M48: 46293 | N48: 46293 | O48: 46293 | P48: 46293 | Q48: 46293 | R48: 46293
B49: Defect ID

Sheet FE-45
A2: Function Code | C2: FE-45 | F2: Function Name | L2: FE-45_Community Groups - Join, Leave & Handle Join Requests
A3: Created By | C3: AnNH | F3: Executed By | L3: HieuPT
A4: Lines of code | C4: 178 | F4: Lack of test cases | L4: =IF(Functions!E6<>"N/A",SUM(C4*Functions!E6/1000,-O7),"N/A") -> N/A
A5: Test requirement | C5: Join / leave a group and approve or reject join requests
A6: Passed | C6: Failed | F6: Untested | L6: N/A/B | O6: Total Test Cases
A7: =COUNTIF(F48:T48,"P") -> 12 | C7: =COUNTIF(F48:T48,"F") -> 0 | F7: =SUM(O7,-A7,-C7) -> 0 | L7: =COUNTIF(F47:T47,"N") -> 7 | M7: =COUNTIF(F47:T47,"A") -> 5 | N7: =COUNTIF(F47:T47,"B") -> 0 | O7: =COUNTA(F9:T9) -> 12
F9: UTCID01 | G9: UTCID02 | H9: UTCID03 | I9: UTCID04 | J9: UTCID05 | K9: UTCID06 | L9: UTCID07 | M9: UTCID08 | N9: UTCID09 | O9: UTCID10 | P9: UTCID11 | Q9: UTCID12
A10: Condition | B10: Precondition
D11: Group is public and ACTIVE; user not a member | F11: O
D12: Group is private and ACTIVE | G12: O
D13: User is already an ACTIVE member | H13: O
D14: User has a PENDING request | I14: O
D15: Group is INACTIVE | J15: O
D16: User previously left the group | K16: O
D17: User is MEMBER | L17: O
D18: User is OWNER | M18: O
D19: Caller is OWNER; pending requests exist | N19: O
D20: Caller is OWNER; request pending | O20: O
D21: Caller is ADMIN; request pending | P21: O
D22: Caller is MEMBER | Q22: O
B23: Input
D24: joinGroup(groupId, userId) | F24: O | G24: O | H24: O | I24: O | J24: O | K24: O
D25: leaveGroup(groupId, userId) | L25: O | M25: O
D26: getJoinRequests(groupId, ownerId) | N26: O
D27: handleJoinRequest(groupId, requestId, approve=true) | O27: O
D28: handleJoinRequest(groupId, requestId, approve=false) | P28: O
D29: handleJoinRequest(groupId, requestId, true) | Q29: O
A31: Confirm | B31: Return
D32: Membership ACTIVE with role MEMBER; member count +1 | F32: O
D33: Membership PENDING; member count unchanged | G33: O
D34: Membership reactivated | K34: O
D35: Membership set to LEFT; member count -1 | L35: O
D36: List of pending requests | N36: O
D37: Member becomes ACTIVE; applicant notified | O37: O
D38: Request REJECTED | P38: O
B39: Exception
D40: ConflictException: Bạn đã là thành viên của hội nhóm này. | H40: O
D41: ConflictException: pending request exists | I41: O
D42: BadRequestException: Hội nhóm đang tạm ngừng hoạt động. | J42: O
D43: BadRequestException: owner cannot leave the group | M43: O
D44: ForbiddenException: Bạn không có quyền quản lý hội nhóm này. | Q44: O
B45: Log message
A47: Result | B47: Type(N : Normal, A : Abnormal, B : Boundary) | F47: N | G47: N | H47: A | I47: A | J47: A | K47: N | L47: N | M47: A | N47: N | O47: N | P47: N | Q47: A
B48: Passed/Failed | F48: P | G48: P | H48: P | I48: P | J48: P | K48: P | L48: P | M48: P | N48: P | O48: P | P48: P | Q48: P
B49: Executed Date | F49: 46293 | G49: 46293 | H49: 46293 | I49: 46293 | J49: 46293 | K49: 46293 | L49: 46293 | M49: 46293 | N49: 46293 | O49: 46293 | P49: 46293 | Q49: 46293
B50: Defect ID

Sheet FE-46
A2: Function Code | C2: FE-46 | F2: Function Name | L2: FE-46_Community Groups - Members & Roles
A3: Created By | C3: AnNH | F3: Executed By | L3: HuyLTN
A4: Lines of code | C4: 97 | F4: Lack of test cases | L4: =IF(Functions!E6<>"N/A",SUM(C4*Functions!E6/1000,-O7),"N/A") -> N/A
A5: Test requirement | C5: View members, remove a member and change member roles
A6: Passed | C6: Failed | F6: Untested | L6: N/A/B | O6: Total Test Cases
A7: =COUNTIF(F41:T41,"P") -> 9 | C7: =COUNTIF(F41:T41,"F") -> 0 | F7: =SUM(O7,-A7,-C7) -> 0 | L7: =COUNTIF(F40:T40,"N") -> 5 | M7: =COUNTIF(F40:T40,"A") -> 4 | N7: =COUNTIF(F40:T40,"B") -> 0 | O7: =COUNTA(F9:T9) -> 9
F9: UTCID01 | G9: UTCID02 | H9: UTCID03 | I9: UTCID04 | J9: UTCID05 | K9: UTCID06 | L9: UTCID07 | M9: UTCID08 | N9: UTCID09
A10: Condition | B10: Precondition
D11: Group has 3 members | F11: O
D12: Caller is OWNER; target is MEMBER | G12: O
D13: Caller is ADMIN; target is MEMBER | H13: O
D14: Caller is ADMIN; target is OWNER | I14: O
D15: Caller is MEMBER | J15: O
D16: Caller is OWNER; group has no ADMIN | K16: O
